Workbook
Name クライテリア本文: 'アセスメント'!$A$2:$E$330

Sheet 概要

Sheet アセスメント
E1: =progressbar!E9 -> progress :□□□□□□□□□□□□□□□□□□□□ 0/320 | F1: 未入力の項目または入力エラーの項目があります。
B2: theme | C2: category | D2: point of view | E2: criterion | F2: yes | G2: no | H2: but | I2: remarks
A3: =criteria!A2 -> 1 | B3: =criteria!B2 -> TEAM-1-1 | C3: =criteria!E2 -> チーム構成と権限委譲 | D3: =criteria!D2 -> メトリクスの計測 | E3: =hyperlink(vlookup(B3,link!$B$2:$D$332,3,FALSE),criteria!F2) -> システムを開発する１チームの構成人数は、3人以上10人以下か。（ピザ2枚ルール） | F3: FALSE | G3: FALSE | H3: FALSE
A4: =criteria!A3 -> 2 | B4: =criteria!B3 -> TEAM-1-2 | D4: =criteria!D3 -> 学習と改善 | E4: =hyperlink(vlookup(B4,link!$B$2:$D$332,3,FALSE),criteria!F3) -> ある特定の人物に属人化した仕事を洗い出し、減らしていく仕組みがチームにあるか。 | F4: FALSE | G4: FALSE | H4: FALSE
A5: =criteria!A4 -> 3 | B5: =criteria!B4 -> TEAM-1-3 | D5: =criteria!D4 -> プラクティス | E5: =hyperlink(vlookup(B5,link!$B$2:$D$332,3,FALSE),criteria!F4) -> チームとチームメンバーの権限について、RACI図やデリゲーションポーカーなどによって、可視化され共有されているか。 | F5: FALSE | G5: FALSE | H5: FALSE
A6: =criteria!A5 -> 4 | B6: =criteria!B5 -> TEAM-1-4 | D6: =criteria!D5 -> プラクティス | E6: =hyperlink(vlookup(B6,link!$B$2:$D$332,3,FALSE),criteria!F5) -> チームは価値提供をするのに必要な全職能のメンバーで構成されているか。(フィーチャーチーム) | F6: FALSE | G6: FALSE | H6: FALSE
A7: =criteria!A6 -> 5 | B7: =criteria!B6 -> TEAM-1-5 | D7: =criteria!D6 -> プラクティス | E7: =hyperlink(vlookup(B7,link!$B$2:$D$332,3,FALSE),criteria!F6) -> チームおよびチームリーダーは、チームのミッションのために必要な外部のリソースを調達するための予算や権限をもっているか。 | F7: FALSE | G7: FALSE | H7: FALSE
A8: =criteria!A7 -> 6 | B8: =criteria!B7 -> TEAM-1-6 | D8: =criteria!D7 -> アンチパターン | E8: =hyperlink(vlookup(B8,link!$B$2:$D$332,3,FALSE),criteria!F7) -> チームという単位は存在するが、メンバーのそれぞれのやっている仕事の内容をよく知らないし、代わりにやることもできない。 | F8: FALSE | G8: FALSE | H8: FALSE
A9: =criteria!A8 -> 7 | B9: =criteria!B8 -> TEAM-1-7 | D9: =criteria!D8 -> アンチパターン | E9: =hyperlink(vlookup(B9,link!$B$2:$D$332,3,FALSE),criteria!F8) -> チームリーダーが複数のチームやプロジェクトを兼務しており、自チームのためにすべての時間を使うことができない。 | F9: FALSE | G9: FALSE | H9: FALSE
A10: =criteria!A9 -> 8 | B10: =criteria!B9 -> TEAM-1-8 | D10: =criteria!D9 -> アンチパターン | E10: =hyperlink(vlookup(B10,link!$B$2:$D$332,3,FALSE),criteria!F9) -> チームリーダーがメンバーに権限委譲できておらず、ボトルネックになっている。 | F10: FALSE | G10: FALSE | H10: FALSE
A11: =criteria!A10 -> 9 | B11: =criteria!B10 -> TEAM-2-1 | C11: =criteria!E10 -> チームビルディング | D11: =criteria!D10 -> メトリクスの計測 | E11: =hyperlink(vlookup(B11,link!$B$2:$D$332,3,FALSE),criteria!F10) -> チームは少なくとも半年以上継続して存在しているか。 | F11: FALSE | G11: FALSE | H11: FALSE
A12: =criteria!A11 -> 10 | B12: =criteria!B11 -> TEAM-2-2 | D12: =criteria!D11 -> 学習と改善 | E12: =hyperlink(vlookup(B12,link!$B$2:$D$332,3,FALSE),criteria!F11) -> チームは月に一度以上の頻度で仕事のふりかえりをおこなっており、その際にプロジェクト憲章またはインセプションデッキを見返して目的を再確認しているか。 | F12: FALSE | G12: FALSE | H12: FALSE
A13: =criteria!A12 -> 11 | B13: =criteria!B12 -> TEAM-2-3 | D13: =criteria!D12 -> プラクティス | E13: =hyperlink(vlookup(B13,link!$B$2:$D$332,3,FALSE),criteria!F12) -> インセプションデッキまたはプロジェクト憲章を作成し、チームの存在理由についてチーム全員が把握しているか。 | F13: FALSE | G13: FALSE | H13: FALSE
A14: =criteria!A13 -> 12 | B14: =criteria!B13 -> TEAM-2-4 | D14: =criteria!D13 -> プラクティス | E14: =hyperlink(vlookup(B14,link!$B$2:$D$332,3,FALSE),criteria!F13) -> 新しくチームに参画するメンバー用のオンボーディング・デック（チームの一員として働き始めるための、価値観・実務・スキル・相互理解のための明文化されたドキュメント集）が存在するか。 | F14: FALSE | G14: FALSE | H14: FALSE
A15: =criteria!A14 -> 13 | B15: =criteria!B14 -> TEAM-2-5 | D15: =criteria!D14 -> プラクティス | E15: =hyperlink(vlookup(B15,link!$B$2:$D$332,3,FALSE),criteria!F14) -> チームメンバー全員で定期的にカジュアルにコミュニケーションをとる場がある（ランチ、ディナー、レクレーション等） | F15: FALSE | G15: FALSE | H15: FALSE
A16: =criteria!A15 -> 14 | B16: =criteria!B15 -> TEAM-2-6 | D16: =criteria!D15 -> アンチパターン | E16: =hyperlink(vlookup(B16,link!$B$2:$D$332,3,FALSE),criteria!F15) -> オンボーディングプログラムが、文章を読むだけのものになっており、ハンズオンやミッション理解の伴わない形骸化したものになっている。 | F16: FALSE | G16: FALSE | H16: FALSE
A17: =criteria!A16 -> 15 | B17: =criteria!B16 -> TEAM-2-7 | D17: =criteria!D16 -> アンチパターン | E17: =hyperlink(vlookup(B17,link!$B$2:$D$332,3,FALSE),criteria!F16) -> 1年以上チームのやることが変わっておらず、チームメンバーも固定されている。 | F17: FALSE | G17: FALSE | H17: FALSE
A18: =criteria!A17 -> 16 | B18: =criteria!B17 -> TEAM-2-8 | D18: =criteria!D17 -> アンチパターン | E18: =hyperlink(vlookup(B18,link!$B$2:$D$332,3,FALSE),criteria!F17) -> チーム内でチームミッションの改善に関係する議論がどんな理由であれ発生していない。 | F18: FALSE | G18: FALSE | H18: FALSE
A19: =criteria!A18 -> 17 | B19: =criteria!B18 -> TEAM-3-1 | C19: =criteria!E18 -> 心理的安全性 | D19: =criteria!D18 -> メトリクスの計測 | E19: =hyperlink(vlookup(B19,link!$B$2:$D$332,3,FALSE),criteria!F18) -> チームメンバーの心理的安全性を測る指標があり、定期的に計測しているか。 | F19: FALSE | G19: FALSE | H19: FALSE
A20: =criteria!A19 -> 18 | B20: =criteria!B19 -> TEAM-3-2 | D20: =criteria!D19 -> 学習と改善 | E20: =hyperlink(vlookup(B20,link!$B$2:$D$332,3,FALSE),criteria!F19) -> 1on1や、落ち着いた場面でのカジュアルな雑談を含む直接業務に関わらないキャリアやタスクの壁打ちを、月に1度程度は実施しているか。 | F20: FALSE | G20: FALSE | H20: FALSE
A21: =criteria!A20 -> 19 | B21: =criteria!B20 -> TEAM-3-3 | D21: =criteria!D20 -> プラクティス | E21: =hyperlink(vlookup(B21,link!$B$2:$D$332,3,FALSE),criteria!F20) -> チームメンバーの行動/発言を明示的に承認行為をおこなう習慣があるか。（成果ではなく行動したこと自体に対して、拍手する・感謝を述べるなど） | F21: FALSE | G21: FALSE | H21: FALSE
A22: =criteria!A21 -> 20 | B22: =criteria!B21 -> TEAM-3-4 | D22: =criteria!D21 -> プラクティス | E22: =hyperlink(vlookup(B22,link!$B$2:$D$332,3,FALSE),criteria!F21) -> チームメンバー間で挨拶をしたり、雑談をする習慣はあるか。 | F22: FALSE | G22: FALSE | H22: FALSE
A23: =criteria!A22 -> 21 | B23: =criteria!B22 -> TEAM-3-5 | D23: =criteria!D22 -> プラクティス | E23: =hyperlink(vlookup(B23,link!$B$2:$D$332,3,FALSE),criteria!F22) -> チームの不安や不満などを可視化し、吸い上げるための仕組みを持っているか。 | F23: FALSE | G23: FALSE | H23: FALSE
A24: =criteria!A23 -> 22 | B24: =criteria!B23 -> TEAM-3-6 | D24: =criteria!D23 -> アンチパターン | E24: =hyperlink(vlookup(B24,link!$B$2:$D$332,3,FALSE),criteria!F23) -> ミッションや共通のゴール設定をしないまま意見を集め、課題のためというよりも個人のための意見しか出てこない状況になっている。 | F24: FALSE | G24: FALSE | H24: FALSE
A25: =criteria!A24 -> 23 | B25: =criteria!B24 -> TEAM-3-7 | D25: =criteria!D24 -> アンチパターン | E25: =hyperlink(vlookup(B25,link!$B$2:$D$332,3,FALSE),criteria!F24) -> 心理的安全性を仲の良さと捉えて、事業のための意見ではなく、仲良くすることが目的化しているため、意見を封殺してしまう。 | F25: FALSE | G25: FALSE | H25: FALSE
A26: =criteria!A25 -> 24 | B26: =criteria!B25 -> TEAM-3-8 | D26: =criteria!D25 -> アンチパターン | E26: =hyperlink(vlookup(B26,link!$B$2:$D$332,3,FALSE),criteria!F25) -> 事業目標や納期目標に対して、威圧的なマネジメントや権威的な命令を繰り返したことで、意見が出てこない状況になっている。 | F26: FALSE | G26: FALSE | H26: FALSE
A27: =criteria!A26 -> 25 | B27: =criteria!B26 -> TEAM-4-1 | C27: =criteria!E26 -> タスクマネジメント | D27: =criteria!D26 -> メトリクスの計測 | E27: =hyperlink(vlookup(B27,link!$B$2:$D$332,3,FALSE),criteria!F26) -> アイデアレベルの要望や構想から、要件に落ちるまでのリードタイムは計測されているか。 | F27: FALSE | G27: FALSE | H27: FALSE
A28: =criteria!A27 -> 26 | B28: =criteria!B27 -> TEAM-4-2 | D28: =criteria!D27 -> 学習と改善 | E28: =hyperlink(vlookup(B28,link!$B$2:$D$332,3,FALSE),criteria!F27) -> 仕事を始めるための定義と、完了するための定義はチームやステークホルダーで定期的に見直されているか。 | F28: FALSE | G28: FALSE | H28: FALSE
A29: =criteria!A28 -> 27 | B29: =criteria!B28 -> TEAM-4-3 | D29: =criteria!D28 -> プラクティス | E29: =hyperlink(vlookup(B29,link!$B$2:$D$332,3,FALSE),criteria!F28) -> 上長やステークホルダーを含め、共通のタスク管理ツールを利用しており、プロジェクトの状況を可視化したダッシュボードに常にアクセス可能か。 | F29: FALSE | G29: FALSE | H29: FALSE
A30: =criteria!A29 -> 28 | B30: =criteria!B29 -> TEAM-4-4 | D30: =criteria!D29 -> プラクティス | E30: =hyperlink(vlookup(B30,link!$B$2:$D$332,3,FALSE),criteria!F29) -> チームが仕事を始めるために必要な課題やタスクの粒度について、明文化されたフォーマットが存在するか。 | F30: FALSE | G30: FALSE | H30: FALSE
A31: =criteria!A30 -> 29 | B31: =criteria!B30 -> TEAM-4-5 | D31: =criteria!D30 -> プラクティス | E31: =hyperlink(vlookup(B31,link!$B$2:$D$332,3,FALSE),criteria!F30) -> チームのタスクに関して、「完成(完了)の定義(Definition of DONE)」が存在するか。 | F31: FALSE | G31: FALSE | H31: FALSE
A32: =criteria!A31 -> 30 | B32: =criteria!B31 -> TEAM-4-6 | D32: =criteria!D31 -> アンチパターン | E32: =hyperlink(vlookup(B32,link!$B$2:$D$332,3,FALSE),criteria!F31) -> 他部署からの依頼が明確なタスクツールではなく、担当者へのダイレクトメール/メッセージ/口頭など透明性のない形で行われている。 | F32: FALSE | G32: FALSE | H32: FALSE
A33: =criteria!A32 -> 31 | B33: =criteria!B32 -> TEAM-4-7 | D33: =criteria!D32 -> アンチパターン | E33: =hyperlink(vlookup(B33,link!$B$2:$D$332,3,FALSE),criteria!F32) -> どのチームタスクであるかが曖昧なとき、ボールが落ちないようにするための仕組みや文化が存在しない。 | F33: FALSE | G33: FALSE | H33: FALSE
A34: =criteria!A33 -> 32 | B34: =criteria!B33 -> TEAM-4-8 | D34: =criteria!D33 -> アンチパターン | E34: =hyperlink(vlookup(B34,link!$B$2:$D$332,3,FALSE),criteria!F33) -> どのチームタスクであるか曖昧な仕事が発生したあとに、事後検証（ポストモーテム）が行われず都度話し合いで解決している。 | F34: FALSE | G34: FALSE | H34: FALSE
A35: =criteria!A34 -> 33 | B35: =criteria!B34 -> TEAM-5-1 | C35: =criteria!E34 -> 透明性ある目標管理 | D35: =criteria!D34 -> メトリクスの計測 | E35: =hyperlink(vlookup(B35,link!$B$2:$D$332,3,FALSE),criteria!F34) -> １年後などのチームとプロダクトの目指す姿が、言語化され、いくつかの計測可能な指標により明晰化されているか。 | F35: FALSE | G35: FALSE | H35: FALSE
A36: =criteria!A35 -> 34 | B36: =criteria!B35 -> TEAM-5-2 | D36: =criteria!D35 -> 学習と改善 | E36: =hyperlink(vlookup(B36,link!$B$2:$D$332,3,FALSE),criteria!F35) -> 仮説的な目標に対して、うまくいかなかった際にチームとして「学んだこと」を言語化・他チームへ公開・学習しているか。 | F36: FALSE | G36: FALSE | H36: FALSE
A37: =criteria!A36 -> 35 | B37: =criteria!B36 -> TEAM-5-3 | D37: =criteria!D36 -> プラクティス | E37: =hyperlink(vlookup(B37,link!$B$2:$D$332,3,FALSE),criteria!F36) -> 四半期にフォーカスすべき目標が言語化され、いくつかの計測可能な指標によって明晰化されているか。 | F37: FALSE | G37: FALSE | H37: FALSE
A38: =criteria!A37 -> 36 | B38: =criteria!B37 -> TEAM-5-4 | D38: =criteria!D37 -> プラクティス | E38: =hyperlink(vlookup(B38,link!$B$2:$D$332,3,FALSE),criteria!F37) -> フォーカスすべき目標に対して、どのようにアプローチするのかの計画をチームで共有しているか。 | F38: FALSE | G38: FALSE | H38: FALSE
A39: =criteria!A38 -> 37 | B39: =criteria!B38 -> TEAM-5-5 | D39: =criteria!D38 -> プラクティス | E39: =hyperlink(vlookup(B39,link!$B$2:$D$332,3,FALSE),criteria!F38) -> ビジネス上、重要なマイルストーンとそのスケジュールをチームで常に共有し、その進捗を確認しているか。 | F39: FALSE | G39: FALSE | H39: FALSE
A40: =criteria!A39 -> 38 | B40: =criteria!B39 -> TEAM-5-6 | D40: =criteria!D39 -> アンチパターン | E40: =hyperlink(vlookup(B40,link!$B$2:$D$332,3,FALSE),criteria!F39) -> 目標管理が強く評価制度に結びついているため、ストレッチしたゴール設定をすることが難しくなっている。 | F40: FALSE | G40: FALSE | H40: FALSE
A41: =criteria!A40 -> 39 | B41: =criteria!B40 -> TEAM-5-7 | D41: =criteria!D40 -> アンチパターン | E41: =hyperlink(vlookup(B41,link!$B$2:$D$332,3,FALSE),criteria!F40) -> 目標項目の一部に、その達成手段が健全に行われているかをチェックするための目標(健全化指標)を立てていない。 | F41: FALSE | G41: FALSE | H41: FALSE
A42: =criteria!A41 -> 40 | B42: =criteria!B41 -> TEAM-5-8 | D42: =criteria!D41 -> アンチパターン | E42: =hyperlink(vlookup(B42,link!$B$2:$D$332,3,FALSE),criteria!F41) -> 目標が定量的でなく、第三者からみて達成度合いが不明確なものになっている。 | F42: FALSE | G42: FALSE | H42: FALSE
A43: =criteria!A42 -> 41 | B43: =criteria!B42 -> TEAM-6-1 | C43: =criteria!E42 -> 経験主義的な見積りと計画 | D43: =criteria!D42 -> メトリクスの計測 | E43: =hyperlink(vlookup(B43,link!$B$2:$D$332,3,FALSE),criteria!F42) -> チームのベロシティを把握しており、その分散値の変化を計測しているか。 | F43: FALSE | G43: FALSE | H43: FALSE
A44: =criteria!A43 -> 42 | B44: =criteria!B43 -> TEAM-6-2 | D44: =criteria!D43 -> 学習と改善 | E44: =hyperlink(vlookup(B44,link!$B$2:$D$332,3,FALSE),criteria!F43) -> 見積りと実績の履歴を元に、見積りの精度を向上させるための方法について定期的な学習/ふりかえりを行なっているか。 | F44: FALSE | G44: FALSE | H44: FALSE
A45: =criteria!A44 -> 43 | B45: =criteria!B44 -> TEAM-6-3 | D45: =criteria!D44 -> プラクティス | E45: =hyperlink(vlookup(B45,link!$B$2:$D$332,3,FALSE),criteria!F44) -> 見積りは、実際にその仕事を行う本人を含むチームの複数人で行われているか。 | F45: FALSE | G45: FALSE | H45: FALSE
A46: =criteria!A45 -> 44 | B46: =criteria!B45 -> TEAM-6-4 | D46: =criteria!D45 -> プラクティス | E46: =hyperlink(vlookup(B46,link!$B$2:$D$332,3,FALSE),criteria!F45) -> スケジュールがクリティカルな場合には当初から精密に、仮説検証や価値がクリティカルな場合には荒い粒度から段階的に詳細化するなどして、状況に応じて見積りや計画の方法を変えているか。 | F46: FALSE | G46: FALSE | H46: FALSE
A47: =criteria!A46 -> 45 | B47: =criteria!B46 -> TEAM-6-5 | D47: =criteria!D46 -> プラクティス | E47: =hyperlink(vlookup(B47,link!$B$2:$D$332,3,FALSE),criteria!F46) -> 相対見積もりの基準となる要件（ユーザーストーリー）が存在し、定期的にアップデートしているか。 | F47: FALSE | G47: FALSE | H47: FALSE
A48: =criteria!A47 -> 46 | B48: =criteria!B47 -> TEAM-6-6 | D48: =criteria!D47 -> アンチパターン | E48: =hyperlink(vlookup(B48,link!$B$2:$D$332,3,FALSE),criteria!F47) -> スケジュールのバッファ（緩衝期間）が全体計画に対して1/4以下しかもうけていない。 | F48: FALSE | G48: FALSE | H48: FALSE
A49: =criteria!A48 -> 47 | B49: =criteria!B48 -> TEAM-6-7 | D49: =criteria!D48 -> アンチパターン | E49: =hyperlink(vlookup(B49,link!$B$2:$D$332,3,FALSE),criteria!F48) -> 機能要件のバッファ(緩衝機能)を全体計画に対して設けられていない。(「必須な機能」と「あったらよい機能」が分類されず、曖昧になっている。) | F49: FALSE | G49: FALSE | H49: FALSE
A50: =criteria!A49 -> 48 | B50: =criteria!B49 -> TEAM-6-8 | D50: =criteria!D49 -> アンチパターン | E50: =hyperlink(vlookup(B50,link!$B$2:$D$332,3,FALSE),criteria!F49) -> 相対見積もりによって得られたベロシティの数値自体を、生産性の指標にしており、数値的なコミットメントや改善が要求されている。 | F50: FALSE | G50: FALSE | H50: FALSE
A51: =criteria!A50 -> 49 | B51: =criteria!B50 -> TEAM-7-1 | C51: =criteria!E50 -> ふりかえり習慣 | D51: =criteria!D50 -> メトリクスの計測 | E51: =hyperlink(vlookup(B51,link!$B$2:$D$332,3,FALSE),criteria!F50) -> ふりかえりのテーマごとに数字を集めたり計測するなどして、ファクトベースで議論できるようにしているか。 | F51: FALSE | G51: FALSE | H51: FALSE
A52: =criteria!A51 -> 50 | B52: =criteria!B51 -> TEAM-7-2 | D52: =criteria!D51 -> 学習と改善 | E52: =hyperlink(vlookup(B52,link!$B$2:$D$332,3,FALSE),criteria!F51) -> チームのメンバーは、チームで合意した1カ月以内のサイクルでふりかえりを実施しているか。 | F52: FALSE | G52: FALSE | H52: FALSE
A53: =criteria!A52 -> 51 | B53: =criteria!B52 -> TEAM-7-3 | D53: =criteria!D52 -> プラクティス | E53: =hyperlink(vlookup(B53,link!$B$2:$D$332,3,FALSE),criteria!F52) -> ふりかえりの場はチーム全員が参加しているか。 | F53: FALSE | G53: FALSE | H53: FALSE
A54: =criteria!A53 -> 52 | B54: =criteria!B53 -> TEAM-7-4 | D54: =criteria!D53 -> プラクティス | E54: =hyperlink(vlookup(B54,link!$B$2:$D$332,3,FALSE),criteria!F53) -> ふりかえりはテーマを定め、議論を行い次回のふりかえりまでに実行可能なタスクが切り出されているか | F54: FALSE | G54: FALSE | H54: FALSE
A55: =criteria!A54 -> 53 | B55: =criteria!B54 -> TEAM-7-5 | D55: =criteria!D54 -> プラクティス | E55: =hyperlink(vlookup(B55,link!$B$2:$D$332,3,FALSE),criteria!F54) -> ふりかえりにおいて前回のふりかえりで改善するために起案したタスクが実行されたか検証しているか | F55: FALSE | G55: FALSE | H55: FALSE
A56: =criteria!A55 -> 54 | B56: =criteria!B55 -> TEAM-7-6 | D56: =criteria!D55 -> アンチパターン | E56: =hyperlink(vlookup(B56,link!$B$2:$D$332,3,FALSE),criteria!F55) -> ふりかえりをしていたが、しばしば意見が出なかったため、ふりかえり自体をやめた。 | F56: FALSE | G56: FALSE | H56: FALSE
A57: =criteria!A56 -> 55 | B57: =criteria!B56 -> TEAM-7-7 | D57: =criteria!D56 -> アンチパターン | E57: =hyperlink(vlookup(B57,link!$B$2:$D$332,3,FALSE),criteria!F56) -> ふりかえるべきテーマに関しての、起きた出来事を時系列に事実関係を整理するなどの準備をせずにふりかえりをすすめている。 | F57: FALSE | G57: FALSE | H57: FALSE
A58: =criteria!A57 -> 56 | B58: =criteria!B57 -> TEAM-7-8 | D58: =criteria!D57 -> アンチパターン | E58: =hyperlink(vlookup(B58,link!$B$2:$D$332,3,FALSE),criteria!F57) -> ふりかえりに適切なファシリテーターがいない。 | F58: FALSE | G58: FALSE | H58: FALSE
A59: =criteria!A58 -> 57 | B59: =criteria!B58 -> TEAM-8-1 | C59: =criteria!E58 -> バリューストリーム最適化 | D59: =criteria!D58 -> メトリクスの計測 | E59: =hyperlink(vlookup(B59,link!$B$2:$D$332,3,FALSE),criteria!F58) -> チームのリードタイム、フロー効率性および各工程のサイクルタイムを継続的に計測しているか。(またはエンジニアリングインテリジェンスのサービスを利用している) | F59: FALSE | G59: FALSE | H59: FALSE
A60: =criteria!A59 -> 58 | B60: =criteria!B59 -> TEAM-8-2 | D60: =criteria!D59 -> 学習と改善 | E60: =hyperlink(vlookup(B60,link!$B$2:$D$332,3,FALSE),criteria!F59) -> チームのバリューストリームマッピングを作成し、繰り返しボトルネックを把握しながら自動化と学習を繰り返しているか。 | F60: FALSE | G60: FALSE | H60: FALSE
A61: =criteria!A60 -> 59 | B61: =criteria!B60 -> TEAM-8-3 | D61: =criteria!D60 -> プラクティス | E61: =hyperlink(vlookup(B61,link!$B$2:$D$332,3,FALSE),criteria!F60) -> バリューストリーム改善のために、開発リソースの10%以上を継続的に確保しているか。 | F61: FALSE | G61: FALSE | H61: FALSE
A62: =criteria!A61 -> 60 | B62: =criteria!B61 -> TEAM-8-4 | D62: =criteria!D61 -> プラクティス | E62: =hyperlink(vlookup(B62,link!$B$2:$D$332,3,FALSE),criteria!F61) -> 設定ファイルや一部のソースコードに対して、エンジニアでなくても必要に応じて修正のためのPull Request(Merge Request)を投げることがあるか。 | F62: FALSE | G62: FALSE | H62: FALSE
A63: =criteria!A62 -> 61 | B63: =criteria!B62 -> TEAM-8-5 | D63: =criteria!D62 -> プラクティス | E63: =hyperlink(vlookup(B63,link!$B$2:$D$332,3,FALSE),criteria!F62) -> ペアプログラミング/モブプログラミングを実施しているか。 | F63: FALSE | G63: FALSE | H63: FALSE
A64: =criteria!A63 -> 62 | B64: =criteria!B63 -> TEAM-8-6 | D64: =criteria!D63 -> アンチパターン | E64: =hyperlink(vlookup(B64,link!$B$2:$D$332,3,FALSE),criteria!F63) -> 属人的なタスクがある状態を効率的だと解釈して改善をしない。 | F64: FALSE | G64: FALSE | H64: FALSE
A65: =criteria!A64 -> 63 | B65: =criteria!B64 -> TEAM-8-7 | D65: =criteria!D64 -> アンチパターン | E65: =hyperlink(vlookup(B65,link!$B$2:$D$332,3,FALSE),criteria!F64) -> フロー効率性などの数値指標に囚われすぎて、全体の効率が悪化するなど価値提供に結びつかない状態である。 | F65: FALSE | G65: FALSE | H65: FALSE
A66: =criteria!A65 -> 64 | B66: =criteria!B65 -> TEAM-8-8 | D66: =criteria!D65 -> アンチパターン | E66: =hyperlink(vlookup(B66,link!$B$2:$D$332,3,FALSE),criteria!F65) -> 数値改善のために簡単で予測可能な仕事ばかりを引き受け、難しめのタスクを引き受けない。 | F66: FALSE | G66: FALSE | H66: FALSE
A67: =criteria!A66 -> 65 | B67: =criteria!B66 -> SYSTEM-1-1 | C67: =criteria!E66 -> バージョン管理 | D67: =criteria!D66 -> メトリクスの計測 | E67: =hyperlink(vlookup(B67,link!$B$2:$D$332,3,FALSE),criteria!F66) -> バージョン管理システムの履歴情報(Code Churn)の分析をもとにバグ予測や品質上の問題を指摘するツールを導入し、継続的に改善しているか。 | F67: FALSE | G67: FALSE | H67: FALSE
A68: =criteria!A67 -> 66 | B68: =criteria!B67 -> SYSTEM-1-2 | D68: =criteria!D67 -> 学習と改善 | E68: =hyperlink(vlookup(B68,link!$B$2:$D$332,3,FALSE),criteria!F67) -> 明文化されたブランチ戦略が存在するか。そして、それは守られているか。 | F68: FALSE | G68: FALSE | H68: FALSE
A69: =criteria!A68 -> 67 | B69: =criteria!B68 -> SYSTEM-1-3 | D69: =criteria!D68 -> プラクティス | E69: =hyperlink(vlookup(B69,link!$B$2:$D$332,3,FALSE),criteria!F68) -> すべてのアプリケーションコードをGit/GitHubなどのバージョン管理システムで自社管理しているか。（権利を有する全てのソースコードについて、自社がアカウントを管理する統一のバージョン管理システムで扱っているか） | F69: FALSE | G69: FALSE | H69: FALSE
A70: =criteria!A69 -> 68 | B70: =criteria!B69 -> SYSTEM-1-4 | D70: =criteria!D69 -> プラクティス | E70: =hyperlink(vlookup(B70,link!$B$2:$D$332,3,FALSE),criteria!F69) -> インフラ構成とシステム要素のプロビジョニングをソースコードとして実行可能な形式にした上で、バージョン管理システムで管理しているか。（Infrastructure as Code） | F70: FALSE | G70: FALSE | H70: FALSE
A71: =criteria!A70 -> 69 | B71: =criteria!B70 -> SYSTEM-1-5 | D71: =criteria!D70 -> プラクティス | E71: =hyperlink(vlookup(B71,link!$B$2:$D$332,3,FALSE),criteria!F70) -> 統合テスト/デプロイメントの自動化に関わるソースコードをアプリケーションコードと同一のバージョン管理システムで管理しているか。 | F71: FALSE | G71: FALSE | H71: FALSE
A72: =criteria!A71 -> 70 | B72: =criteria!B71 -> SYSTEM-1-6 | D72: =criteria!D71 -> アンチパターン | E72: =hyperlink(vlookup(B72,link!$B$2:$D$332,3,FALSE),criteria!F71) -> ソースコード自体のセキュリティレベルを高く設定しており、開発支援系SaaSの利用を禁止している。 | F72: FALSE | G72: FALSE | H72: FALSE
A73: =criteria!A72 -> 71 | B73: =criteria!B72 -> SYSTEM-1-7 | D73: =criteria!D72 -> アンチパターン | E73: =hyperlink(vlookup(B73,link!$B$2:$D$332,3,FALSE),criteria!F72) -> バージョン管理システムが複数存在していたり、１つのツールからすべての履歴を閲覧できないなど、中途半端な状態のままになっていないか。 | F73: FALSE | G73: FALSE | H73: FALSE
A74: =criteria!A73 -> 72 | B74: =criteria!B73 -> SYSTEM-1-8 | D74: =criteria!D73 -> アンチパターン | E74: =hyperlink(vlookup(B74,link!$B$2:$D$332,3,FALSE),criteria!F73) -> システムのソースコードの閲覧を関連するエンジニアのみに限定している。（別チームのエンジニアや他のステークホルダーが閲覧できない。） | F74: FALSE | G74: FALSE | H74: FALSE
A75: =criteria!A74 -> 73 | B75: =criteria!B74 -> SYSTEM-2-1 | C75: =criteria!E74 -> ソースコードの明確さ | D75: =criteria!D74 -> メトリクスの計測 | E75: =hyperlink(vlookup(B75,link!$B$2:$D$332,3,FALSE),criteria!F74) -> アプリケーションコードの循環的複雑度などのメトリクスを、ツール/サービスを用いて継続的に計測しているか。 | F75: FALSE | G75: FALSE | H75: FALSE
A76: =criteria!A75 -> 74 | B76: =criteria!B75 -> SYSTEM-2-2 | D76: =criteria!D75 -> 学習と改善 | E76: =hyperlink(vlookup(B76,link!$B$2:$D$332,3,FALSE),criteria!F75) -> デッドコードを四半期以上のサイクルで定期的に棚卸しし、削除や分解をしているか。 | F76: FALSE | G76: FALSE | H76: FALSE
A77: =criteria!A76 -> 75 | B77: =criteria!B76 -> SYSTEM-2-3 | D77: =criteria!D76 -> プラクティス | E77: =hyperlink(vlookup(B77,link!$B$2:$D$332,3,FALSE),criteria!F76) -> コードレビューをする習慣や規則があり、本番用ブランチ(master / mainなど)へのマージはコードレビューを必須としているか。 | F77: FALSE | G77: FALSE | H77: FALSE
A78: =criteria!A77 -> 76 | B78: =criteria!B77 -> SYSTEM-2-4 | D78: =criteria!D77 -> プラクティス | E78: =hyperlink(vlookup(B78,link!$B$2:$D$332,3,FALSE),criteria!F77) -> 明文化されているコードレビューガイドラインが存在するか。 | F78: FALSE | G78: FALSE | H78: FALSE
A79: =criteria!A78 -> 77 | B79: =criteria!B78 -> SYSTEM-2-5 | D79: =criteria!D78 -> プラクティス | E79: =hyperlink(vlookup(B79,link!$B$2:$D$332,3,FALSE),criteria!F78) -> コードレビューガイドラインを満たさないコードを自動的に検出・補正する各種Linterやフォーマッタなどのツール群を整備しており、ソースコードを変更する誰もが使うことができるか。 | F79: FALSE | G79: FALSE | H79: FALSE
A80: =criteria!A79 -> 78 | B80: =criteria!B79 -> SYSTEM-2-6 | D80: =criteria!D79 -> アンチパターン | E80: =hyperlink(vlookup(B80,link!$B$2:$D$332,3,FALSE),criteria!F79) -> コードレビューをできる人物がチームの中におらず、レビュー待ちに1、2営業日がかかる。 | F80: FALSE | G80: FALSE | H80: FALSE
A81: =criteria!A80 -> 79 | B81: =criteria!B80 -> SYSTEM-2-7 | D81: =criteria!D80 -> アンチパターン | E81: =hyperlink(vlookup(B81,link!$B$2:$D$332,3,FALSE),criteria!F80) -> コードレビューガイドラインは１年以上メンテナンスされておらず、形骸化している。 | F81: FALSE | G81: FALSE | H81: FALSE
A82: =criteria!A81 -> 80 | B82: =criteria!B81 -> SYSTEM-2-8 | D82: =criteria!D81 -> アンチパターン | E82: =hyperlink(vlookup(B82,link!$B$2:$D$332,3,FALSE),criteria!F81) -> コードレビューガイドラインの多くの項目が、自動的なフォーマッタなどで統一・解決可能な些末な事柄である。 | F82: FALSE | G82: FALSE | H82: FALSE
A83: =criteria!A82 -> 81 | B83: =criteria!B82 -> SYSTEM-3-1 | C83: =criteria!E82 -> 継続的インテグレーション | D83: =criteria!D82 -> メトリクスの計測 | E83: =hyperlink(vlookup(B83,link!$B$2:$D$332,3,FALSE),criteria!F82) -> すべてのインテグレーションテストにかかる時間が計測されており、それは30分以内に完了するか。 | F83: FALSE | G83: FALSE | H83: FALSE
A84: =criteria!A83 -> 82 | B84: =criteria!B83 -> SYSTEM-3-2 | D84: =criteria!D83 -> 学習と改善 | E84: =hyperlink(vlookup(B84,link!$B$2:$D$332,3,FALSE),criteria!F83) -> テストカバレッジ基準や自動テストガイドラインを用意し、これらを継続的に改善するための工数がチームで割かれているか。 | F84: FALSE | G84: FALSE | H84: FALSE
A85: =criteria!A84 -> 83 | B85: =criteria!B84 -> SYSTEM-3-3 | D85: =criteria!D84 -> プラクティス | E85: =hyperlink(vlookup(B85,link!$B$2:$D$332,3,FALSE),criteria!F84) -> プロダクトの半分以上のモジュール/クラスファイルに対して、ユニットテストが存在しているか。 | F85: FALSE | G85: FALSE | H85: FALSE
A86: =criteria!A85 -> 84 | B86: =criteria!B85 -> SYSTEM-3-4 | D86: =criteria!D85 -> プラクティス | E86: =hyperlink(vlookup(B86,link!$B$2:$D$332,3,FALSE),criteria!F85) -> テスト用データやスタブ/モックなどを整備し、テストを書きやすくするための環境整備をしているか。 | F86: FALSE | G86: FALSE | H86: FALSE
A87: =criteria!A86 -> 85 | B87: =criteria!B86 -> SYSTEM-3-5 | D87: =criteria!D86 -> プラクティス | E87: =hyperlink(vlookup(B87,link!$B$2:$D$332,3,FALSE),criteria!F86) -> 継続的インテグレーション環境が存在し、開発者は開発ブランチの全テストをリソース調整することなく、自由に行うことができるか。 | F87: FALSE | G87: FALSE | H87: FALSE
A88: =criteria!A87 -> 86 | B88: =criteria!B87 -> SYSTEM-3-6 | D88: =criteria!D87 -> アンチパターン | E88: =hyperlink(vlookup(B88,link!$B$2:$D$332,3,FALSE),criteria!F87) -> 一部の人だけがテストを書き、一部の人はテストを書かないといったように自動テストを個々人の努力目標などになっている。 | F88: FALSE | G88: FALSE | H88: FALSE
A89: =criteria!A88 -> 87 | B89: =criteria!B88 -> SYSTEM-3-7 | D89: =criteria!D88 -> アンチパターン | E89: =hyperlink(vlookup(B89,link!$B$2:$D$332,3,FALSE),criteria!F88) -> テスト自体が複雑になって、長期間メンテナンスされていない。 | F89: FALSE | G89: FALSE | H89: FALSE
A90: =criteria!A89 -> 88 | B90: =criteria!B89 -> SYSTEM-3-8 | D90: =criteria!D89 -> アンチパターン | E90: =hyperlink(vlookup(B90,link!$B$2:$D$332,3,FALSE),criteria!F89) -> 自動テストが失敗したまま、そのコードが本番デプロイされることを許容している。 | F90: FALSE | G90: FALSE | H90: FALSE
A91: =criteria!A90 -> 89 | B91: =criteria!B90 -> SYSTEM-4-1 | C91: =criteria!E90 -> 継続的デプロイ | D91: =criteria!D90 -> メトリクスの計測 | E91: =hyperlink(vlookup(B91,link!$B$2:$D$332,3,FALSE),criteria!F90) -> デプロイ頻度とデプロイ成功率を継続的に測定しており、これらを改善することを目標管理しているか。 | F91: FALSE | G91: FALSE | H91: FALSE
A92: =criteria!A91 -> 90 | B92: =criteria!B91 -> SYSTEM-4-2 | D92: =criteria!D91 -> 学習と改善 | E92: =hyperlink(vlookup(B92,link!$B$2:$D$332,3,FALSE),criteria!F91) -> デプロイ時に社内のユーザーや開発者のみを対象もしくは、一部のサーバのみにサービスをリリースしてエラーがないかを確かめるカナリアリリースができるか。 | F92: FALSE | G92: FALSE | H92: FALSE
A93: =criteria!A92 -> 91 | B93: =criteria!B92 -> SYSTEM-4-3 | D93: =criteria!D92 -> プラクティス | E93: =hyperlink(vlookup(B93,link!$B$2:$D$332,3,FALSE),criteria!F92) -> デプロイ完了時、および構成変更時にインフラ構成に関する自動的なテスト(e2eのスモークテストおよびServerspecなどのインフラ環境テスト)を実行しているか。 | F93: FALSE | G93: FALSE | H93: FALSE
A94: =criteria!A93 -> 92 | B94: =criteria!B93 -> SYSTEM-4-4 | D94: =criteria!D93 -> プラクティス | E94: =hyperlink(vlookup(B94,link!$B$2:$D$332,3,FALSE),criteria!F93) -> ブルーグリーンデプロイメントができるか。（稼働中のサーバーを切り替えるのではなく、別環境にデプロイ作業をしてから本番の向き先を切り替えるデプロイ手法。） | F94: FALSE | G94: FALSE | H94: FALSE
A95: =criteria!A94 -> 93 | B95: =criteria!B94 -> SYSTEM-4-5 | D95: =criteria!D94 -> プラクティス | E95: =hyperlink(vlookup(B95,link!$B$2:$D$332,3,FALSE),criteria!F94) -> デプロイ作業を伴わず、一部の機能を安全にオフにしたり、オンにしたりできるか。( Feature Toggle /Soft Launch/ Dark launchなどの仕組みを導入・実装しているか。) | F95: FALSE | G95: FALSE | H95: FALSE
A96: =criteria!A95 -> 94 | B96: =criteria!B95 -> SYSTEM-4-6 | D96: =criteria!D95 -> アンチパターン | E96: =hyperlink(vlookup(B96,link!$B$2:$D$332,3,FALSE),criteria!F95) -> デプロイされたコードに問題が発生した際に、前のバージョンへの切り戻しを意思決定してから5分以内に切り戻すことができない。 | F96: FALSE | G96: FALSE | H96: FALSE
A97: =criteria!A96 -> 95 | B97: =criteria!B96 -> SYSTEM-4-7 | D97: =criteria!D96 -> アンチパターン | E97: =hyperlink(vlookup(B97,link!$B$2:$D$332,3,FALSE),criteria!F96) -> 開発者のメンバー自身が、権限を持つ人物の承認があっても、自分のコードを本番環境にデプロイできない。 | F97: FALSE | G97: FALSE | H97: FALSE
A98: =criteria!A97 -> 96 | B98: =criteria!B97 -> SYSTEM-4-8 | D98: =criteria!D97 -> アンチパターン | E98: =hyperlink(vlookup(B98,link!$B$2:$D$332,3,FALSE),criteria!F97) -> デプロイ工程が自動化されておらず、本番反映に1時間以上かかっていたり、特定の時間帯しかできないなどの制約事項がかかっている。 | F98: FALSE | G98: FALSE | H98: FALSE
A99: =criteria!A98 -> 97 | B99: =criteria!B98 -> SYSTEM-5-1 | C99: =criteria!E98 -> API駆動開発 | D99: =criteria!D98 -> メトリクスの計測 | E99: =hyperlink(vlookup(B99,link!$B$2:$D$332,3,FALSE),criteria!F98) -> 社内外のAPIの利用者にとってのユーザビリティについてヒアリング/アンケートを行い継続的な改善が行われているか。 | F99: FALSE | G99: FALSE | H99: FALSE
A100: =criteria!A99 -> 98 | B100: =criteria!B99 -> SYSTEM-5-2 | D100: =criteria!D99 -> 学習と改善 | E100: =hyperlink(vlookup(B100,link!$B$2:$D$332,3,FALSE),criteria!F99) -> 各APIについて、動作するインタラクティブなドキュメントや管理サービスを持っているか。 | F100: FALSE | G100: FALSE | H100: FALSE
...

Sheet 可視化
C1: 未入力の項目または入力エラーの項目があります。
A2: テーマ | B2: No | C2: カテゴリー | L2: 合計 | M2: カテゴリ | N2: 偏差値 | O2: レイティング
A3: チーム | B3: =category!B2 -> 1 | C3: =category!C2 -> チーム構成と権限委譲 | D3: =indirect("counting!L"& ((row()-3)*8 + COLUMN() -2)) -> - | E3: =indirect("counting!L"& ((row()-3)*8 + COLUMN() -2)) -> - | F3: =indirect("counting!L"& ((row()-3)*8 + COLUMN() -2)) -> - | G3: =indirect("counting!L"& ((row()-3)*8 + COLUMN() -2)) -> - | H3: =indirect("counting!L"& ((row()-3)*8 + COLUMN() -2)) -> - | I3: =indirect("counting!L"& ((row()-3)*8 + COLUMN() -2)) -> - | J3: =indirect("counting!L"& ((row()-3)*8 + COLUMN() -2)) -> - | K3: =indirect("counting!L"& ((row()-3)*8 + COLUMN() -2)) -> - | L3: =sum(D3:K3) -> 0 | M3: =sum(L3:L10) -> 0 | N3: =((M3-stats!B2)/stats!C2)*10+50 -> 7.4941452 | O3: =vlookup(N3,rating!$B$2:$D$13,3,TRUE) -> DD
B4: =category!B3 -> 2 | C4: =category!C3 -> チームビルディング | D4: =indirect("counting!L"& ((row()-3)*8 + COLUMN() -2)) -> - | E4: =indirect("counting!L"& ((row()-3)*8 + COLUMN() -2)) -> - | F4: =indirect("counting!L"& ((row()-3)*8 + COLUMN() -2)) -> - | G4: =indirect("counting!L"& ((row()-3)*8 + COLUMN() -2)) -> - | H4: =indirect("counting!L"& ((row()-3)*8 + COLUMN() -2)) -> - | I4: =indirect("counting!L"& ((row()-3)*8 + COLUMN() -2)) -> - | J4: =indirect("counting!L"& ((row()-3)*8 + COLUMN() -2)) -> - | K4: =indirect("counting!L"& ((row()-3)*8 + COLUMN() -2)) -> - | L4: =sum(D4:K4) -> 0
B5: =category!B4 -> 3 | C5: =category!C4 -> 心理的安全性 | D5: =indirect("counting!L"& ((row()-3)*8 + COLUMN() -2)) -> - | E5: =indirect("counting!L"& ((row()-3)*8 + COLUMN() -2)) -> - | F5: =indirect("counting!L"& ((row()-3)*8 + COLUMN() -2)) -> - | G5: =indirect("counting!L"& ((row()-3)*8 + COLUMN() -2)) -> - | H5: =indirect("counting!L"& ((row()-3)*8 + COLUMN() -2)) -> - | I5: =indirect("counting!L"& ((row()-3)*8 + COLUMN() -2)) -> - | J5: =indirect("counting!L"& ((row()-3)*8 + COLUMN() -2)) -> - | K5: =indirect("counting!L"& ((row()-3)*8 + COLUMN() -2)) -> - | L5: =sum(D5:K5) -> 0
B6: =category!B5 -> 4 | C6: =category!C5 -> タスクマネジメント | D6: =indirect("counting!L"& ((row()-3)*8 + COLUMN() -2)) -> - | E6: =indirect("counting!L"& ((row()-3)*8 + COLUMN() -2)) -> - | F6: =indirect("counting!L"& ((row()-3)*8 + COLUMN() -2)) -> - | G6: =indirect("counting!L"& ((row()-3)*8 + COLUMN() -2)) -> - | H6: =indirect("counting!L"& ((row()-3)*8 + COLUMN() -2)) -> - | I6: =indirect("counting!L"& ((row()-3)*8 + COLUMN() -2)) -> - | J6: =indirect("counting!L"& ((row()-3)*8 + COLUMN() -2)) -> - | K6: =indirect("counting!L"& ((row()-3)*8 + COLUMN() -2)) -> - | L6: =sum(D6:K6) -> 0
B7: =category!B6 -> 5 | C7: =category!C6 -> 透明性ある目標管理 | D7: =indirect("counting!L"& ((row()-3)*8 + COLUMN() -2)) -> - | E7: =indirect("counting!L"& ((row()-3)*8 + COLUMN() -2)) -> - | F7: =indirect("counting!L"& ((row()-3)*8 + COLUMN() -2)) -> - | G7: =indirect("counting!L"& ((row()-3)*8 + COLUMN() -2)) -> - | H7: =indirect("counting!L"& ((row()-3)*8 + COLUMN() -2)) -> - | I7: =indirect("counting!L"& ((row()-3)*8 + COLUMN() -2)) -> - | J7: =indirect("counting!L"& ((row()-3)*8 + COLUMN() -2)) -> - | K7: =indirect("counting!L"& ((row()-3)*8 + COLUMN() -2)) -> - | L7: =sum(D7:K7) -> 0
B8: =category!B7 -> 6 | C8: =category!C7 -> 経験主義的な見積りと計画 | D8: =indirect("counting!L"& ((row()-3)*8 + COLUMN() -2)) -> - | E8: =indirect("counting!L"& ((row()-3)*8 + COLUMN() -2)) -> - | F8: =indirect("counting!L"& ((row()-3)*8 + COLUMN() -2)) -> - | G8: =indirect("counting!L"& ((row()-3)*8 + COLUMN() -2)) -> - | H8: =indirect("counting!L"& ((row()-3)*8 + COLUMN() -2)) -> - | I8: =indirect("counting!L"& ((row()-3)*8 + COLUMN() -2)) -> - | J8: =indirect("counting!L"& ((row()-3)*8 + COLUMN() -2)) -> - | K8: =indirect("counting!L"& ((row()-3)*8 + COLUMN() -2)) -> - | L8: =sum(D8:K8) -> 0
B9: =category!B8 -> 7 | C9: =category!C8 -> ふりかえり習慣 | D9: =indirect("counting!L"& ((row()-3)*8 + COLUMN() -2)) -> - | E9: =indirect("counting!L"& ((row()-3)*8 + COLUMN() -2)) -> - | F9: =indirect("counting!L"& ((row()-3)*8 + COLUMN() -2)) -> - | G9: =indirect("counting!L"& ((row()-3)*8 + COLUMN() -2)) -> - | H9: =indirect("counting!L"& ((row()-3)*8 + COLUMN() -2)) -> - | I9: =indirect("counting!L"& ((row()-3)*8 + COLUMN() -2)) -> - | J9: =indirect("counting!L"& ((row()-3)*8 + COLUMN() -2)) -> - | K9: =indirect("counting!L"& ((row()-3)*8 + COLUMN() -2)) -> - | L9: =sum(D9:K9) -> 0
B10: =category!B9 -> 8 | C10: =category!C9 -> バリューストリーム最適化 | D10: =indirect("counting!L"& ((row()-3)*8 + COLUMN() -2)) -> - | E10: =indirect("counting!L"& ((row()-3)*8 + COLUMN() -2)) -> - | F10: =indirect("counting!L"& ((row()-3)*8 + COLUMN() -2)) -> - | G10: =indirect("counting!L"& ((row()-3)*8 + COLUMN() -2)) -> - | H10: =indirect("counting!L"& ((row()-3)*8 + COLUMN() -2)) -> - | I10: =indirect("counting!L"& ((row()-3)*8 + COLUMN() -2)) -> - | J10: =indirect("counting!L"& ((row()-3)*8 + COLUMN() -2)) -> - | K10: =indirect("counting!L"& ((row()-3)*8 + COLUMN() -2)) -> - | L10: =sum(D10:K10) -> 0
A11: システム | B11: =category!B10 -> 1 | C11: =category!C10 -> バージョン管理 | D11: =indirect("counting!L"& ((row()-3)*8 + COLUMN() -2)) -> - | E11: =indirect("counting!L"& ((row()-3)*8 + COLUMN() -2)) -> - | F11: =indirect("counting!L"& ((row()-3)*8 + COLUMN() -2)) -> - | G11: =indirect("counting!L"& ((row()-3)*8 + COLUMN() -2)) -> - | H11: =indirect("counting!L"& ((row()-3)*8 + COLUMN() -2)) -> - | I11: =indirect("counting!L"& ((row()-3)*8 + COLUMN() -2)) -> - | J11: =indirect("counting!L"& ((row()-3)*8 + COLUMN() -2)) -> - | K11: =indirect("counting!L"& ((row()-3)*8 + COLUMN() -2)) -> - | L11: =sum(D11:K11) -> 0 | M11: =sum(L11:L18) -> 0 | N11: =((M11-stats!B3)/stats!C3)*10+50 -> 16.163142 | O11: =vlookup(N11,rating!$B$2:$D$13,3,TRUE) -> DD
B12: =category!B11 -> 2 | C12: =category!C11 -> ソースコードの明確さ | D12: =indirect("counting!L"& ((row()-3)*8 + COLUMN() -2)) -> - | E12: =indirect("counting!L"& ((row()-3)*8 + COLUMN() -2)) -> - | F12: =indirect("counting!L"& ((row()-3)*8 + COLUMN() -2)) -> - | G12: =indirect("counting!L"& ((row()-3)*8 + COLUMN() -2)) -> - | H12: =indirect("counting!L"& ((row()-3)*8 + COLUMN() -2)) -> - | I12: =indirect("counting!L"& ((row()-3)*8 + COLUMN() -2)) -> - | J12: =indirect("counting!L"& ((row()-3)*8 + COLUMN() -2)) -> - | K12: =indirect("counting!L"& ((row()-3)*8 + COLUMN() -2)) -> - | L12: =sum(D12:K12) -> 0
B13: =category!B12 -> 3 | C13: =category!C12 -> 継続的インテグレーション | D13: =indirect("counting!L"& ((row()-3)*8 + COLUMN() -2)) -> - | E13: =indirect("counting!L"& ((row()-3)*8 + COLUMN() -2)) -> - | F13: =indirect("counting!L"& ((row()-3)*8 + COLUMN() -2)) -> - | G13: =indirect("counting!L"& ((row()-3)*8 + COLUMN() -2)) -> - | H13: =indirect("counting!L"& ((row()-3)*8 + COLUMN() -2)) -> - | I13: =indirect("counting!L"& ((row()-3)*8 + COLUMN() -2)) -> - | J13: =indirect("counting!L"& ((row()-3)*8 + COLUMN() -2)) -> - | K13: =indirect("counting!L"& ((row()-3)*8 + COLUMN() -2)) -> - | L13: =sum(D13:K13) -> 0
B14: =category!B13 -> 4 | C14: =category!C13 -> 継続的デプロイ | D14: =indirect("counting!L"& ((row()-3)*8 + COLUMN() -2)) -> - | E14: =indirect("counting!L"& ((row()-3)*8 + COLUMN() -2)) -> - | F14: =indirect("counting!L"& ((row()-3)*8 + COLUMN() -2)) -> - | G14: =indirect("counting!L"& ((row()-3)*8 + COLUMN() -2)) -> - | H14: =indirect("counting!L"& ((row()-3)*8 + COLUMN() -2)) -> - | I14: =indirect("counting!L"& ((row()-3)*8 + COLUMN() -2)) -> - | J14: =indirect("counting!L"& ((row()-3)*8 + COLUMN() -2)) -> - | K14: =indirect("counting!L"& ((row()-3)*8 + COLUMN() -2)) -> - | L14: =sum(D14:K14) -> 0
B15: =category!B14 -> 5 | C15: =category!C14 -> API駆動開発 | D15: =indirect("counting!L"& ((row()-3)*8 + COLUMN() -2)) -> - | E15: =indirect("counting!L"& ((row()-3)*8 + COLUMN() -2)) -> - | F15: =indirect("counting!L"& ((row()-3)*8 + COLUMN() -2)) -> - | G15: =indirect("counting!L"& ((row()-3)*8 + COLUMN() -2)) -> - | H15: =indirect("counting!L"& ((row()-3)*8 + COLUMN() -2)) -> - | I15: =indirect("counting!L"& ((row()-3)*8 + COLUMN() -2)) -> - | J15: =indirect("counting!L"& ((row()-3)*8 + COLUMN() -2)) -> - | K15: =indirect("counting!L"& ((row()-3)*8 + COLUMN() -2)) -> - | L15: =sum(D15:K15) -> 0
B16: =category!B15 -> 6 | C16: =category!C15 -> 疎結合アーキテクチャ | D16: =indirect("counting!L"& ((row()-3)*8 + COLUMN() -2)) -> - | E16: =indirect("counting!L"& ((row()-3)*8 + COLUMN() -2)) -> - | F16: =indirect("counting!L"& ((row()-3)*8 + COLUMN() -2)) -> - | G16: =indirect("counting!L"& ((row()-3)*8 + COLUMN() -2)) -> - | H16: =indirect("counting!L"& ((row()-3)*8 + COLUMN() -2)) -> - | I16: =indirect("counting!L"& ((row()-3)*8 + COLUMN() -2)) -> - | J16: =indirect("counting!L"& ((row()-3)*8 + COLUMN() -2)) -> - | K16: =indirect("counting!L"& ((row()-3)*8 + COLUMN() -2)) -> - | L16: =sum(D16:K16) -> 0
B17: =category!B16 -> 7 | C17: =category!C16 -> システムモニタリング | D17: =indirect("counting!L"& ((row()-3)*8 + COLUMN() -2)) -> - | E17: =indirect("counting!L"& ((row()-3)*8 + COLUMN() -2)) -> - | F17: =indirect("counting!L"& ((row()-3)*8 + COLUMN() -2)) -> - | G17: =indirect("counting!L"& ((row()-3)*8 + COLUMN() -2)) -> - | H17: =indirect("counting!L"& ((row()-3)*8 + COLUMN() -2)) -> - | I17: =indirect("counting!L"& ((row()-3)*8 + COLUMN() -2)) -> - | J17: =indirect("counting!L"& ((row()-3)*8 + COLUMN() -2)) -> - | K17: =indirect("counting!L"& ((row()-3)*8 + COLUMN() -2)) -> - | L17: =sum(D17:K17) -> 0
B18: =category!B17 -> 8 | C18: =category!C17 -> セキュリティシフトレフト | D18: =indirect("counting!L"& ((row()-3)*8 + COLUMN() -2)) -> - | E18: =indirect("counting!L"& ((row()-3)*8 + COLUMN() -2)) -> - | F18: =indirect("counting!L"& ((row()-3)*8 + COLUMN() -2)) -> - | G18: =indirect("counting!L"& ((row()-3)*8 + COLUMN() -2)) -> - | H18: =indirect("counting!L"& ((row()-3)*8 + COLUMN() -2)) -> - | I18: =indirect("counting!L"& ((row()-3)*8 + COLUMN() -2)) -> - | J18: =indirect("counting!L"& ((row()-3)*8 + COLUMN() -2)) -> - | K18: =indirect("counting!L"& ((row()-3)*8 + COLUMN() -2)) -> - | L18: =sum(D18:K18) -> 0
A19: データ | B19: =category!B18 -> 1 | C19: =category!C18 -> 顧客接点のデジタル化 | D19: =indirect("counting!L"& ((row()-3)*8 + COLUMN() -2)) -> - | E19: =indirect("counting!L"& ((row()-3)*8 + COLUMN() -2)) -> - | F19: =indirect("counting!L"& ((row()-3)*8 + COLUMN() -2)) -> - | G19: =indirect("counting!L"& ((row()-3)*8 + COLUMN() -2)) -> - | H19: =indirect("counting!L"& ((row()-3)*8 + COLUMN() -2)) -> - | I19: =indirect("counting!L"& ((row()-3)*8 + COLUMN() -2)) -> - | J19: =indirect("counting!L"& ((row()-3)*8 + COLUMN() -2)) -> - | K19: =indirect("counting!L"& ((row()-3)*8 + COLUMN() -2)) -> - | L19: =sum(D19:K19) -> 0 | M19: =sum(L19:L26) -> 0 | N19: =((M19-stats!B4)/stats!C4)*10+50 -> 24.86535 | O19: =vlookup(N19,rating!$B$2:$D$13,3,TRUE) -> DD
B20: =category!B19 -> 2 | C20: =category!C19 -> 事業活動データの収集 | D20: =indirect("counting!L"& ((row()-3)*8 + COLUMN() -2)) -> - | E20: =indirect("counting!L"& ((row()-3)*8 + COLUMN() -2)) -> - | F20: =indirect("counting!L"& ((row()-3)*8 + COLUMN() -2)) -> - | G20: =indirect("counting!L"& ((row()-3)*8 + COLUMN() -2)) -> - | H20: =indirect("counting!L"& ((row()-3)*8 + COLUMN() -2)) -> - | I20: =indirect("counting!L"& ((row()-3)*8 + COLUMN() -2)) -> - | J20: =indirect("counting!L"& ((row()-3)*8 + COLUMN() -2)) -> - | K20: =indirect("counting!L"& ((row()-3)*8 + COLUMN() -2)) -> - | L20: =sum(D20:K20) -> 0
B21: =category!B20 -> 3 | C21: =category!C20 -> データ蓄積・分析基盤 | D21: =indirect("counting!L"& ((row()-3)*8 + COLUMN() -2)) -> - | E21: =indirect("counting!L"& ((row()-3)*8 + COLUMN() -2)) -> - | F21: =indirect("counting!L"& ((row()-3)*8 + COLUMN() -2)) -> - | G21: =indirect("counting!L"& ((row()-3)*8 + COLUMN() -2)) -> - | H21: =indirect("counting!L"& ((row()-3)*8 + COLUMN() -2)) -> - | I21: =indirect("counting!L"& ((row()-3)*8 + COLUMN() -2)) -> - | J21: =indirect("counting!L"& ((row()-3)*8 + COLUMN() -2)) -> - | K21: =indirect("counting!L"& ((row()-3)*8 + COLUMN() -2)) -> - | L21: =sum(D21:K21) -> 0
B22: =category!B21 -> 4 | C22: =category!C21 -> データ処理パイプライン | D22: =indirect("counting!L"& ((row()-3)*8 + COLUMN() -2)) -> - | E22: =indirect("counting!L"& ((row()-3)*8 + COLUMN() -2)) -> - | F22: =indirect("counting!L"& ((row()-3)*8 + COLUMN() -2)) -> - | G22: =indirect("counting!L"& ((row()-3)*8 + COLUMN() -2)) -> - | H22: =indirect("counting!L"& ((row()-3)*8 + COLUMN() -2)) -> - | I22: =indirect("counting!L"& ((row()-3)*8 + COLUMN() -2)) -> - | J22: =indirect("counting!L"& ((row()-3)*8 + COLUMN() -2)) -> - | K22: =indirect("counting!L"& ((row()-3)*8 + COLUMN() -2)) -> - | L22: =sum(D22:K22) -> 0
B23: =category!B22 -> 5 | C23: =category!C22 -> データ可視化とリテラシー | D23: =indirect("counting!L"& ((row()-3)*8 + COLUMN() -2)) -> - | E23: =indirect("counting!L"& ((row()-3)*8 + COLUMN() -2)) -> - | F23: =indirect("counting!L"& ((row()-3)*8 + COLUMN() -2)) -> - | G23: =indirect("counting!L"& ((row()-3)*8 + COLUMN() -2)) -> - | H23: =indirect("counting!L"& ((row()-3)*8 + COLUMN() -2)) -> - | I23: =indirect("counting!L"& ((row()-3)*8 + COLUMN() -2)) -> - | J23: =indirect("counting!L"& ((row()-3)*8 + COLUMN() -2)) -> - | K23: =indirect("counting!L"& ((row()-3)*8 + COLUMN() -2)) -> - | L23: =sum(D23:K23) -> 0
B24: =category!B23 -> 6 | C24: =category!C23 -> 機械学習プロジェクト管理 | D24: =indirect("counting!L"& ((row()-3)*8 + COLUMN() -2)) -> - | E24: =indirect("counting!L"& ((row()-3)*8 + COLUMN() -2)) -> - | F24: =indirect("counting!L"& ((row()-3)*8 + COLUMN() -2)) -> - | G24: =indirect("counting!L"& ((row()-3)*8 + COLUMN() -2)) -> - | H24: =indirect("counting!L"& ((row()-3)*8 + COLUMN() -2)) -> - | I24: =indirect("counting!L"& ((row()-3)*8 + COLUMN() -2)) -> - | J24: =indirect("counting!L"& ((row()-3)*8 + COLUMN() -2)) -> - | K24: =indirect("counting!L"& ((row()-3)*8 + COLUMN() -2)) -> - | L24: =sum(D24:K24) -> 0
B25: =category!B24 -> 7 | C25: =category!C24 -> マーケティング自動化 | D25: =indirect("counting!L"& ((row()-3)*8 + COLUMN() -2)) -> - | E25: =indirect("counting!L"& ((row()-3)*8 + COLUMN() -2)) -> - | F25: =indirect("counting!L"& ((row()-3)*8 + COLUMN() -2)) -> - | G25: =indirect("counting!L"& ((row()-3)*8 + COLUMN() -2)) -> - | H25: =indirect("counting!L"& ((row()-3)*8 + COLUMN() -2)) -> - | I25: =indirect("counting!L"& ((row()-3)*8 + COLUMN() -2)) -> - | J25: =indirect("counting!L"& ((row()-3)*8 + COLUMN() -2)) -> - | K25: =indirect("counting!L"& ((row()-3)*8 + COLUMN() -2)) -> - | L25: =sum(D25:K25) -> 0
B26: =category!B25 -> 8 | C26: =category!C25 -> 自動的な意思決定 | D26: =indirect("counting!L"& ((row()-3)*8 + COLUMN() -2)) -> - | E26: =indirect("counting!L"& ((row()-3)*8 + COLUMN() -2)) -> - | F26: =indirect("counting!L"& ((row()-3)*8 + COLUMN() -2)) -> - | G26: =indirect("counting!L"& ((row()-3)*8 + COLUMN() -2)) -> - | H26: =indirect("counting!L"& ((row()-3)*8 + COLUMN() -2)) -> - | I26: =indirect("counting!L"& ((row()-3)*8 + COLUMN() -2)) -> - | J26: =indirect("counting!L"& ((row()-3)*8 + COLUMN() -2)) -> - | K26: =indirect("counting!L"& ((row()-3)*8 + COLUMN() -2)) -> - | L26: =sum(D26:K26) -> 0
A27: デザイン | B27: =category!B26 -> 1 | C27: =category!C26 -> ペルソナの設定 | D27: =indirect("counting!L"& ((row()-3)*8 + COLUMN() -2)) -> - | E27: =indirect("counting!L"& ((row()-3)*8 + COLUMN() -2)) -> - | F27: =indirect("counting!L"& ((row()-3)*8 + COLUMN() -2)) -> - | G27: =indirect("counting!L"& ((row()-3)*8 + COLUMN() -2)) -> - | H27: =indirect("counting!L"& ((row()-3)*8 + COLUMN() -2)) -> - | I27: =indirect("counting!L"& ((row()-3)*8 + COLUMN() -2)) -> - | J27: =indirect("counting!L"& ((row()-3)*8 + COLUMN() -2)) -> - | K27: =indirect("counting!L"& ((row()-3)*8 + COLUMN() -2)) -> - | L27: =sum(D27:K27) -> 0 | M27: =sum(L27:L34) -> 0 | N27: =((M27-stats!B5)/stats!C5)*10+50 -> 21.414822 | O27: =vlookup(N27,rating!$B$2:$D$13,3,TRUE) -> DD
B28: =category!B27 -> 2 | C28: =category!C27 -> 顧客体験 | D28: =indirect("counting!L"& ((row()-3)*8 + COLUMN() -2)) -> - | E28: =indirect("counting!L"& ((row()-3)*8 + COLUMN() -2)) -> - | F28: =indirect("counting!L"& ((row()-3)*8 + COLUMN() -2)) -> - | G28: =indirect("counting!L"& ((row()-3)*8 + COLUMN() -2)) -> - | H28: =indirect("counting!L"& ((row()-3)*8 + COLUMN() -2)) -> - | I28: =indirect("counting!L"& ((row()-3)*8 + COLUMN() -2)) -> - | J28: =indirect("counting!L"& ((row()-3)*8 + COLUMN() -2)) -> - | K28: =indirect("counting!L"& ((row()-3)*8 + COLUMN() -2)) -> - | L28: =sum(D28:K28) -> 0
B29: =category!B28 -> 3 | C29: =category!C28 -> ユーザーインタビュー | D29: =indirect("counting!L"& ((row()-3)*8 + COLUMN() -2)) -> - | E29: =indirect("counting!L"& ((row()-3)*8 + COLUMN() -2)) -> - | F29: =indirect("counting!L"& ((row()-3)*8 + COLUMN() -2)) -> - | G29: =indirect("counting!L"& ((row()-3)*8 + COLUMN() -2)) -> - | H29: =indirect("counting!L"& ((row()-3)*8 + COLUMN() -2)) -> - | I29: =indirect("counting!L"& ((row()-3)*8 + COLUMN() -2)) -> - | J29: =indirect("counting!L"& ((row()-3)*8 + COLUMN() -2)) -> - | K29: =indirect("counting!L"& ((row()-3)*8 + COLUMN() -2)) -> - | L29: =sum(D29:K29) -> 0
B30: =category!B29 -> 4 | C30: =category!C29 -> デザインシステムの管理 | D30: =indirect("counting!L"& ((row()-3)*8 + COLUMN() -2)) -> - | E30: =indirect("counting!L"& ((row()-3)*8 + COLUMN() -2)) -> - | F30: =indirect("counting!L"& ((row()-3)*8 + COLUMN() -2)) -> - | G30: =indirect("counting!L"& ((row()-3)*8 + COLUMN() -2)) -> - | H30: =indirect("counting!L"& ((row()-3)*8 + COLUMN() -2)) -> - | I30: =indirect("counting!L"& ((row()-3)*8 + COLUMN() -2)) -> - | J30: =indirect("counting!L"& ((row()-3)*8 + COLUMN() -2)) -> - | K30: =indirect("counting!L"& ((row()-3)*8 + COLUMN() -2)) -> - | L30: =sum(D30:K30) -> 0
B31: =category!B30 -> 5 | C31: =category!C30 -> デザイン組織 | D31: =indirect("counting!L"& ((row()-3)*8 + COLUMN() -2)) -> - | E31: =indirect("counting!L"& ((row()-3)*8 + COLUMN() -2)) -> - | F31: =indirect("counting!L"& ((row()-3)*8 + COLUMN() -2)) -> - | G31: =indirect("counting!L"& ((row()-3)*8 + COLUMN() -2)) -> - | H31: =indirect("counting!L"& ((row()-3)*8 + COLUMN() -2)) -> - | I31: =indirect("counting!L"& ((row()-3)*8 + COLUMN() -2)) -> - | J31: =indirect("counting!L"& ((row()-3)*8 + COLUMN() -2)) -> - | K31: =indirect("counting!L"& ((row()-3)*8 + COLUMN() -2)) -> - | L31: =sum(D31:K31) -> 0
B32: =category!B31 -> 6 | C32: =category!C31 -> プロトタイピング | D32: =indirect("counting!L"& ((row()-3)*8 + COLUMN() -2)) -> - | E32: =indirect("counting!L"& ((row()-3)*8 + COLUMN() -2)) -> - | F32: =indirect("counting!L"& ((row()-3)*8 + COLUMN() -2)) -> - | G32: =indirect("counting!L"& ((row()-3)*8 + COLUMN() -2)) -> - | H32: =indirect("counting!L"& ((row()-3)*8 + COLUMN() -2)) -> - | I32: =indirect("counting!L"& ((row()-3)*8 + COLUMN() -2)) -> - | J32: =indirect("counting!L"& ((row()-3)*8 + COLUMN() -2)) -> - | K32: =indirect("counting!L"& ((row()-3)*8 + COLUMN() -2)) -> - | L32: =sum(D32:K32) -> 0
B33: =category!B32 -> 7 | C33: =category!C32 -> ユーザビリティテスト | D33: =indirect("counting!L"& ((row()-3)*8 + COLUMN() -2)) -> - | E33: =indirect("counting!L"& ((row()-3)*8 + COLUMN() -2)) -> - | F33: =indirect("counting!L"& ((row()-3)*8 + COLUMN() -2)) -> - | G33: =indirect("counting!L"& ((row()-3)*8 + COLUMN() -2)) -> - | H33: =indirect("counting!L"& ((row()-3)*8 + COLUMN() -2)) -> - | I33: =indirect("counting!L"& ((row()-3)*8 + COLUMN() -2)) -> - | J33: =indirect("counting!L"& ((row()-3)*8 + COLUMN() -2)) -> - | K33: =indirect("counting!L"& ((row()-3)*8 + COLUMN() -2)) -> - | L33: =sum(D33:K33) -> 0
B34: =category!B33 -> 8 | C34: =category!C33 -> プロダクトマネジメント | D34: =indirect("counting!L"& ((row()-3)*8 + COLUMN() -2)) -> - | E34: =indirect("counting!L"& ((row()-3)*8 + COLUMN() -2)) -> - | F34: =indirect("counting!L"& ((row()-3)*8 + COLUMN() -2)) -> - | G34: =indirect("counting!L"& ((row()-3)*8 + COLUMN() -2)) -> - | H34: =indirect("counting!L"& ((row()-3)*8 + COLUMN() -2)) -> - | I34: =indirect("counting!L"& ((row()-3)*8 + COLUMN() -2)) -> - | J34: =indirect("counting!L"& ((row()-3)*8 + COLUMN() -2)) -> - | K34: =indirect("counting!L"& ((row()-3)*8 + COLUMN() -2)) -> - | L34: =sum(D34:K34) -> 0
A35: コーポレート | B35: =category!B34 -> 1 | C35: =category!C34 -> スパン・オブ・コントロール | D35: =indirect("counting!L"& ((row()-3)*8 + COLUMN() -2)) -> - | E35: =indirect("counting!L"& ((row()-3)*8 + COLUMN() -2)) -> - | F35: =indirect("counting!L"& ((row()-3)*8 + COLUMN() -2)) -> - | G35: =indirect("counting!L"& ((row()-3)*8 + COLUMN() -2)) -> - | H35: =indirect("counting!L"& ((row()-3)*8 + COLUMN() -2)) -> - | I35: =indirect("counting!L"& ((row()-3)*8 + COLUMN() -2)) -> - | J35: =indirect("counting!L"& ((row()-3)*8 + COLUMN() -2)) -> - | K35: =indirect("counting!L"& ((row()-3)*8 + COLUMN() -2)) -> - | L35: =sum(D35:K35) -> 0 | M35: =sum(L35:L42) -> 0 | N35: =((M35-stats!B6)/stats!C6)*10+50 -> 5.2046784 | O35: =vlookup(N35,rating!$B$2:$D$13,3,TRUE) -> DD
B36: =category!B35 -> 2 | C36: =category!C35 -> 開発者環境投資 | D36: =indirect("counting!L"& ((row()-3)*8 + COLUMN() -2)) -> - | E36: =indirect("counting!L"& ((row()-3)*8 + COLUMN() -2)) -> - | F36: =indirect("counting!L"& ((row()-3)*8 + COLUMN() -2)) -> - | G36: =indirect("counting!L"& ((row()-3)*8 + COLUMN() -2)) -> - | H36: =indirect("counting!L"& ((row()-3)*8 + COLUMN() -2)) -> - | I36: =indirect("counting!L"& ((row()-3)*8 + COLUMN() -2)) -> - | J36: =indirect("counting!L"& ((row()-3)*8 + COLUMN() -2)) -> - | K36: =indirect("counting!L"& ((row()-3)*8 + COLUMN() -2)) -> - | L36: =sum(D36:K36) -> 0
B37: =category!B36 -> 3 | C37: =category!C36 -> コミュニケーションツール | D37: =indirect("counting!L"& ((row()-3)*8 + COLUMN() -2)) -> - | E37: =indirect("counting!L"& ((row()-3)*8 + COLUMN() -2)) -> - | F37: =indirect("counting!L"& ((row()-3)*8 + COLUMN() -2)) -> - | G37: =indirect("counting!L"& ((row()-3)*8 + COLUMN() -2)) -> - | H37: =indirect("counting!L"& ((row()-3)*8 + COLUMN() -2)) -> - | I37: =indirect("counting!L"& ((row()-3)*8 + COLUMN() -2)) -> - | J37: =indirect("counting!L"& ((row()-3)*8 + COLUMN() -2)) -> - | K37: =indirect("counting!L"& ((row()-3)*8 + COLUMN() -2)) -> - | L37: =sum(D37:K37) -> 0
B38: =category!B37 -> 4 | C38: =category!C37 -> 人事制度・育成戦略 | D38: =indirect("counting!L"& ((row()-3)*8 + COLUMN() -2)) -> - | E38: =indirect("counting!L"& ((row()-3)*8 + COLUMN() -2)) -> - | F38: =indirect("counting!L"& ((row()-3)*8 + COLUMN() -2)) -> - | G38: =indirect("counting!L"& ((row()-3)*8 + COLUMN() -2)) -> - | H38: =indirect("counting!L"& ((row()-3)*8 + COLUMN() -2)) -> - | I38: =indirect("counting!L"& ((row()-3)*8 + COLUMN() -2)) -> - | J38: =indirect("counting!L"& ((row()-3)*8 + COLUMN() -2)) -> - | K38: =indirect("counting!L"& ((row()-3)*8 + COLUMN() -2)) -> - | L38: =sum(D38:K38) -> 0
B39: =category!B38 -> 5 | C39: =category!C38 -> デジタル人材採用戦略 | D39: =indirect("counting!L"& ((row()-3)*8 + COLUMN() -2)) -> - | E39: =indirect("counting!L"& ((row()-3)*8 + COLUMN() -2)) -> - | F39: =indirect("counting!L"& ((row()-3)*8 + COLUMN() -2)) -> - | G39: =indirect("counting!L"& ((row()-3)*8 + COLUMN() -2)) -> - | H39: =indirect("counting!L"& ((row()-3)*8 + COLUMN() -2)) -> - | I39: =indirect("counting!L"& ((row()-3)*8 + COLUMN() -2)) -> - | J39: =indirect("counting!L"& ((row()-3)*8 + COLUMN() -2)) -> - | K39: =indirect("counting!L"& ((row()-3)*8 + COLUMN() -2)) -> - | L39: =sum(D39:K39) -> 0
B40: =category!B39 -> 6 | C40: =category!C39 -> モダンなITサービスの活用 | D40: =indirect("counting!L"& ((row()-3)*8 + COLUMN() -2)) -> - | E40: =indirect("counting!L"& ((row()-3)*8 + COLUMN() -2)) -> - | F40: =indirect("counting!L"& ((row()-3)*8 + COLUMN() -2)) -> - | G40: =indirect("counting!L"& ((row()-3)*8 + COLUMN() -2)) -> - | H40: =indirect("counting!L"& ((row()-3)*8 + COLUMN() -2)) -> - | I40: =indirect("counting!L"& ((row()-3)*8 + COLUMN() -2)) -> - | J40: =indirect("counting!L"& ((row()-3)*8 + COLUMN() -2)) -> - | K40: =indirect("counting!L"& ((row()-3)*8 + COLUMN() -2)) -> - | L40: =sum(D40:K40) -> 0
B41: =category!B40 -> 7 | C41: =category!C40 -> 経営のデジタルファースト | D41: =indirect("counting!L"& ((row()-3)*8 + COLUMN() -2)) -> - | E41: =indirect("counting!L"& ((row()-3)*8 + COLUMN() -2)) -> - | F41: =indirect("counting!L"& ((row()-3)*8 + COLUMN() -2)) -> - | G41: =indirect("counting!L"& ((row()-3)*8 + COLUMN() -2)) -> - | H41: =indirect("counting!L"& ((row()-3)*8 + COLUMN() -2)) -> - | I41: =indirect("counting!L"& ((row()-3)*8 + COLUMN() -2)) -> - | J41: =indirect("counting!L"& ((row()-3)*8 + COLUMN() -2)) -> - | K41: =indirect("counting!L"& ((row()-3)*8 + COLUMN() -2)) -> - | L41: =sum(D41:K41) -> 0
B42: =category!B41 -> 8 | C42: =category!C41 -> 攻めのセキュリティ | D42: =indirect("counting!L"& ((row()-3)*8 + COLUMN() -2)) -> - | E42: =indirect("counting!L"& ((row()-3)*8 + COLUMN() -2)) -> - | F42: =indirect("counting!L"& ((row()-3)*8 + COLUMN() -2)) -> - | G42: =indirect("counting!L"& ((row()-3)*8 + COLUMN() -2)) -> - | H42: =indirect("counting!L"& ((row()-3)*8 + COLUMN() -2)) -> - | I42: =indirect("counting!L"& ((row()-3)*8 + COLUMN() -2)) -> - | J42: =indirect("counting!L"& ((row()-3)*8 + COLUMN() -2)) -> - | K42: =indirect("counting!L"& ((row()-3)*8 + COLUMN() -2)) -> - | L42: =sum(D42:K42) -> 0
C43: 合計 | D43: =sum(D3:D42) -> 0 | E43: =sum(E3:E42) -> 0 | F43: =sum(F3:H42) -> 0 | I43: =sum(I3:K42) -> 0 | L43: =sum(L3:L42) -> 0

Sheet 過去アセスメント変換
A1: テーマ | B1: No | C1: カテゴリー | D1: メトリクスの計測 | E1: 学習と改善 | F1: プラクティスと習慣 | I1: アンチパターン | P1: Name | R1: yes | S1: no | T1: but
A2: チーム | B2: =category!B2 -> 1 | C2: =category!C2 -> チーム構成と権限委譲 | M2: 1 | N2: =FLOOR((M2-1)/8,1)+1 -> 1 | O2: =mod(M2-1,8)+1 -> 1 | P2: ='アセスメント'!B3 -> TEAM-1-1 | Q2: =indirect("R"&N2+ 1&"C"&3+O2,FALSE) | R2: =IFERROR(__xludf.DUMMYFUNCTION("REGEXMATCH($Q2,""Yes"")"),FALSE) -> FALSE | S2: =IFERROR(__xludf.DUMMYFUNCTION("REGEXMATCH($Q2,""No"")"),FALSE) -> FALSE | T2: =IFERROR(__xludf.DUMMYFUNCTION("REGEXMATCH($Q2,""but"")"),FALSE) -> FALSE
B3: =category!B3 -> 2 | C3: =category!C3 -> チームビルディング | M3: 2 | N3: =FLOOR((M3-1)/8,1)+1 -> 1 | O3: =mod(M3-1,8)+1 -> 2 | P3: ='アセスメント'!B4 -> TEAM-1-2 | Q3: =indirect("R"&N3+ 1&"C"&3+O3,FALSE) | R3: =IFERROR(__xludf.DUMMYFUNCTION("REGEXMATCH($Q3,""Yes"")"),FALSE) -> FALSE | S3: =IFERROR(__xludf.DUMMYFUNCTION("REGEXMATCH($Q3,""No"")"),FALSE) -> FALSE | T3: =IFERROR(__xludf.DUMMYFUNCTION("REGEXMATCH($Q3,""but"")"),FALSE) -> FALSE
B4: =category!B4 -> 3 | C4: =category!C4 -> 心理的安全性 | M4: 3 | N4: =FLOOR((M4-1)/8,1)+1 -> 1 | O4: =mod(M4-1,8)+1 -> 3 | P4: ='アセスメント'!B5 -> TEAM-1-3 | Q4: =indirect("R"&N4+ 1&"C"&3+O4,FALSE) | R4: =IFERROR(__xludf.DUMMYFUNCTION("REGEXMATCH($Q4,""Yes"")"),FALSE) -> FALSE | S4: =IFERROR(__xludf.DUMMYFUNCTION("REGEXMATCH($Q4,""No"")"),FALSE) -> FALSE | T4: =IFERROR(__xludf.DUMMYFUNCTION("REGEXMATCH($Q4,""but"")"),FALSE) -> FALSE
B5: =category!B5 -> 4 | C5: =category!C5 -> タスクマネジメント | M5: 4 | N5: =FLOOR((M5-1)/8,1)+1 -> 1 | O5: =mod(M5-1,8)+1 -> 4 | P5: ='アセスメント'!B6 -> TEAM-1-4 | Q5: =indirect("R"&N5+ 1&"C"&3+O5,FALSE) | R5: =IFERROR(__xludf.DUMMYFUNCTION("REGEXMATCH($Q5,""Yes"")"),FALSE) -> FALSE | S5: =IFERROR(__xludf.DUMMYFUNCTION("REGEXMATCH($Q5,""No"")"),FALSE) -> FALSE | T5: =IFERROR(__xludf.DUMMYFUNCTION("REGEXMATCH($Q5,""but"")"),FALSE) -> FALSE
B6: =category!B6 -> 5 | C6: =category!C6 -> 透明性ある目標管理 | M6: 5 | N6: =FLOOR((M6-1)/8,1)+1 -> 1 | O6: =mod(M6-1,8)+1 -> 5 | P6: ='アセスメント'!B7 -> TEAM-1-5 | Q6: =indirect("R"&N6+ 1&"C"&3+O6,FALSE) | R6: =IFERROR(__xludf.DUMMYFUNCTION("REGEXMATCH($Q6,""Yes"")"),FALSE) -> FALSE | S6: =IFERROR(__xludf.DUMMYFUNCTION("REGEXMATCH($Q6,""No"")"),FALSE) -> FALSE | T6: =IFERROR(__xludf.DUMMYFUNCTION("REGEXMATCH($Q6,""but"")"),FALSE) -> FALSE
B7: =category!B7 -> 6 | C7: =category!C7 -> 経験主義的な見積りと計画 | M7: 6 | N7: =FLOOR((M7-1)/8,1)+1 -> 1 | O7: =mod(M7-1,8)+1 -> 6 | P7: ='アセスメント'!B8 -> TEAM-1-6 | Q7: =indirect("R"&N7+ 1&"C"&3+O7,FALSE) | R7: =IFERROR(__xludf.DUMMYFUNCTION("REGEXMATCH($Q7,""Yes"")"),FALSE) -> FALSE | S7: =IFERROR(__xludf.DUMMYFUNCTION("REGEXMATCH($Q7,""No"")"),FALSE) -> FALSE | T7: =IFERROR(__xludf.DUMMYFUNCTION("REGEXMATCH($Q7,""but"")"),FALSE) -> FALSE
B8: =category!B8 -> 7 | C8: =category!C8 -> ふりかえり習慣 | M8: 7 | N8: =FLOOR((M8-1)/8,1)+1 -> 1 | O8: =mod(M8-1,8)+1 -> 7 | P8: ='アセスメント'!B9 -> TEAM-1-7 | Q8: =indirect("R"&N8+ 1&"C"&3+O8,FALSE) | R8: =IFERROR(__xludf.DUMMYFUNCTION("REGEXMATCH($Q8,""Yes"")"),FALSE) -> FALSE | S8: =IFERROR(__xludf.DUMMYFUNCTION("REGEXMATCH($Q8,""No"")"),FALSE) -> FALSE | T8: =IFERROR(__xludf.DUMMYFUNCTION("REGEXMATCH($Q8,""but"")"),FALSE) -> FALSE
B9: =category!B9 -> 8 | C9: =category!C9 -> バリューストリーム最適化 | M9: 8 | N9: =FLOOR((M9-1)/8,1)+1 -> 1 | O9: =mod(M9-1,8)+1 -> 8 | P9: ='アセスメント'!B10 -> TEAM-1-8 | Q9: =indirect("R"&N9+ 1&"C"&3+O9,FALSE) | R9: =IFERROR(__xludf.DUMMYFUNCTION("REGEXMATCH($Q9,""Yes"")"),FALSE) -> FALSE | S9: =IFERROR(__xludf.DUMMYFUNCTION("REGEXMATCH($Q9,""No"")"),FALSE) -> FALSE | T9: =IFERROR(__xludf.DUMMYFUNCTION("REGEXMATCH($Q9,""but"")"),FALSE) -> FALSE
A10: システム | B10: =category!B10 -> 1 | C10: =category!C10 -> バージョン管理 | M10: 9 | N10: =FLOOR((M10-1)/8,1)+1 -> 2 | O10: =mod(M10-1,8)+1 -> 1 | P10: ='アセスメント'!B11 -> TEAM-2-1 | Q10: =indirect("R"&N10+ 1&"C"&3+O10,FALSE) | R10: =IFERROR(__xludf.DUMMYFUNCTION("REGEXMATCH($Q10,""Yes"")"),FALSE) -> FALSE | S10: =IFERROR(__xludf.DUMMYFUNCTION("REGEXMATCH($Q10,""No"")"),FALSE) -> FALSE | T10: =IFERROR(__xludf.DUMMYFUNCTION("REGEXMATCH($Q10,""but"")"),FALSE) -> FALSE
B11: =category!B11 -> 2 | C11: =category!C11 -> ソースコードの明確さ | M11: 10 | N11: =FLOOR((M11-1)/8,1)+1 -> 2 | O11: =mod(M11-1,8)+1 -> 2 | P11: ='アセスメント'!B12 -> TEAM-2-2 | Q11: =indirect("R"&N11+ 1&"C"&3+O11,FALSE) | R11: =IFERROR(__xludf.DUMMYFUNCTION("REGEXMATCH($Q11,""Yes"")"),FALSE) -> FALSE | S11: =IFERROR(__xludf.DUMMYFUNCTION("REGEXMATCH($Q11,""No"")"),FALSE) -> FALSE | T11: =IFERROR(__xludf.DUMMYFUNCTION("REGEXMATCH($Q11,""but"")"),FALSE) -> FALSE
B12: =category!B12 -> 3 | C12: =category!C12 -> 継続的インテグレーション | M12: 11 | N12: =FLOOR((M12-1)/8,1)+1 -> 2 | O12: =mod(M12-1,8)+1 -> 3 | P12: ='アセスメント'!B13 -> TEAM-2-3 | Q12: =indirect("R"&N12+ 1&"C"&3+O12,FALSE) | R12: =IFERROR(__xludf.DUMMYFUNCTION("REGEXMATCH($Q12,""Yes"")"),FALSE) -> FALSE | S12: =IFERROR(__xludf.DUMMYFUNCTION("REGEXMATCH($Q12,""No"")"),FALSE) -> FALSE | T12: =IFERROR(__xludf.DUMMYFUNCTION("REGEXMATCH($Q12,""but"")"),FALSE) -> FALSE
B13: =category!B13 -> 4 | C13: =category!C13 -> 継続的デプロイ | M13: 12 | N13: =FLOOR((M13-1)/8,1)+1 -> 2 | O13: =mod(M13-1,8)+1 -> 4 | P13: ='アセスメント'!B14 -> TEAM-2-4 | Q13: =indirect("R"&N13+ 1&"C"&3+O13,FALSE) | R13: =IFERROR(__xludf.DUMMYFUNCTION("REGEXMATCH($Q13,""Yes"")"),FALSE) -> FALSE | S13: =IFERROR(__xludf.DUMMYFUNCTION("REGEXMATCH($Q13,""No"")"),FALSE) -> FALSE | T13: =IFERROR(__xludf.DUMMYFUNCTION("REGEXMATCH($Q13,""but"")"),FALSE) -> FALSE
B14: =category!B14 -> 5 | C14: =category!C14 -> API駆動開発 | M14: 13 | N14: =FLOOR((M14-1)/8,1)+1 -> 2 | O14: =mod(M14-1,8)+1 -> 5 | P14: ='アセスメント'!B15 -> TEAM-2-5 | Q14: =indirect("R"&N14+ 1&"C"&3+O14,FALSE) | R14: =IFERROR(__xludf.DUMMYFUNCTION("REGEXMATCH($Q14,""Yes"")"),FALSE) -> FALSE | S14: =IFERROR(__xludf.DUMMYFUNCTION("REGEXMATCH($Q14,""No"")"),FALSE) -> FALSE | T14: =IFERROR(__xludf.DUMMYFUNCTION("REGEXMATCH($Q14,""but"")"),FALSE) -> FALSE
B15: =category!B15 -> 6 | C15: =category!C15 -> 疎結合アーキテクチャ | M15: 14 | N15: =FLOOR((M15-1)/8,1)+1 -> 2 | O15: =mod(M15-1,8)+1 -> 6 | P15: ='アセスメント'!B16 -> TEAM-2-6 | Q15: =indirect("R"&N15+ 1&"C"&3+O15,FALSE) | R15: =IFERROR(__xludf.DUMMYFUNCTION("REGEXMATCH($Q15,""Yes"")"),FALSE) -> FALSE | S15: =IFERROR(__xludf.DUMMYFUNCTION("REGEXMATCH($Q15,""No"")"),FALSE) -> FALSE | T15: =IFERROR(__xludf.DUMMYFUNCTION("REGEXMATCH($Q15,""but"")"),FALSE) -> FALSE
B16: =category!B16 -> 7 | C16: =category!C16 -> システムモニタリング | M16: 15 | N16: =FLOOR((M16-1)/8,1)+1 -> 2 | O16: =mod(M16-1,8)+1 -> 7 | P16: ='アセスメント'!B17 -> TEAM-2-7 | Q16: =indirect("R"&N16+ 1&"C"&3+O16,FALSE) | R16: =IFERROR(__xludf.DUMMYFUNCTION("REGEXMATCH($Q16,""Yes"")"),FALSE) -> FALSE | S16: =IFERROR(__xludf.DUMMYFUNCTION("REGEXMATCH($Q16,""No"")"),FALSE) -> FALSE | T16: =IFERROR(__xludf.DUMMYFUNCTION("REGEXMATCH($Q16,""but"")"),FALSE) -> FALSE
B17: =category!B17 -> 8 | C17: =category!C17 -> セキュリティシフトレフト | M17: 16 | N17: =FLOOR((M17-1)/8,1)+1 -> 2 | O17: =mod(M17-1,8)+1 -> 8 | P17: ='アセスメント'!B18 -> TEAM-2-8 | Q17: =indirect("R"&N17+ 1&"C"&3+O17,FALSE) | R17: =IFERROR(__xludf.DUMMYFUNCTION("REGEXMATCH($Q17,""Yes"")"),FALSE) -> FALSE | S17: =IFERROR(__xludf.DUMMYFUNCTION("REGEXMATCH($Q17,""No"")"),FALSE) -> FALSE | T17: =IFERROR(__xludf.DUMMYFUNCTION("REGEXMATCH($Q17,""but"")"),FALSE) -> FALSE
A18: データ | B18: =category!B18 -> 1 | C18: =category!C18 -> 顧客接点のデジタル化 | M18: 17 | N18: =FLOOR((M18-1)/8,1)+1 -> 3 | O18: =mod(M18-1,8)+1 -> 1 | P18: ='アセスメント'!B19 -> TEAM-3-1 | Q18: =indirect("R"&N18+ 1&"C"&3+O18,FALSE) | R18: =IFERROR(__xludf.DUMMYFUNCTION("REGEXMATCH($Q18,""Yes"")"),FALSE) -> FALSE | S18: =IFERROR(__xludf.DUMMYFUNCTION("REGEXMATCH($Q18,""No"")"),FALSE) -> FALSE | T18: =IFERROR(__xludf.DUMMYFUNCTION("REGEXMATCH($Q18,""but"")"),FALSE) -> FALSE
B19: =category!B19 -> 2 | C19: =category!C19 -> 事業活動データの収集 | M19: 18 | N19: =FLOOR((M19-1)/8,1)+1 -> 3 | O19: =mod(M19-1,8)+1 -> 2 | P19: ='アセスメント'!B20 -> TEAM-3-2 | Q19: =indirect("R"&N19+ 1&"C"&3+O19,FALSE) | R19: =IFERROR(__xludf.DUMMYFUNCTION("REGEXMATCH($Q19,""Yes"")"),FALSE) -> FALSE | S19: =IFERROR(__xludf.DUMMYFUNCTION("REGEXMATCH($Q19,""No"")"),FALSE) -> FALSE | T19: =IFERROR(__xludf.DUMMYFUNCTION("REGEXMATCH($Q19,""but"")"),FALSE) -> FALSE
B20: =category!B20 -> 3 | C20: =category!C20 -> データ蓄積・分析基盤 | M20: 19 | N20: =FLOOR((M20-1)/8,1)+1 -> 3 | O20: =mod(M20-1,8)+1 -> 3 | P20: ='アセスメント'!B21 -> TEAM-3-3 | Q20: =indirect("R"&N20+ 1&"C"&3+O20,FALSE) | R20: =IFERROR(__xludf.DUMMYFUNCTION("REGEXMATCH($Q20,""Yes"")"),FALSE) -> FALSE | S20: =IFERROR(__xludf.DUMMYFUNCTION("REGEXMATCH($Q20,""No"")"),FALSE) -> FALSE | T20: =IFERROR(__xludf.DUMMYFUNCTION("REGEXMATCH($Q20,""but"")"),FALSE) -> FALSE
B21: =category!B21 -> 4 | C21: =category!C21 -> データ処理パイプライン | M21: 20 | N21: =FLOOR((M21-1)/8,1)+1 -> 3 | O21: =mod(M21-1,8)+1 -> 4 | P21: ='アセスメント'!B22 -> TEAM-3-4 | Q21: =indirect("R"&N21+ 1&"C"&3+O21,FALSE) | R21: =IFERROR(__xludf.DUMMYFUNCTION("REGEXMATCH($Q21,""Yes"")"),FALSE) -> FALSE | S21: =IFERROR(__xludf.DUMMYFUNCTION("REGEXMATCH($Q21,""No"")"),FALSE) -> FALSE | T21: =IFERROR(__xludf.DUMMYFUNCTION("REGEXMATCH($Q21,""but"")"),FALSE) -> FALSE
B22: =category!B22 -> 5 | C22: =category!C22 -> データ可視化とリテラシー | M22: 21 | N22: =FLOOR((M22-1)/8,1)+1 -> 3 | O22: =mod(M22-1,8)+1 -> 5 | P22: ='アセスメント'!B23 -> TEAM-3-5 | Q22: =indirect("R"&N22+ 1&"C"&3+O22,FALSE) | R22: =IFERROR(__xludf.DUMMYFUNCTION("REGEXMATCH($Q22,""Yes"")"),FALSE) -> FALSE | S22: =IFERROR(__xludf.DUMMYFUNCTION("REGEXMATCH($Q22,""No"")"),FALSE) -> FALSE | T22: =IFERROR(__xludf.DUMMYFUNCTION("REGEXMATCH($Q22,""but"")"),FALSE) -> FALSE
B23: =category!B23 -> 6 | C23: =category!C23 -> 機械学習プロジェクト管理 | M23: 22 | N23: =FLOOR((M23-1)/8,1)+1 -> 3 | O23: =mod(M23-1,8)+1 -> 6 | P23: ='アセスメント'!B24 -> TEAM-3-6 | Q23: =indirect("R"&N23+ 1&"C"&3+O23,FALSE) | R23: =IFERROR(__xludf.DUMMYFUNCTION("REGEXMATCH($Q23,""Yes"")"),FALSE) -> FALSE | S23: =IFERROR(__xludf.DUMMYFUNCTION("REGEXMATCH($Q23,""No"")"),FALSE) -> FALSE | T23: =IFERROR(__xludf.DUMMYFUNCTION("REGEXMATCH($Q23,""but"")"),FALSE) -> FALSE
B24: =category!B24 -> 7 | C24: =category!C24 -> マーケティング自動化 | M24: 23 | N24: =FLOOR((M24-1)/8,1)+1 -> 3 | O24: =mod(M24-1,8)+1 -> 7 | P24: ='アセスメント'!B25 -> TEAM-3-7 | Q24: =indirect("R"&N24+ 1&"C"&3+O24,FALSE) | R24: =IFERROR(__xludf.DUMMYFUNCTION("REGEXMATCH($Q24,""Yes"")"),FALSE) -> FALSE | S24: =IFERROR(__xludf.DUMMYFUNCTION("REGEXMATCH($Q24,""No"")"),FALSE) -> FALSE | T24: =IFERROR(__xludf.DUMMYFUNCTION("REGEXMATCH($Q24,""but"")"),FALSE) -> FALSE
B25: =category!B25 -> 8 | C25: =category!C25 -> 自動的な意思決定 | M25: 24 | N25: =FLOOR((M25-1)/8,1)+1 -> 3 | O25: =mod(M25-1,8)+1 -> 8 | P25: ='アセスメント'!B26 -> TEAM-3-8 | Q25: =indirect("R"&N25+ 1&"C"&3+O25,FALSE) | R25: =IFERROR(__xludf.DUMMYFUNCTION("REGEXMATCH($Q25,""Yes"")"),FALSE) -> FALSE | S25: =IFERROR(__xludf.DUMMYFUNCTION("REGEXMATCH($Q25,""No"")"),FALSE) -> FALSE | T25: =IFERROR(__xludf.DUMMYFUNCTION("REGEXMATCH($Q25,""but"")"),FALSE) -> FALSE
A26: デザイン | B26: =category!B26 -> 1 | C26: =category!C26 -> ペルソナの設定 | M26: 25 | N26: =FLOOR((M26-1)/8,1)+1 -> 4 | O26: =mod(M26-1,8)+1 -> 1 | P26: ='アセスメント'!B27 -> TEAM-4-1 | Q26: =indirect("R"&N26+ 1&"C"&3+O26,FALSE) | R26: =IFERROR(__xludf.DUMMYFUNCTION("REGEXMATCH($Q26,""Yes"")"),FALSE) -> FALSE | S26: =IFERROR(__xludf.DUMMYFUNCTION("REGEXMATCH($Q26,""No"")"),FALSE) -> FALSE | T26: =IFERROR(__xludf.DUMMYFUNCTION("REGEXMATCH($Q26,""but"")"),FALSE) -> FALSE
B27: =category!B27 -> 2 | C27: =category!C27 -> 顧客体験 | M27: 26 | N27: =FLOOR((M27-1)/8,1)+1 -> 4 | O27: =mod(M27-1,8)+1 -> 2 | P27: ='アセスメント'!B28 -> TEAM-4-2 | Q27: =indirect("R"&N27+ 1&"C"&3+O27,FALSE) | R27: =IFERROR(__xludf.DUMMYFUNCTION("REGEXMATCH($Q27,""Yes"")"),FALSE) -> FALSE | S27: =IFERROR(__xludf.DUMMYFUNCTION("REGEXMATCH($Q27,""No"")"),FALSE) -> FALSE | T27: =IFERROR(__xludf.DUMMYFUNCTION("REGEXMATCH($Q27,""but"")"),FALSE) -> FALSE
B28: =category!B28 -> 3 | C28: =category!C28 -> ユーザーインタビュー | M28: 27 | N28: =FLOOR((M28-1)/8,1)+1 -> 4 | O28: =mod(M28-1,8)+1 -> 3 | P28: ='アセスメント'!B29 -> TEAM-4-3 | Q28: =indirect("R"&N28+ 1&"C"&3+O28,FALSE) | R28: =IFERROR(__xludf.DUMMYFUNCTION("REGEXMATCH($Q28,""Yes"")"),FALSE) -> FALSE | S28: =IFERROR(__xludf.DUMMYFUNCTION("REGEXMATCH($Q28,""No"")"),FALSE) -> FALSE | T28: =IFERROR(__xludf.DUMMYFUNCTION("REGEXMATCH($Q28,""but"")"),FALSE) -> FALSE
B29: =category!B29 -> 4 | C29: =category!C29 -> デザインシステムの管理 | M29: 28 | N29: =FLOOR((M29-1)/8,1)+1 -> 4 | O29: =mod(M29-1,8)+1 -> 4 | P29: ='アセスメント'!B30 -> TEAM-4-4 | Q29: =indirect("R"&N29+ 1&"C"&3+O29,FALSE) | R29: =IFERROR(__xludf.DUMMYFUNCTION("REGEXMATCH($Q29,""Yes"")"),FALSE) -> FALSE | S29: =IFERROR(__xludf.DUMMYFUNCTION("REGEXMATCH($Q29,""No"")"),FALSE) -> FALSE | T29: =IFERROR(__xludf.DUMMYFUNCTION("REGEXMATCH($Q29,""but"")"),FALSE) -> FALSE
B30: =category!B30 -> 5 | C30: =category!C30 -> デザイン組織 | M30: 29 | N30: =FLOOR((M30-1)/8,1)+1 -> 4 | O30: =mod(M30-1,8)+1 -> 5 | P30: ='アセスメント'!B31 -> TEAM-4-5 | Q30: =indirect("R"&N30+ 1&"C"&3+O30,FALSE) | R30: =IFERROR(__xludf.DUMMYFUNCTION("REGEXMATCH($Q30,""Yes"")"),FALSE) -> FALSE | S30: =IFERROR(__xludf.DUMMYFUNCTION("REGEXMATCH($Q30,""No"")"),FALSE) -> FALSE | T30: =IFERROR(__xludf.DUMMYFUNCTION("REGEXMATCH($Q30,""but"")"),FALSE) -> FALSE
B31: =category!B31 -> 6 | C31: =category!C31 -> プロトタイピング | M31: 30 | N31: =FLOOR((M31-1)/8,1)+1 -> 4 | O31: =mod(M31-1,8)+1 -> 6 | P31: ='アセスメント'!B32 -> TEAM-4-6 | Q31: =indirect("R"&N31+ 1&"C"&3+O31,FALSE) | R31: =IFERROR(__xludf.DUMMYFUNCTION("REGEXMATCH($Q31,""Yes"")"),FALSE) -> FALSE | S31: =IFERROR(__xludf.DUMMYFUNCTION("REGEXMATCH($Q31,""No"")"),FALSE) -> FALSE | T31: =IFERROR(__xludf.DUMMYFUNCTION("REGEXMATCH($Q31,""but"")"),FALSE) -> FALSE
B32: =category!B32 -> 7 | C32: =category!C32 -> ユーザビリティテスト | M32: 31 | N32: =FLOOR((M32-1)/8,1)+1 -> 4 | O32: =mod(M32-1,8)+1 -> 7 | P32: ='アセスメント'!B33 -> TEAM-4-7 | Q32: =indirect("R"&N32+ 1&"C"&3+O32,FALSE) | R32: =IFERROR(__xludf.DUMMYFUNCTION("REGEXMATCH($Q32,""Yes"")"),FALSE) -> FALSE | S32: =IFERROR(__xludf.DUMMYFUNCTION("REGEXMATCH($Q32,""No"")"),FALSE) -> FALSE | T32: =IFERROR(__xludf.DUMMYFUNCTION("REGEXMATCH($Q32,""but"")"),FALSE) -> FALSE
B33: =category!B33 -> 8 | C33: =category!C33 -> プロダクトマネジメント | M33: 32 | N33: =FLOOR((M33-1)/8,1)+1 -> 4 | O33: =mod(M33-1,8)+1 -> 8 | P33: ='アセスメント'!B34 -> TEAM-4-8 | Q33: =indirect("R"&N33+ 1&"C"&3+O33,FALSE) | R33: =IFERROR(__xludf.DUMMYFUNCTION("REGEXMATCH($Q33,""Yes"")"),FALSE) -> FALSE | S33: =IFERROR(__xludf.DUMMYFUNCTION("REGEXMATCH($Q33,""No"")"),FALSE) -> FALSE | T33: =IFERROR(__xludf.DUMMYFUNCTION("REGEXMATCH($Q33,""but"")"),FALSE) -> FALSE
A34: コーポレート | B34: =category!B34 -> 1 | C34: =category!C34 -> スパン・オブ・コントロール | M34: 33 | N34: =FLOOR((M34-1)/8,1)+1 -> 5 | O34: =mod(M34-1,8)+1 -> 1 | P34: ='アセスメント'!B35 -> TEAM-5-1 | Q34: =indirect("R"&N34+ 1&"C"&3+O34,FALSE) | R34: =IFERROR(__xludf.DUMMYFUNCTION("REGEXMATCH($Q34,""Yes"")"),FALSE) -> FALSE | S34: =IFERROR(__xludf.DUMMYFUNCTION("REGEXMATCH($Q34,""No"")"),FALSE) -> FALSE | T34: =IFERROR(__xludf.DUMMYFUNCTION("REGEXMATCH($Q34,""but"")"),FALSE) -> FALSE
B35: =category!B35 -> 2 | C35: =category!C35 -> 開発者環境投資 | M35: 34 | N35: =FLOOR((M35-1)/8,1)+1 -> 5 | O35: =mod(M35-1,8)+1 -> 2 | P35: ='アセスメント'!B36 -> TEAM-5-2 | Q35: =indirect("R"&N35+ 1&"C"&3+O35,FALSE) | R35: =IFERROR(__xludf.DUMMYFUNCTION("REGEXMATCH($Q35,""Yes"")"),FALSE) -> FALSE | S35: =IFERROR(__xludf.DUMMYFUNCTION("REGEXMATCH($Q35,""No"")"),FALSE) -> FALSE | T35: =IFERROR(__xludf.DUMMYFUNCTION("REGEXMATCH($Q35,""but"")"),FALSE) -> FALSE
B36: =category!B36 -> 3 | C36: =category!C36 -> コミュニケーションツール | M36: 35 | N36: =FLOOR((M36-1)/8,1)+1 -> 5 | O36: =mod(M36-1,8)+1 -> 3 | P36: ='アセスメント'!B37 -> TEAM-5-3 | Q36: =indirect("R"&N36+ 1&"C"&3+O36,FALSE) | R36: =IFERROR(__xludf.DUMMYFUNCTION("REGEXMATCH($Q36,""Yes"")"),FALSE) -> FALSE | S36: =IFERROR(__xludf.DUMMYFUNCTION("REGEXMATCH($Q36,""No"")"),FALSE) -> FALSE | T36: =IFERROR(__xludf.DUMMYFUNCTION("REGEXMATCH($Q36,""but"")"),FALSE) -> FALSE
B37: =category!B37 -> 4 | C37: =category!C37 -> 人事制度・育成戦略 | M37: 36 | N37: =FLOOR((M37-1)/8,1)+1 -> 5 | O37: =mod(M37-1,8)+1 -> 4 | P37: ='アセスメント'!B38 -> TEAM-5-4 | Q37: =indirect("R"&N37+ 1&"C"&3+O37,FALSE) | R37: =IFERROR(__xludf.DUMMYFUNCTION("REGEXMATCH($Q37,""Yes"")"),FALSE) -> FALSE | S37: =IFERROR(__xludf.DUMMYFUNCTION("REGEXMATCH($Q37,""No"")"),FALSE) -> FALSE | T37: =IFERROR(__xludf.DUMMYFUNCTION("REGEXMATCH($Q37,""but"")"),FALSE) -> FALSE
B38: =category!B38 -> 5 | C38: =category!C38 -> デジタル人材採用戦略 | M38: 37 | N38: =FLOOR((M38-1)/8,1)+1 -> 5 | O38: =mod(M38-1,8)+1 -> 5 | P38: ='アセスメント'!B39 -> TEAM-5-5 | Q38: =indirect("R"&N38+ 1&"C"&3+O38,FALSE) | R38: =IFERROR(__xludf.DUMMYFUNCTION("REGEXMATCH($Q38,""Yes"")"),FALSE) -> FALSE | S38: =IFERROR(__xludf.DUMMYFUNCTION("REGEXMATCH($Q38,""No"")"),FALSE) -> FALSE | T38: =IFERROR(__xludf.DUMMYFUNCTION("REGEXMATCH($Q38,""but"")"),FALSE) -> FALSE
B39: =category!B39 -> 6 | C39: =category!C39 -> モダンなITサービスの活用 | M39: 38 | N39: =FLOOR((M39-1)/8,1)+1 -> 5 | O39: =mod(M39-1,8)+1 -> 6 | P39: ='アセスメント'!B40 -> TEAM-5-6 | Q39: =indirect("R"&N39+ 1&"C"&3+O39,FALSE) | R39: =IFERROR(__xludf.DUMMYFUNCTION("REGEXMATCH($Q39,""Yes"")"),FALSE) -> FALSE | S39: =IFERROR(__xludf.DUMMYFUNCTION("REGEXMATCH($Q39,""No"")"),FALSE) -> FALSE | T39: =IFERROR(__xludf.DUMMYFUNCTION("REGEXMATCH($Q39,""but"")"),FALSE) -> FALSE
B40: =category!B40 -> 7 | C40: =category!C40 -> 経営のデジタルファースト | M40: 39 | N40: =FLOOR((M40-1)/8,1)+1 -> 5 | O40: =mod(M40-1,8)+1 -> 7 | P40: ='アセスメント'!B41 -> TEAM-5-7 | Q40: =indirect("R"&N40+ 1&"C"&3+O40,FALSE) | R40: =IFERROR(__xludf.DUMMYFUNCTION("REGEXMATCH($Q40,""Yes"")"),FALSE) -> FALSE | S40: =IFERROR(__xludf.DUMMYFUNCTION("REGEXMATCH($Q40,""No"")"),FALSE) -> FALSE | T40: =IFERROR(__xludf.DUMMYFUNCTION("REGEXMATCH($Q40,""but"")"),FALSE) -> FALSE
B41: =category!B41 -> 8 | C41: =category!C41 -> 攻めのセキュリティ | M41: 40 | N41: =FLOOR((M41-1)/8,1)+1 -> 5 | O41: =mod(M41-1,8)+1 -> 8 | P41: ='アセスメント'!B42 -> TEAM-5-8 | Q41: =indirect("R"&N41+ 1&"C"&3+O41,FALSE) | R41: =IFERROR(__xludf.DUMMYFUNCTION("REGEXMATCH($Q41,""Yes"")"),FALSE) -> FALSE | S41: =IFERROR(__xludf.DUMMYFUNCTION("REGEXMATCH($Q41,""No"")"),FALSE) -> FALSE | T41: =IFERROR(__xludf.DUMMYFUNCTION("REGEXMATCH($Q41,""but"")"),FALSE) -> FALSE
M42: 41 | N42: =FLOOR((M42-1)/8,1)+1 -> 6 | O42: =mod(M42-1,8)+1 -> 1 | P42: ='アセスメント'!B43 -> TEAM-6-1 | Q42: =indirect("R"&N42+ 1&"C"&3+O42,FALSE) | R42: =IFERROR(__xludf.DUMMYFUNCTION("REGEXMATCH($Q42,""Yes"")"),FALSE) -> FALSE | S42: =IFERROR(__xludf.DUMMYFUNCTION("REGEXMATCH($Q42,""No"")"),FALSE) -> FALSE | T42: =IFERROR(__xludf.DUMMYFUNCTION("REGEXMATCH($Q42,""but"")"),FALSE) -> FALSE
M43: 42 | N43: =FLOOR((M43-1)/8,1)+1 -> 6 | O43: =mod(M43-1,8)+1 -> 2 | P43: ='アセスメント'!B44 -> TEAM-6-2 | Q43: =indirect("R"&N43+ 1&"C"&3+O43,FALSE) | R43: =IFERROR(__xludf.DUMMYFUNCTION("REGEXMATCH($Q43,""Yes"")"),FALSE) -> FALSE | S43: =IFERROR(__xludf.DUMMYFUNCTION("REGEXMATCH($Q43,""No"")"),FALSE) -> FALSE | T43: =IFERROR(__xludf.DUMMYFUNCTION("REGEXMATCH($Q43,""but"")"),FALSE) -> FALSE
M44: 43 | N44: =FLOOR((M44-1)/8,1)+1 -> 6 | O44: =mod(M44-1,8)+1 -> 3 | P44: ='アセスメント'!B45 -> TEAM-6-3 | Q44: =indirect("R"&N44+ 1&"C"&3+O44,FALSE) | R44: =IFERROR(__xludf.DUMMYFUNCTION("REGEXMATCH($Q44,""Yes"")"),FALSE) -> FALSE | S44: =IFERROR(__xludf.DUMMYFUNCTION("REGEXMATCH($Q44,""No"")"),FALSE) -> FALSE | T44: =IFERROR(__xludf.DUMMYFUNCTION("REGEXMATCH($Q44,""but"")"),FALSE) -> FALSE
M45: 44 | N45: =FLOOR((M45-1)/8,1)+1 -> 6 | O45: =mod(M45-1,8)+1 -> 4 | P45: ='アセスメント'!B46 -> TEAM-6-4 | Q45: =indirect("R"&N45+ 1&"C"&3+O45,FALSE) | R45: =IFERROR(__xludf.DUMMYFUNCTION("REGEXMATCH($Q45,""Yes"")"),FALSE) -> FALSE | S45: =IFERROR(__xludf.DUMMYFUNCTION("REGEXMATCH($Q45,""No"")"),FALSE) -> FALSE | T45: =IFERROR(__xludf.DUMMYFUNCTION("REGEXMATCH($Q45,""but"")"),FALSE) -> FALSE
M46: 45 | N46: =FLOOR((M46-1)/8,1)+1 -> 6 | O46: =mod(M46-1,8)+1 -> 5 | P46: ='アセスメント'!B47 -> TEAM-6-5 | Q46: =indirect("R"&N46+ 1&"C"&3+O46,FALSE) | R46: =IFERROR(__xludf.DUMMYFUNCTION("REGEXMATCH($Q46,""Yes"")"),FALSE) -> FALSE | S46: =IFERROR(__xludf.DUMMYFUNCTION("REGEXMATCH($Q46,""No"")"),FALSE) -> FALSE | T46: =IFERROR(__xludf.DUMMYFUNCTION("REGEXMATCH($Q46,""but"")"),FALSE) -> FALSE
M47: 46 | N47: =FLOOR((M47-1)/8,1)+1 -> 6 | O47: =mod(M47-1,8)+1 -> 6 | P47: ='アセスメント'!B48 -> TEAM-6-6 | Q47: =indirect("R"&N47+ 1&"C"&3+O47,FALSE) | R47: =IFERROR(__xludf.DUMMYFUNCTION("REGEXMATCH($Q47,""Yes"")"),FALSE) -> FALSE | S47: =IFERROR(__xludf.DUMMYFUNCTION("REGEXMATCH($Q47,""No"")"),FALSE) -> FALSE | T47: =IFERROR(__xludf.DUMMYFUNCTION("REGEXMATCH($Q47,""but"")"),FALSE) -> FALSE
M48: 47 | N48: =FLOOR((M48-1)/8,1)+1 -> 6 | O48: =mod(M48-1,8)+1 -> 7 | P48: ='アセスメント'!B49 -> TEAM-6-7 | Q48: =indirect("R"&N48+ 1&"C"&3+O48,FALSE) | R48: =IFERROR(__xludf.DUMMYFUNCTION("REGEXMATCH($Q48,""Yes"")"),FALSE) -> FALSE | S48: =IFERROR(__xludf.DUMMYFUNCTION("REGEXMATCH($Q48,""No"")"),FALSE) -> FALSE | T48: =IFERROR(__xludf.DUMMYFUNCTION("REGEXMATCH($Q48,""but"")"),FALSE) -> FALSE
M49: 48 | N49: =FLOOR((M49-1)/8,1)+1 -> 6 | O49: =mod(M49-1,8)+1 -> 8 | P49: ='アセスメント'!B50 -> TEAM-6-8 | Q49: =indirect("R"&N49+ 1&"C"&3+O49,FALSE) | R49: =IFERROR(__xludf.DUMMYFUNCTION("REGEXMATCH($Q49,""Yes"")"),FALSE) -> FALSE | S49: =IFERROR(__xludf.DUMMYFUNCTION("REGEXMATCH($Q49,""No"")"),FALSE) -> FALSE | T49: =IFERROR(__xludf.DUMMYFUNCTION("REGEXMATCH($Q49,""but"")"),FALSE) -> FALSE
M50: 49 | N50: =FLOOR((M50-1)/8,1)+1 -> 7 | O50: =mod(M50-1,8)+1 -> 1 | P50: ='アセスメント'!B51 -> TEAM-7-1 | Q50: =indirect("R"&N50+ 1&"C"&3+O50,FALSE) | R50: =IFERROR(__xludf.DUMMYFUNCTION("REGEXMATCH($Q50,""Yes"")"),FALSE) -> FALSE | S50: =IFERROR(__xludf.DUMMYFUNCTION("REGEXMATCH($Q50,""No"")"),FALSE) -> FALSE | T50: =IFERROR(__xludf.DUMMYFUNCTION("REGEXMATCH($Q50,""but"")"),FALSE) -> FALSE
M51: 50 | N51: =FLOOR((M51-1)/8,1)+1 -> 7 | O51: =mod(M51-1,8)+1 -> 2 | P51: ='アセスメント'!B52 -> TEAM-7-2 | Q51: =indirect("R"&N51+ 1&"C"&3+O51,FALSE) | R51: =IFERROR(__xludf.DUMMYFUNCTION("REGEXMATCH($Q51,""Yes"")"),FALSE) -> FALSE | S51: =IFERROR(__xludf.DUMMYFUNCTION("REGEXMATCH($Q51,""No"")"),FALSE) -> FALSE | T51: =IFERROR(__xludf.DUMMYFUNCTION("REGEXMATCH($Q51,""but"")"),FALSE) -> FALSE
M52: 51 | N52: =FLOOR((M52-1)/8,1)+1 -> 7 | O52: =mod(M52-1,8)+1 -> 3 | P52: ='アセスメント'!B53 -> TEAM-7-3 | Q52: =indirect("R"&N52+ 1&"C"&3+O52,FALSE) | R52: =IFERROR(__xludf.DUMMYFUNCTION("REGEXMATCH($Q52,""Yes"")"),FALSE) -> FALSE | S52: =IFERROR(__xludf.DUMMYFUNCTION("REGEXMATCH($Q52,""No"")"),FALSE) -> FALSE | T52: =IFERROR(__xludf.DUMMYFUNCTION("REGEXMATCH($Q52,""but"")"),FALSE) -> FALSE
M53: 52 | N53: =FLOOR((M53-1)/8,1)+1 -> 7 | O53: =mod(M53-1,8)+1 -> 4 | P53: ='アセスメント'!B54 -> TEAM-7-4 | Q53: =indirect("R"&N53+ 1&"C"&3+O53,FALSE) | R53: =IFERROR(__xludf.DUMMYFUNCTION("REGEXMATCH($Q53,""Yes"")"),FALSE) -> FALSE | S53: =IFERROR(__xludf.DUMMYFUNCTION("REGEXMATCH($Q53,""No"")"),FALSE) -> FALSE | T53: =IFERROR(__xludf.DUMMYFUNCTION("REGEXMATCH($Q53,""but"")"),FALSE) -> FALSE
M54: 53 | N54: =FLOOR((M54-1)/8,1)+1 -> 7 | O54: =mod(M54-1,8)+1 -> 5 | P54: ='アセスメント'!B55 -> TEAM-7-5 | Q54: =indirect("R"&N54+ 1&"C"&3+O54,FALSE) | R54: =IFERROR(__xludf.DUMMYFUNCTION("REGEXMATCH($Q54,""Yes"")"),FALSE) -> FALSE | S54: =IFERROR(__xludf.DUMMYFUNCTION("REGEXMATCH($Q54,""No"")"),FALSE) -> FALSE | T54: =IFERROR(__xludf.DUMMYFUNCTION("REGEXMATCH($Q54,""but"")"),FALSE) -> FALSE
M55: 54 | N55: =FLOOR((M55-1)/8,1)+1 -> 7 | O55: =mod(M55-1,8)+1 -> 6 | P55: ='アセスメント'!B56 -> TEAM-7-6 | Q55: =indirect("R"&N55+ 1&"C"&3+O55,FALSE) | R55: =IFERROR(__xludf.DUMMYFUNCTION("REGEXMATCH($Q55,""Yes"")"),FALSE) -> FALSE | S55: =IFERROR(__xludf.DUMMYFUNCTION("REGEXMATCH($Q55,""No"")"),FALSE) -> FALSE | T55: =IFERROR(__xludf.DUMMYFUNCTION("REGEXMATCH($Q55,""but"")"),FALSE) -> FALSE
M56: 55 | N56: =FLOOR((M56-1)/8,1)+1 -> 7 | O56: =mod(M56-1,8)+1 -> 7 | P56: ='アセスメント'!B57 -> TEAM-7-7 | Q56: =indirect("R"&N56+ 1&"C"&3+O56,FALSE) | R56: =IFERROR(__xludf.DUMMYFUNCTION("REGEXMATCH($Q56,""Yes"")"),FALSE) -> FALSE | S56: =IFERROR(__xludf.DUMMYFUNCTION("REGEXMATCH($Q56,""No"")"),FALSE) -> FALSE | T56: =IFERROR(__xludf.DUMMYFUNCTION("REGEXMATCH($Q56,""but"")"),FALSE) -> FALSE
M57: 56 | N57: =FLOOR((M57-1)/8,1)+1 -> 7 | O57: =mod(M57-1,8)+1 -> 8 | P57: ='アセスメント'!B58 -> TEAM-7-8 | Q57: =indirect("R"&N57+ 1&"C"&3+O57,FALSE) | R57: =IFERROR(__xludf.DUMMYFUNCTION("REGEXMATCH($Q57,""Yes"")"),FALSE) -> FALSE | S57: =IFERROR(__xludf.DUMMYFUNCTION("REGEXMATCH($Q57,""No"")"),FALSE) -> FALSE | T57: =IFERROR(__xludf.DUMMYFUNCTION("REGEXMATCH($Q57,""but"")"),FALSE) -> FALSE
M58: 57 | N58: =FLOOR((M58-1)/8,1)+1 -> 8 | O58: =mod(M58-1,8)+1 -> 1 | P58: ='アセスメント'!B59 -> TEAM-8-1 | Q58: =indirect("R"&N58+ 1&"C"&3+O58,FALSE) | R58: =IFERROR(__xludf.DUMMYFUNCTION("REGEXMATCH($Q58,""Yes"")"),FALSE) -> FALSE | S58: =IFERROR(__xludf.DUMMYFUNCTION("REGEXMATCH($Q58,""No"")"),FALSE) -> FALSE | T58: =IFERROR(__xludf.DUMMYFUNCTION("REGEXMATCH($Q58,""but"")"),FALSE) -> FALSE
M59: 58 | N59: =FLOOR((M59-1)/8,1)+1 -> 8 | O59: =mod(M59-1,8)+1 -> 2 | P59: ='アセスメント'!B60 -> TEAM-8-2 | Q59: =indirect("R"&N59+ 1&"C"&3+O59,FALSE) | R59: =IFERROR(__xludf.DUMMYFUNCTION("REGEXMATCH($Q59,""Yes"")"),FALSE) -> FALSE | S59: =IFERROR(__xludf.DUMMYFUNCTION("REGEXMATCH($Q59,""No"")"),FALSE) -> FALSE | T59: =IFERROR(__xludf.DUMMYFUNCTION("REGEXMATCH($Q59,""but"")"),FALSE) -> FALSE
M60: 59 | N60: =FLOOR((M60-1)/8,1)+1 -> 8 | O60: =mod(M60-1,8)+1 -> 3 | P60: ='アセスメント'!B61 -> TEAM-8-3 | Q60: =indirect("R"&N60+ 1&"C"&3+O60,FALSE) | R60: =IFERROR(__xludf.DUMMYFUNCTION("REGEXMATCH($Q60,""Yes"")"),FALSE) -> FALSE | S60: =IFERROR(__xludf.DUMMYFUNCTION("REGEXMATCH($Q60,""No"")"),FALSE) -> FALSE | T60: =IFERROR(__xludf.DUMMYFUNCTION("REGEXMATCH($Q60,""but"")"),FALSE) -> FALSE
M61: 60 | N61: =FLOOR((M61-1)/8,1)+1 -> 8 | O61: =mod(M61-1,8)+1 -> 4 | P61: ='アセスメント'!B62 -> TEAM-8-4 | Q61: =indirect("R"&N61+ 1&"C"&3+O61,FALSE) | R61: =IFERROR(__xludf.DUMMYFUNCTION("REGEXMATCH($Q61,""Yes"")"),FALSE) -> FALSE | S61: =IFERROR(__xludf.DUMMYFUNCTION("REGEXMATCH($Q61,""No"")"),FALSE) -> FALSE | T61: =IFERROR(__xludf.DUMMYFUNCTION("REGEXMATCH($Q61,""but"")"),FALSE) -> FALSE
M62: 61 | N62: =FLOOR((M62-1)/8,1)+1 -> 8 | O62: =mod(M62-1,8)+1 -> 5 | P62: ='アセスメント'!B63 -> TEAM-8-5 | Q62: =indirect("R"&N62+ 1&"C"&3+O62,FALSE) | R62: =IFERROR(__xludf.DUMMYFUNCTION("REGEXMATCH($Q62,""Yes"")"),FALSE) -> FALSE | S62: =IFERROR(__xludf.DUMMYFUNCTION("REGEXMATCH($Q62,""No"")"),FALSE) -> FALSE | T62: =IFERROR(__xludf.DUMMYFUNCTION("REGEXMATCH($Q62,""but"")"),FALSE) -> FALSE
M63: 62 | N63: =FLOOR((M63-1)/8,1)+1 -> 8 | O63: =mod(M63-1,8)+1 -> 6 | P63: ='アセスメント'!B64 -> TEAM-8-6 | Q63: =indirect("R"&N63+ 1&"C"&3+O63,FALSE) | R63: =IFERROR(__xludf.DUMMYFUNCTION("REGEXMATCH($Q63,""Yes"")"),FALSE) -> FALSE | S63: =IFERROR(__xludf.DUMMYFUNCTION("REGEXMATCH($Q63,""No"")"),FALSE) -> FALSE | T63: =IFERROR(__xludf.DUMMYFUNCTION("REGEXMATCH($Q63,""but"")"),FALSE) -> FALSE
M64: 63 | N64: =FLOOR((M64-1)/8,1)+1 -> 8 | O64: =mod(M64-1,8)+1 -> 7 | P64: ='アセスメント'!B65 -> TEAM-8-7 | Q64: =indirect("R"&N64+ 1&"C"&3+O64,FALSE) | R64: =IFERROR(__xludf.DUMMYFUNCTION("REGEXMATCH($Q64,""Yes"")"),FALSE) -> FALSE | S64: =IFERROR(__xludf.DUMMYFUNCTION("REGEXMATCH($Q64,""No"")"),FALSE) -> FALSE | T64: =IFERROR(__xludf.DUMMYFUNCTION("REGEXMATCH($Q64,""but"")"),FALSE) -> FALSE
M65: 64 | N65: =FLOOR((M65-1)/8,1)+1 -> 8 | O65: =mod(M65-1,8)+1 -> 8 | P65: ='アセスメント'!B66 -> TEAM-8-8 | Q65: =indirect("R"&N65+ 1&"C"&3+O65,FALSE) | R65: =IFERROR(__xludf.DUMMYFUNCTION("REGEXMATCH($Q65,""Yes"")"),FALSE) -> FALSE | S65: =IFERROR(__xludf.DUMMYFUNCTION("REGEXMATCH($Q65,""No"")"),FALSE) -> FALSE | T65: =IFERROR(__xludf.DUMMYFUNCTION("REGEXMATCH($Q65,""but"")"),FALSE) -> FALSE
M66: 65 | N66: =FLOOR((M66-1)/8,1)+1 -> 9 | O66: =mod(M66-1,8)+1 -> 1 | P66: ='アセスメント'!B67 -> SYSTEM-1-1 | Q66: =indirect("R"&N66+ 1&"C"&3+O66,FALSE) | R66: =IFERROR(__xludf.DUMMYFUNCTION("REGEXMATCH($Q66,""Yes"")"),FALSE) -> FALSE | S66: =IFERROR(__xludf.DUMMYFUNCTION("REGEXMATCH($Q66,""No"")"),FALSE) -> FALSE | T66: =IFERROR(__xludf.DUMMYFUNCTION("REGEXMATCH($Q66,""but"")"),FALSE) -> FALSE
M67: 66 | N67: =FLOOR((M67-1)/8,1)+1 -> 9 | O67: =mod(M67-1,8)+1 -> 2 | P67: ='アセスメント'!B68 -> SYSTEM-1-2 | Q67: =indirect("R"&N67+ 1&"C"&3+O67,FALSE) | R67: =IFERROR(__xludf.DUMMYFUNCTION("REGEXMATCH($Q67,""Yes"")"),FALSE) -> FALSE | S67: =IFERROR(__xludf.DUMMYFUNCTION("REGEXMATCH($Q67,""No"")"),FALSE) -> FALSE | T67: =IFERROR(__xludf.DUMMYFUNCTION("REGEXMATCH($Q67,""but"")"),FALSE) -> FALSE
M68: 67 | N68: =FLOOR((M68-1)/8,1)+1 -> 9 | O68: =mod(M68-1,8)+1 -> 3 | P68: ='アセスメント'!B69 -> SYSTEM-1-3 | Q68: =indirect("R"&N68+ 1&"C"&3+O68,FALSE) | R68: =IFERROR(__xludf.DUMMYFUNCTION("REGEXMATCH($Q68,""Yes"")"),FALSE) -> FALSE | S68: =IFERROR(__xludf.DUMMYFUNCTION("REGEXMATCH($Q68,""No"")"),FALSE) -> FALSE | T68: =IFERROR(__xludf.DUMMYFUNCTION("REGEXMATCH($Q68,""but"")"),FALSE) -> FALSE
M69: 68 | N69: =FLOOR((M69-1)/8,1)+1 -> 9 | O69: =mod(M69-1,8)+1 -> 4 | P69: ='アセスメント'!B70 -> SYSTEM-1-4 | Q69: =indirect("R"&N69+ 1&"C"&3+O69,FALSE) | R69: =IFERROR(__xludf.DUMMYFUNCTION("REGEXMATCH($Q69,""Yes"")"),FALSE) -> FALSE | S69: =IFERROR(__xludf.DUMMYFUNCTION("REGEXMATCH($Q69,""No"")"),FALSE) -> FALSE | T69: =IFERROR(__xludf.DUMMYFUNCTION("REGEXMATCH($Q69,""but"")"),FALSE) -> FALSE
M70: 69 | N70: =FLOOR((M70-1)/8,1)+1 -> 9 | O70: =mod(M70-1,8)+1 -> 5 | P70: ='アセスメント'!B71 -> SYSTEM-1-5 | Q70: =indirect("R"&N70+ 1&"C"&3+O70,FALSE) | R70: =IFERROR(__xludf.DUMMYFUNCTION("REGEXMATCH($Q70,""Yes"")"),FALSE) -> FALSE | S70: =IFERROR(__xludf.DUMMYFUNCTION("REGEXMATCH($Q70,""No"")"),FALSE) -> FALSE | T70: =IFERROR(__xludf.DUMMYFUNCTION("REGEXMATCH($Q70,""but"")"),FALSE) -> FALSE
M71: 70 | N71: =FLOOR((M71-1)/8,1)+1 -> 9 | O71: =mod(M71-1,8)+1 -> 6 | P71: ='アセスメント'!B72 -> SYSTEM-1-6 | Q71: =indirect("R"&N71+ 1&"C"&3+O71,FALSE) | R71: =IFERROR(__xludf.DUMMYFUNCTION("REGEXMATCH($Q71,""Yes"")"),FALSE) -> FALSE | S71: =IFERROR(__xludf.DUMMYFUNCTION("REGEXMATCH($Q71,""No"")"),FALSE) -> FALSE | T71: =IFERROR(__xludf.DUMMYFUNCTION("REGEXMATCH($Q71,""but"")"),FALSE) -> FALSE
M72: 71 | N72: =FLOOR((M72-1)/8,1)+1 -> 9 | O72: =mod(M72-1,8)+1 -> 7 | P72: ='アセスメント'!B73 -> SYSTEM-1-7 | Q72: =indirect("R"&N72+ 1&"C"&3+O72,FALSE) | R72: =IFERROR(__xludf.DUMMYFUNCTION("REGEXMATCH($Q72,""Yes"")"),FALSE) -> FALSE | S72: =IFERROR(__xludf.DUMMYFUNCTION("REGEXMATCH($Q72,""No"")"),FALSE) -> FALSE | T72: =IFERROR(__xludf.DUMMYFUNCTION("REGEXMATCH($Q72,""but"")"),FALSE) -> FALSE
M73: 72 | N73: =FLOOR((M73-1)/8,1)+1 -> 9 | O73: =mod(M73-1,8)+1 -> 8 | P73: ='アセスメント'!B74 -> SYSTEM-1-8 | Q73: =indirect("R"&N73+ 1&"C"&3+O73,FALSE) | R73: =IFERROR(__xludf.DUMMYFUNCTION("REGEXMATCH($Q73,""Yes"")"),FALSE) -> FALSE | S73: =IFERROR(__xludf.DUMMYFUNCTION("REGEXMATCH($Q73,""No"")"),FALSE) -> FALSE | T73: =IFERROR(__xludf.DUMMYFUNCTION("REGEXMATCH($Q73,""but"")"),FALSE) -> FALSE
M74: 73 | N74: =FLOOR((M74-1)/8,1)+1 -> 10 | O74: =mod(M74-1,8)+1 -> 1 | P74: ='アセスメント'!B75 -> SYSTEM-2-1 | Q74: =indirect("R"&N74+ 1&"C"&3+O74,FALSE) | R74: =IFERROR(__xludf.DUMMYFUNCTION("REGEXMATCH($Q74,""Yes"")"),FALSE) -> FALSE | S74: =IFERROR(__xludf.DUMMYFUNCTION("REGEXMATCH($Q74,""No"")"),FALSE) -> FALSE | T74: =IFERROR(__xludf.DUMMYFUNCTION("REGEXMATCH($Q74,""but"")"),FALSE) -> FALSE
M75: 74 | N75: =FLOOR((M75-1)/8,1)+1 -> 10 | O75: =mod(M75-1,8)+1 -> 2 | P75: ='アセスメント'!B76 -> SYSTEM-2-2 | Q75: =indirect("R"&N75+ 1&"C"&3+O75,FALSE) | R75: =IFERROR(__xludf.DUMMYFUNCTION("REGEXMATCH($Q75,""Yes"")"),FALSE) -> FALSE | S75: =IFERROR(__xludf.DUMMYFUNCTION("REGEXMATCH($Q75,""No"")"),FALSE) -> FALSE | T75: =IFERROR(__xludf.DUMMYFUNCTION("REGEXMATCH($Q75,""but"")"),FALSE) -> FALSE
M76: 75 | N76: =FLOOR((M76-1)/8,1)+1 -> 10 | O76: =mod(M76-1,8)+1 -> 3 | P76: ='アセスメント'!B77 -> SYSTEM-2-3 | Q76: =indirect("R"&N76+ 1&"C"&3+O76,FALSE) | R76: =IFERROR(__xludf.DUMMYFUNCTION("REGEXMATCH($Q76,""Yes"")"),FALSE) -> FALSE | S76: =IFERROR(__xludf.DUMMYFUNCTION("REGEXMATCH($Q76,""No"")"),FALSE) -> FALSE | T76: =IFERROR(__xludf.DUMMYFUNCTION("REGEXMATCH($Q76,""but"")"),FALSE) -> FALSE
M77: 76 | N77: =FLOOR((M77-1)/8,1)+1 -> 10 | O77: =mod(M77-1,8)+1 -> 4 | P77: ='アセスメント'!B78 -> SYSTEM-2-4 | Q77: =indirect("R"&N77+ 1&"C"&3+O77,FALSE) | R77: =IFERROR(__xludf.DUMMYFUNCTION("REGEXMATCH($Q77,""Yes"")"),FALSE) -> FALSE | S77: =IFERROR(__xludf.DUMMYFUNCTION("REGEXMATCH($Q77,""No"")"),FALSE) -> FALSE | T77: =IFERROR(__xludf.DUMMYFUNCTION("REGEXMATCH($Q77,""but"")"),FALSE) -> FALSE
M78: 77 | N78: =FLOOR((M78-1)/8,1)+1 -> 10 | O78: =mod(M78-1,8)+1 -> 5 | P78: ='アセスメント'!B79 -> SYSTEM-2-5 | Q78: =indirect("R"&N78+ 1&"C"&3+O78,FALSE) | R78: =IFERROR(__xludf.DUMMYFUNCTION("REGEXMATCH($Q78,""Yes"")"),FALSE) -> FALSE | S78: =IFERROR(__xludf.DUMMYFUNCTION("REGEXMATCH($Q78,""No"")"),FALSE) -> FALSE | T78: =IFERROR(__xludf.DUMMYFUNCTION("REGEXMATCH($Q78,""but"")"),FALSE) -> FALSE
M79: 78 | N79: =FLOOR((M79-1)/8,1)+1 -> 10 | O79: =mod(M79-1,8)+1 -> 6 | P79: ='アセスメント'!B80 -> SYSTEM-2-6 | Q79: =indirect("R"&N79+ 1&"C"&3+O79,FALSE) | R79: =IFERROR(__xludf.DUMMYFUNCTION("REGEXMATCH($Q79,""Yes"")"),FALSE) -> FALSE | S79: =IFERROR(__xludf.DUMMYFUNCTION("REGEXMATCH($Q79,""No"")"),FALSE) -> FALSE | T79: =IFERROR(__xludf.DUMMYFUNCTION("REGEXMATCH($Q79,""but"")"),FALSE) -> FALSE
M80: 79 | N80: =FLOOR((M80-1)/8,1)+1 -> 10 | O80: =mod(M80-1,8)+1 -> 7 | P80: ='アセスメント'!B81 -> SYSTEM-2-7 | Q80: =indirect("R"&N80+ 1&"C"&3+O80,FALSE) | R80: =IFERROR(__xludf.DUMMYFUNCTION("REGEXMATCH($Q80,""Yes"")"),FALSE) -> FALSE | S80: =IFERROR(__xludf.DUMMYFUNCTION("REGEXMATCH($Q80,""No"")"),FALSE) -> FALSE | T80: =IFERROR(__xludf.DUMMYFUNCTION("REGEXMATCH($Q80,""but"")"),FALSE) -> FALSE
M81: 80 | N81: =FLOOR((M81-1)/8,1)+1 -> 10 | O81: =mod(M81-1,8)+1 -> 8 | P81: ='アセスメント'!B82 -> SYSTEM-2-8 | Q81: =indirect("R"&N81+ 1&"C"&3+O81,FALSE) | R81: =IFERROR(__xludf.DUMMYFUNCTION("REGEXMATCH($Q81,""Yes"")"),FALSE) -> FALSE | S81: =IFERROR(__xludf.DUMMYFUNCTION("REGEXMATCH($Q81,""No"")"),FALSE) -> FALSE | T81: =IFERROR(__xludf.DUMMYFUNCTION("REGEXMATCH($Q81,""but"")"),FALSE) -> FALSE
M82: 81 | N82: =FLOOR((M82-1)/8,1)+1 -> 11 | O82: =mod(M82-1,8)+1 -> 1 | P82: ='アセスメント'!B83 -> SYSTEM-3-1 | Q82: =indirect("R"&N82+ 1&"C"&3+O82,FALSE) | R82: =IFERROR(__xludf.DUMMYFUNCTION("REGEXMATCH($Q82,""Yes"")"),FALSE) -> FALSE | S82: =IFERROR(__xludf.DUMMYFUNCTION("REGEXMATCH($Q82,""No"")"),FALSE) -> FALSE | T82: =IFERROR(__xludf.DUMMYFUNCTION("REGEXMATCH($Q82,""but"")"),FALSE) -> FALSE
M83: 82 | N83: =FLOOR((M83-1)/8,1)+1 -> 11 | O83: =mod(M83-1,8)+1 -> 2 | P83: ='アセスメント'!B84 -> SYSTEM-3-2 | Q83: =indirect("R"&N83+ 1&"C"&3+O83,FALSE) | R83: =IFERROR(__xludf.DUMMYFUNCTION("REGEXMATCH($Q83,""Yes"")"),FALSE) -> FALSE | S83: =IFERROR(__xludf.DUMMYFUNCTION("REGEXMATCH($Q83,""No"")"),FALSE) -> FALSE | T83: =IFERROR(__xludf.DUMMYFUNCTION("REGEXMATCH($Q83,""but"")"),FALSE) -> FALSE
M84: 83 | N84: =FLOOR((M84-1)/8,1)+1 -> 11 | O84: =mod(M84-1,8)+1 -> 3 | P84: ='アセスメント'!B85 -> SYSTEM-3-3 | Q84: =indirect("R"&N84+ 1&"C"&3+O84,FALSE) | R84: =IFERROR(__xludf.DUMMYFUNCTION("REGEXMATCH($Q84,""Yes"")"),FALSE) -> FALSE | S84: =IFERROR(__xludf.DUMMYFUNCTION("REGEXMATCH($Q84,""No"")"),FALSE) -> FALSE | T84: =IFERROR(__xludf.DUMMYFUNCTION("REGEXMATCH($Q84,""but"")"),FALSE) -> FALSE
M85: 84 | N85: =FLOOR((M85-1)/8,1)+1 -> 11 | O85: =mod(M85-1,8)+1 -> 4 | P85: ='アセスメント'!B86 -> SYSTEM-3-4 | Q85: =indirect("R"&N85+ 1&"C"&3+O85,FALSE) | R85: =IFERROR(__xludf.DUMMYFUNCTION("REGEXMATCH($Q85,""Yes"")"),FALSE) -> FALSE | S85: =IFERROR(__xludf.DUMMYFUNCTION("REGEXMATCH($Q85,""No"")"),FALSE) -> FALSE | T85: =IFERROR(__xludf.DUMMYFUNCTION("REGEXMATCH($Q85,""but"")"),FALSE) -> FALSE
M86: 85 | N86: =FLOOR((M86-1)/8,1)+1 -> 11 | O86: =mod(M86-1,8)+1 -> 5 | P86: ='アセスメント'!B87 -> SYSTEM-3-5 | Q86: =indirect("R"&N86+ 1&"C"&3+O86,FALSE) | R86: =IFERROR(__xludf.DUMMYFUNCTION("REGEXMATCH($Q86,""Yes"")"),FALSE) -> FALSE | S86: =IFERROR(__xludf.DUMMYFUNCTION("REGEXMATCH($Q86,""No"")"),FALSE) -> FALSE | T86: =IFERROR(__xludf.DUMMYFUNCTION("REGEXMATCH($Q86,""but"")"),FALSE) -> FALSE
M87: 86 | N87: =FLOOR((M87-1)/8,1)+1 -> 11 | O87: =mod(M87-1,8)+1 -> 6 | P87: ='アセスメント'!B88 -> SYSTEM-3-6 | Q87: =indirect("R"&N87+ 1&"C"&3+O87,FALSE) | R87: =IFERROR(__xludf.DUMMYFUNCTION("REGEXMATCH($Q87,""Yes"")"),FALSE) -> FALSE | S87: =IFERROR(__xludf.DUMMYFUNCTION("REGEXMATCH($Q87,""No"")"),FALSE) -> FALSE | T87: =IFERROR(__xludf.DUMMYFUNCTION("REGEXMATCH($Q87,""but"")"),FALSE) -> FALSE
M88: 87 | N88: =FLOOR((M88-1)/8,1)+1 -> 11 | O88: =mod(M88-1,8)+1 -> 7 | P88: ='アセスメント'!B89 -> SYSTEM-3-7 | Q88: =indirect("R"&N88+ 1&"C"&3+O88,FALSE) | R88: =IFERROR(__xludf.DUMMYFUNCTION("REGEXMATCH($Q88,""Yes"")"),FALSE) -> FALSE | S88: =IFERROR(__xludf.DUMMYFUNCTION("REGEXMATCH($Q88,""No"")"),FALSE) -> FALSE | T88: =IFERROR(__xludf.DUMMYFUNCTION("REGEXMATCH($Q88,""but"")"),FALSE) -> FALSE
M89: 88 | N89: =FLOOR((M89-1)/8,1)+1 -> 11 | O89: =mod(M89-1,8)+1 -> 8 | P89: ='アセスメント'!B90 -> SYSTEM-3-8 | Q89: =indirect("R"&N89+ 1&"C"&3+O89,FALSE) | R89: =IFERROR(__xludf.DUMMYFUNCTION("REGEXMATCH($Q89,""Yes"")"),FALSE) -> FALSE | S89: =IFERROR(__xludf.DUMMYFUNCTION("REGEXMATCH($Q89,""No"")"),FALSE) -> FALSE | T89: =IFERROR(__xludf.DUMMYFUNCTION("REGEXMATCH($Q89,""but"")"),FALSE) -> FALSE
M90: 89 | N90: =FLOOR((M90-1)/8,1)+1 -> 12 | O90: =mod(M90-1,8)+1 -> 1 | P90: ='アセスメント'!B91 -> SYSTEM-4-1 | Q90: =indirect("R"&N90+ 1&"C"&3+O90,FALSE) | R90: =IFERROR(__xludf.DUMMYFUNCTION("REGEXMATCH($Q90,""Yes"")"),FALSE) -> FALSE | S90: =IFERROR(__xludf.DUMMYFUNCTION("REGEXMATCH($Q90,""No"")"),FALSE) -> FALSE | T90: =IFERROR(__xludf.DUMMYFUNCTION("REGEXMATCH($Q90,""but"")"),FALSE) -> FALSE
M91: 90 | N91: =FLOOR((M91-1)/8,1)+1 -> 12 | O91: =mod(M91-1,8)+1 -> 2 | P91: ='アセスメント'!B92 -> SYSTEM-4-2 | Q91: =indirect("R"&N91+ 1&"C"&3+O91,FALSE) | R91: =IFERROR(__xludf.DUMMYFUNCTION("REGEXMATCH($Q91,""Yes"")"),FALSE) -> FALSE | S91: =IFERROR(__xludf.DUMMYFUNCTION("REGEXMATCH($Q91,""No"")"),FALSE) -> FALSE | T91: =IFERROR(__xludf.DUMMYFUNCTION("REGEXMATCH($Q91,""but"")"),FALSE) -> FALSE
M92: 91 | N92: =FLOOR((M92-1)/8,1)+1 -> 12 | O92: =mod(M92-1,8)+1 -> 3 | P92: ='アセスメント'!B93 -> SYSTEM-4-3 | Q92: =indirect("R"&N92+ 1&"C"&3+O92,FALSE) | R92: =IFERROR(__xludf.DUMMYFUNCTION("REGEXMATCH($Q92,""Yes"")"),FALSE) -> FALSE | S92: =IFERROR(__xludf.DUMMYFUNCTION("REGEXMATCH($Q92,""No"")"),FALSE) -> FALSE | T92: =IFERROR(__xludf.DUMMYFUNCTION("REGEXMATCH($Q92,""but"")"),FALSE) -> FALSE
M93: 92 | N93: =FLOOR((M93-1)/8,1)+1 -> 12 | O93: =mod(M93-1,8)+1 -> 4 | P93: ='アセスメント'!B94 -> SYSTEM-4-4 | Q93: =indirect("R"&N93+ 1&"C"&3+O93,FALSE) | R93: =IFERROR(__xludf.DUMMYFUNCTION("REGEXMATCH($Q93,""Yes"")"),FALSE) -> FALSE | S93: =IFERROR(__xludf.DUMMYFUNCTION("REGEXMATCH($Q93,""No"")"),FALSE) -> FALSE | T93: =IFERROR(__xludf.DUMMYFUNCTION("REGEXMATCH($Q93,""but"")"),FALSE) -> FALSE
M94: 93 | N94: =FLOOR((M94-1)/8,1)+1 -> 12 | O94: =mod(M94-1,8)+1 -> 5 | P94: ='アセスメント'!B95 -> SYSTEM-4-5 | Q94: =indirect("R"&N94+ 1&"C"&3+O94,FALSE) | R94: =IFERROR(__xludf.DUMMYFUNCTION("REGEXMATCH($Q94,""Yes"")"),FALSE) -> FALSE | S94: =IFERROR(__xludf.DUMMYFUNCTION("REGEXMATCH($Q94,""No"")"),FALSE) -> FALSE | T94: =IFERROR(__xludf.DUMMYFUNCTION("REGEXMATCH($Q94,""but"")"),FALSE) -> FALSE
M95: 94 | N95: =FLOOR((M95-1)/8,1)+1 -> 12 | O95: =mod(M95-1,8)+1 -> 6 | P95: ='アセスメント'!B96 -> SYSTEM-4-6 | Q95: =indirect("R"&N95+ 1&"C"&3+O95,FALSE) | R95: =IFERROR(__xludf.DUMMYFUNCTION("REGEXMATCH($Q95,""Yes"")"),FALSE) -> FALSE | S95: =IFERROR(__xludf.DUMMYFUNCTION("REGEXMATCH($Q95,""No"")"),FALSE) -> FALSE | T95: =IFERROR(__xludf.DUMMYFUNCTION("REGEXMATCH($Q95,""but"")"),FALSE) -> FALSE
M96: 95 | N96: =FLOOR((M96-1)/8,1)+1 -> 12 | O96: =mod(M96-1,8)+1 -> 7 | P96: ='アセスメント'!B97 -> SYSTEM-4-7 | Q96: =indirect("R"&N96+ 1&"C"&3+O96,FALSE) | R96: =IFERROR(__xludf.DUMMYFUNCTION("REGEXMATCH($Q96,""Yes"")"),FALSE) -> FALSE | S96: =IFERROR(__xludf.DUMMYFUNCTION("REGEXMATCH($Q96,""No"")"),FALSE) -> FALSE | T96: =IFERROR(__xludf.DUMMYFUNCTION("REGEXMATCH($Q96,""but"")"),FALSE) -> FALSE
M97: 96 | N97: =FLOOR((M97-1)/8,1)+1 -> 12 | O97: =mod(M97-1,8)+1 -> 8 | P97: ='アセスメント'!B98 -> SYSTEM-4-8 | Q97: =indirect("R"&N97+ 1&"C"&3+O97,FALSE) | R97: =IFERROR(__xludf.DUMMYFUNCTION("REGEXMATCH($Q97,""Yes"")"),FALSE) -> FALSE | S97: =IFERROR(__xludf.DUMMYFUNCTION("REGEXMATCH($Q97,""No"")"),FALSE) -> FALSE | T97: =IFERROR(__xludf.DUMMYFUNCTION("REGEXMATCH($Q97,""but"")"),FALSE) -> FALSE
M98: 97 | N98: =FLOOR((M98-1)/8,1)+1 -> 13 | O98: =mod(M98-1,8)+1 -> 1 | P98: ='アセスメント'!B99 -> SYSTEM-5-1 | Q98: =indirect("R"&N98+ 1&"C"&3+O98,FALSE) | R98: =IFERROR(__xludf.DUMMYFUNCTION("REGEXMATCH($Q98,""Yes"")"),FALSE) -> FALSE | S98: =IFERROR(__xludf.DUMMYFUNCTION("REGEXMATCH($Q98,""No"")"),FALSE) -> FALSE | T98: =IFERROR(__xludf.DUMMYFUNCTION("REGEXMATCH($Q98,""but"")"),FALSE) -> FALSE
M99: 98 | N99: =FLOOR((M99-1)/8,1)+1 -> 13 | O99: =mod(M99-1,8)+1 -> 2 | P99: ='アセスメント'!B100 -> SYSTEM-5-2 | Q99: =indirect("R"&N99+ 1&"C"&3+O99,FALSE) | R99: =IFERROR(__xludf.DUMMYFUNCTION("REGEXMATCH($Q99,""Yes"")"),FALSE) -> FALSE | S99: =IFERROR(__xludf.DUMMYFUNCTION("REGEXMATCH($Q99,""No"")"),FALSE) -> FALSE | T99: =IFERROR(__xludf.DUMMYFUNCTION("REGEXMATCH($Q99,""but"")"),FALSE) -> FALSE
M100: 99 | N100: =FLOOR((M100-1)/8,1)+1 -> 13 | O100: =mod(M100-1,8)+1 -> 3 | P100: ='アセスメント'!B101 -> SYSTEM-5-3 | Q100: =indirect("R"&N100+ 1&"C"&3+O100,FALSE) | R100: =IFERROR(__xludf.DUMMYFUNCTION("REGEXMATCH($Q100,""Yes"")"),FALSE) -> FALSE | S100: =IFERROR(__xludf.DUMMYFUNCTION("REGEXMATCH($Q100,""No"")"),FALSE) -> FALSE | T100: =IFERROR(__xludf.DUMMYFUNCTION("REGEXMATCH($Q100,""but"")"),FALSE) -> FALSE
...

Sheet progressbar
B5: 記入済み | C5: =countif(counting!I2:I321,TRUE) -> 0
B6: ブロック数 | C6: 20
B7: 総数 | C7: 320
B8: 単位 | C8: =C7/C6 -> 16
E9: ="progress :"&textjoin("",TRUE,D10:D29)&" "&C5 & "/" &C7 -> progress :□□□□□□□□□□□□□□□□□□□□ 0/320
B10: 1 | C10: =B10*$C$8 -> 16 | D10: =if($C$5>=C10,"■","□") -> □
B11: 2 | C11: =B11*$C$8 -> 32 | D11: =if($C$5>=C11,"■","□") -> □ | E11: チーム | F11: 3 | G11: =E$17&F11 -> #gid=0&range=F3
B12: 3 | C12: =B12*$C$8 -> 48 | D12: =if($C$5>=C12,"■","□") -> □ | E12: システム | F12: =64+F11 -> 67 | G12: =E$17&F12 -> #gid=0&range=F67
B13: 4 | C13: =B13*$C$8 -> 64 | D13: =if($C$5>=C13,"■","□") -> □ | E13: データ駆動 | F13: =64+F12 -> 131 | G13: =E$17&F13 -> #gid=0&range=F131
B14: 5 | C14: =B14*$C$8 -> 80 | D14: =if($C$5>=C14,"■","□") -> □ | E14: デザイン思考 | F14: =64+F13 -> 195 | G14: =E$17&F14 -> #gid=0&range=F195
B15: 6 | C15: =B15*$C$8 -> 96 | D15: =if($C$5>=C15,"■","□") -> □ | E15: コーポレート | F15: =64+F14 -> 259 | G15: =E$17&F15 -> #gid=0&range=F259
B16: 7 | C16: =B16*$C$8 -> 112 | D16: =if($C$5>=C16,"■","□") -> □
B17: 8 | C17: =B17*$C$8 -> 128 | D17: =if($C$5>=C17,"■","□") -> □ | E17: #gid=0&range=F
B18: 9 | C18: =B18*$C$8 -> 144 | D18: =if($C$5>=C18,"■","□") -> □
B19: 10 | C19: =B19*$C$8 -> 160 | D19: =if($C$5>=C19,"■","□") -> □
B20: 11 | C20: =B20*$C$8 -> 176 | D20: =if($C$5>=C20,"■","□") -> □ | E20: =MATCH(FALSE,counting!I2:I330,0)+2 -> 3
B21: 12 | C21: =B21*$C$8 -> 192 | D21: =if($C$5>=C21,"■","□") -> □ | E21: =E17&E20 -> #gid=0&range=F3
B22: 13 | C22: =B22*$C$8 -> 208 | D22: =if($C$5>=C22,"■","□") -> □
B23: 14 | C23: =B23*$C$8 -> 224 | D23: =if($C$5>=C23,"■","□") -> □
B24: 15 | C24: =B24*$C$8 -> 240 | D24: =if($C$5>=C24,"■","□") -> □
B25: 16 | C25: =B25*$C$8 -> 256 | D25: =if($C$5>=C25,"■","□") -> □
B26: 17 | C26: =B26*$C$8 -> 272 | D26: =if($C$5>=C26,"■","□") -> □
B27: 18 | C27: =B27*$C$8 -> 288 | D27: =if($C$5>=C27,"■","□") -> □
B28: 19 | C28: =B28*$C$8 -> 304 | D28: =if($C$5>=C28,"■","□") -> □
B29: 20 | C29: =B29*$C$8 -> 320 | D29: =if($C$5>=C29,"■","□") -> □

Sheet rating
B2: 偏差値下限 | C2: 偏差値上限 | D2: レイティング
B3: 0 | C3: 33 | D3: DD
B4: =C3 -> 33 | C4: 39 | D4: DDD
B5: =C4 -> 39 | C5: 42 | D5: C
B6: =C5 -> 42 | C6: 45 | D6: CC
B7: =C6 -> 45 | C7: 48 | D7: CCC
B8: =C7 -> 48 | C8: 52 | D8: B
B9: =C8 -> 52 | C9: 55 | D9: BB
B10: =C9 -> 55 | C10: 58 | D10: BBB
B11: =C10 -> 58 | C11: 61 | D11: A
B12: =C11 -> 61 | C12: 67 | D12: AA
B13: =C12 -> 67 | C13: 100 | D13: AAA
A17: 1 | B17: =vlookup(A17,rating!$B$2:$D$13,3,TRUE) -> DD
A18: 2 | B18: =vlookup(A18,rating!$B$2:$D$13,3,TRUE) -> DD
A19: 3 | B19: =vlookup(A19,rating!$B$2:$D$13,3,TRUE) -> DD
A20: 4 | B20: =vlookup(A20,rating!$B$2:$D$13,3,TRUE) -> DD
A21: 5 | B21: =vlookup(A21,rating!$B$2:$D$13,3,TRUE) -> DD
A22: 6 | B22: =vlookup(A22,rating!$B$2:$D$13,3,TRUE) -> DD
A23: 7 | B23: =vlookup(A23,rating!$B$2:$D$13,3,TRUE) -> DD
A24: 8 | B24: =vlookup(A24,rating!$B$2:$D$13,3,TRUE) -> DD
A25: 9 | B25: =vlookup(A25,rating!$B$2:$D$13,3,TRUE) -> DD
A26: 10 | B26: =vlookup(A26,rating!$B$2:$D$13,3,TRUE) -> DD
A27: 11 | B27: =vlookup(A27,rating!$B$2:$D$13,3,TRUE) -> DD
A28: 12 | B28: =vlookup(A28,rating!$B$2:$D$13,3,TRUE) -> DD
... A119: 103 | B119: =vlookup(A119,rating!$B$2:$D$13,3,TRUE) -> AAA

Sheet counting
C1: yes | D1: no | E1: but | F1: valid | G1: fill | H1: alert | I1: count | J1: isantipattern | L1: point
A2: ='アセスメント'!B3 -> TEAM-1-1 | B2: =criteria!D2 -> メトリクスの計測 | C2: ='アセスメント'!F3 -> FALSE | D2: ='アセスメント'!G3 -> FALSE | E2: ='アセスメント'!H3 -> FALSE | F2: =not(and(C2,D2)) -> TRUE | G2: =or(C2,D2) -> FALSE | H2: =and(G2,not(F2)) -> FALSE | I2: =and(G2,F2) -> FALSE | J2: =if(B2="アンチパターン",true,false) -> FALSE | K2: =if(E2,0.5,if(C2,1,0)) -> 0 | L2: =if(H2,"@" ,if(G2, if(J2,1-K2,K2),"-")) -> - | M2: =IFERROR(__xludf.DUMMYFUNCTION("split(A2,""-"")"),"TEAM") -> TEAM | N2: =IFERROR(__xludf.DUMMYFUNCTION("""COMPUTED_VALUE"""),1.0) -> 1 | O2: =IFERROR(__xludf.DUMMYFUNCTION("""COMPUTED_VALUE"""),1.0) -> 1
A3: ='アセスメント'!B4 -> TEAM-1-2 | B3: =criteria!D3 -> 学習と改善 | C3: ='アセスメント'!F4 -> FALSE | D3: ='アセスメント'!G4 -> FALSE | E3: ='アセスメント'!H4 -> FALSE | F3: =not(and(C3,D3)) -> TRUE | G3: =or(C3,D3) -> FALSE | H3: =and(G3,not(F3)) -> FALSE | I3: =and(G3,F3) -> FALSE | J3: =if(B3="アンチパターン",true,false) -> FALSE | K3: =if(E3,0.5,if(C3,1,0)) -> 0 | L3: =if(H3,"@" ,if(G3, if(J3,1-K3,K3),"-")) -> - | M3: =IFERROR(__xludf.DUMMYFUNCTION("split(A3,""-"")"),"TEAM") -> TEAM | N3: =IFERROR(__xludf.DUMMYFUNCTION("""COMPUTED_VALUE"""),1.0) -> 1 | O3: =IFERROR(__xludf.DUMMYFUNCTION("""COMPUTED_VALUE"""),2.0) -> 2
A4: ='アセスメント'!B5 -> TEAM-1-3 | B4: =criteria!D4 -> プラクティス | C4: ='アセスメント'!F5 -> FALSE | D4: ='アセスメント'!G5 -> FALSE | E4: ='アセスメント'!H5 -> FALSE | F4: =not(and(C4,D4)) -> TRUE | G4: =or(C4,D4) -> FALSE | H4: =and(G4,not(F4)) -> FALSE | I4: =and(G4,F4) -> FALSE | J4: =if(B4="アンチパターン",true,false) -> FALSE | K4: =if(E4,0.5,if(C4,1,0)) -> 0 | L4: =if(H4,"@" ,if(G4, if(J4,1-K4,K4),"-")) -> - | M4: =IFERROR(__xludf.DUMMYFUNCTION("split(A4,""-"")"),"TEAM") -> TEAM | N4: =IFERROR(__xludf.DUMMYFUNCTION("""COMPUTED_VALUE"""),1.0) -> 1 | O4: =IFERROR(__xludf.DUMMYFUNCTION("""COMPUTED_VALUE"""),3.0) -> 3
A5: ='アセスメント'!B6 -> TEAM-1-4 | B5: =criteria!D5 -> プラクティス | C5: ='アセスメント'!F6 -> FALSE | D5: ='アセスメント'!G6 -> FALSE | E5: ='アセスメント'!H6 -> FALSE | F5: =not(and(C5,D5)) -> TRUE | G5: =or(C5,D5) -> FALSE | H5: =and(G5,not(F5)) -> FALSE | I5: =and(G5,F5) -> FALSE | J5: =if(B5="アンチパターン",true,false) -> FALSE | K5: =if(E5,0.5,if(C5,1,0)) -> 0 | L5: =if(H5,"@" ,if(G5, if(J5,1-K5,K5),"-")) -> - | M5: =IFERROR(__xludf.DUMMYFUNCTION("split(A5,""-"")"),"TEAM") -> TEAM | N5: =IFERROR(__xludf.DUMMYFUNCTION("""COMPUTED_VALUE"""),1.0) -> 1 | O5: =IFERROR(__xludf.DUMMYFUNCTION("""COMPUTED_VALUE"""),4.0) -> 4
A6: ='アセスメント'!B7 -> TEAM-1-5 | B6: =criteria!D6 -> プラクティス | C6: ='アセスメント'!F7 -> FALSE | D6: ='アセスメント'!G7 -> FALSE | E6: ='アセスメント'!H7 -> FALSE | F6: =not(and(C6,D6)) -> TRUE | G6: =or(C6,D6) -> FALSE | H6: =and(G6,not(F6)) -> FALSE | I6: =and(G6,F6) -> FALSE | J6: =if(B6="アンチパターン",true,false) -> FALSE | K6: =if(E6,0.5,if(C6,1,0)) -> 0 | L6: =if(H6,"@" ,if(G6, if(J6,1-K6,K6),"-")) -> - | M6: =IFERROR(__xludf.DUMMYFUNCTION("split(A6,""-"")"),"TEAM") -> TEAM | N6: =IFERROR(__xludf.DUMMYFUNCTION("""COMPUTED_VALUE"""),1.0) -> 1 | O6: =IFERROR(__xludf.DUMMYFUNCTION("""COMPUTED_VALUE"""),5.0) -> 5
A7: ='アセスメント'!B8 -> TEAM-1-6 | B7: =criteria!D7 -> アンチパターン | C7: ='アセスメント'!F8 -> FALSE | D7: ='アセスメント'!G8 -> FALSE | E7: ='アセスメント'!H8 -> FALSE | F7: =not(and(C7,D7)) -> TRUE | G7: =or(C7,D7) -> FALSE | H7: =and(G7,not(F7)) -> FALSE | I7: =and(G7,F7) -> FALSE | J7: =if(B7="アンチパターン",true,false) -> TRUE | K7: =if(E7,0.5,if(C7,1,0)) -> 0 | L7: =if(H7,"@" ,if(G7, if(J7,1-K7,K7),"-")) -> - | M7: =IFERROR(__xludf.DUMMYFUNCTION("split(A7,""-"")"),"TEAM") -> TEAM | N7: =IFERROR(__xludf.DUMMYFUNCTION("""COMPUTED_VALUE"""),1.0) -> 1 | O7: =IFERROR(__xludf.DUMMYFUNCTION("""COMPUTED_VALUE"""),6.0) -> 6
A8: ='アセスメント'!B9 -> TEAM-1-7 | B8: =criteria!D8 -> アンチパターン | C8: ='アセスメント'!F9 -> FALSE | D8: ='アセスメント'!G9 -> FALSE | E8: ='アセスメント'!H9 -> FALSE | F8: =not(and(C8,D8)) -> TRUE | G8: =or(C8,D8) -> FALSE | H8: =and(G8,not(F8)) -> FALSE | I8: =and(G8,F8) -> FALSE | J8: =if(B8="アンチパターン",true,false) -> TRUE | K8: =if(E8,0.5,if(C8,1,0)) -> 0 | L8: =if(H8,"@" ,if(G8, if(J8,1-K8,K8),"-")) -> - | M8: =IFERROR(__xludf.DUMMYFUNCTION("split(A8,""-"")"),"TEAM") -> TEAM | N8: =IFERROR(__xludf.DUMMYFUNCTION("""COMPUTED_VALUE"""),1.0) -> 1 | O8: =IFERROR(__xludf.DUMMYFUNCTION("""COMPUTED_VALUE"""),7.0) -> 7
A9: ='アセスメント'!B10 -> TEAM-1-8 | B9: =criteria!D9 -> アンチパターン | C9: ='アセスメント'!F10 -> FALSE | D9: ='アセスメント'!G10 -> FALSE | E9: ='アセスメント'!H10 -> FALSE | F9: =not(and(C9,D9)) -> TRUE | G9: =or(C9,D9) -> FALSE | H9: =and(G9,not(F9)) -> FALSE | I9: =and(G9,F9) -> FALSE | J9: =if(B9="アンチパターン",true,false) -> TRUE | K9: =if(E9,0.5,if(C9,1,0)) -> 0 | L9: =if(H9,"@" ,if(G9, if(J9,1-K9,K9),"-")) -> - | M9: =IFERROR(__xludf.DUMMYFUNCTION("split(A9,""-"")"),"TEAM") -> TEAM | N9: =IFERROR(__xludf.DUMMYFUNCTION("""COMPUTED_VALUE"""),1.0) -> 1 | O9: =IFERROR(__xludf.DUMMYFUNCTION("""COMPUTED_VALUE"""),8.0) -> 8
A10: ='アセスメント'!B11 -> TEAM-2-1 | B10: =criteria!D10 -> メトリクスの計測 | C10: ='アセスメント'!F11 -> FALSE | D10: ='アセスメント'!G11 -> FALSE | E10: ='アセスメント'!H11 -> FALSE | F10: =not(and(C10,D10)) -> TRUE | G10: =or(C10,D10) -> FALSE | H10: =and(G10,not(F10)) -> FALSE | I10: =and(G10,F10) -> FALSE | J10: =if(B10="アンチパターン",true,false) -> FALSE | K10: =if(E10,0.5,if(C10,1,0)) -> 0 | L10: =if(H10,"@" ,if(G10, if(J10,1-K10,K10),"-")) -> - | M10: =IFERROR(__xludf.DUMMYFUNCTION("split(A10,""-"")"),"TEAM") -> TEAM | N10: =IFERROR(__xludf.DUMMYFUNCTION("""COMPUTED_VALUE"""),2.0) -> 2 | O10: =IFERROR(__xludf.DUMMYFUNCTION("""COMPUTED_VALUE"""),1.0) -> 1
A11: ='アセスメント'!B12 -> TEAM-2-2 | B11: =criteria!D11 -> 学習と改善 | C11: ='アセスメント'!F12 -> FALSE | D11: ='アセスメント'!G12 -> FALSE | E11: ='アセスメント'!H12 -> FALSE | F11: =not(and(C11,D11)) -> TRUE | G11: =or(C11,D11) -> FALSE | H11: =and(G11,not(F11)) -> FALSE | I11: =and(G11,F11) -> FALSE | J11: =if(B11="アンチパターン",true,false) -> FALSE | K11: =if(E11,0.5,if(C11,1,0)) -> 0 | L11: =if(H11,"@" ,if(G11, if(J11,1-K11,K11),"-")) -> - | M11: =IFERROR(__xludf.DUMMYFUNCTION("split(A11,""-"")"),"TEAM") -> TEAM | N11: =IFERROR(__xludf.DUMMYFUNCTION("""COMPUTED_VALUE"""),2.0) -> 2 | O11: =IFERROR(__xludf.DUMMYFUNCTION("""COMPUTED_VALUE"""),2.0) -> 2
A12: ='アセスメント'!B13 -> TEAM-2-3 | B12: =criteria!D12 -> プラクティス | C12: ='アセスメント'!F13 -> FALSE | D12: ='アセスメント'!G13 -> FALSE | E12: ='アセスメント'!H13 -> FALSE | F12: =not(and(C12,D12)) -> TRUE | G12: =or(C12,D12) -> FALSE | H12: =and(G12,not(F12)) -> FALSE | I12: =and(G12,F12) -> FALSE | J12: =if(B12="アンチパターン",true,false) -> FALSE | K12: =if(E12,0.5,if(C12,1,0)) -> 0 | L12: =if(H12,"@" ,if(G12, if(J12,1-K12,K12),"-")) -> - | M12: =IFERROR(__xludf.DUMMYFUNCTION("split(A12,""-"")"),"TEAM") -> TEAM | N12: =IFERROR(__xludf.DUMMYFUNCTION("""COMPUTED_VALUE"""),2.0) -> 2 | O12: =IFERROR(__xludf.DUMMYFUNCTION("""COMPUTED_VALUE"""),3.0) -> 3
A13: ='アセスメント'!B14 -> TEAM-2-4 | B13: =criteria!D13 -> プラクティス | C13: ='アセスメント'!F14 -> FALSE | D13: ='アセスメント'!G14 -> FALSE | E13: ='アセスメント'!H14 -> FALSE | F13: =not(and(C13,D13)) -> TRUE | G13: =or(C13,D13) -> FALSE | H13: =and(G13,not(F13)) -> FALSE | I13: =and(G13,F13) -> FALSE | J13: =if(B13="アンチパターン",true,false) -> FALSE | K13: =if(E13,0.5,if(C13,1,0)) -> 0 | L13: =if(H13,"@" ,if(G13, if(J13,1-K13,K13),"-")) -> - | M13: =IFERROR(__xludf.DUMMYFUNCTION("split(A13,""-"")"),"TEAM") -> TEAM | N13: =IFERROR(__xludf.DUMMYFUNCTION("""COMPUTED_VALUE"""),2.0) -> 2 | O13: =IFERROR(__xludf.DUMMYFUNCTION("""COMPUTED_VALUE"""),4.0) -> 4
A14: ='アセスメント'!B15 -> TEAM-2-5 | B14: =criteria!D14 -> プラクティス | C14: ='アセスメント'!F15 -> FALSE | D14: ='アセスメント'!G15 -> FALSE | E14: ='アセスメント'!H15 -> FALSE | F14: =not(and(C14,D14)) -> TRUE | G14: =or(C14,D14) -> FALSE | H14: =and(G14,not(F14)) -> FALSE | I14: =and(G14,F14) -> FALSE | J14: =if(B14="アンチパターン",true,false) -> FALSE | K14: =if(E14,0.5,if(C14,1,0)) -> 0 | L14: =if(H14,"@" ,if(G14, if(J14,1-K14,K14),"-")) -> - | M14: =IFERROR(__xludf.DUMMYFUNCTION("split(A14,""-"")"),"TEAM") -> TEAM | N14: =IFERROR(__xludf.DUMMYFUNCTION("""COMPUTED_VALUE"""),2.0) -> 2 | O14: =IFERROR(__xludf.DUMMYFUNCTION("""COMPUTED_VALUE"""),5.0) -> 5
A15: ='アセスメント'!B16 -> TEAM-2-6 | B15: =criteria!D15 -> アンチパターン | C15: ='アセスメント'!F16 -> FALSE | D15: ='アセスメント'!G16 -> FALSE | E15: ='アセスメント'!H16 -> FALSE | F15: =not(and(C15,D15)) -> TRUE | G15: =or(C15,D15) -> FALSE | H15: =and(G15,not(F15)) -> FALSE | I15: =and(G15,F15) -> FALSE | J15: =if(B15="アンチパターン",true,false) -> TRUE | K15: =if(E15,0.5,if(C15,1,0)) -> 0 | L15: =if(H15,"@" ,if(G15, if(J15,1-K15,K15),"-")) -> - | M15: =IFERROR(__xludf.DUMMYFUNCTION("split(A15,""-"")"),"TEAM") -> TEAM | N15: =IFERROR(__xludf.DUMMYFUNCTION("""COMPUTED_VALUE"""),2.0) -> 2 | O15: =IFERROR(__xludf.DUMMYFUNCTION("""COMPUTED_VALUE"""),6.0) -> 6
A16: ='アセスメント'!B17 -> TEAM-2-7 | B16: =criteria!D16 -> アンチパターン | C16: ='アセスメント'!F17 -> FALSE | D16: ='アセスメント'!G17 -> FALSE | E16: ='アセスメント'!H17 -> FALSE | F16: =not(and(C16,D16)) -> TRUE | G16: =or(C16,D16) -> FALSE | H16: =and(G16,not(F16)) -> FALSE | I16: =and(G16,F16) -> FALSE | J16: =if(B16="アンチパターン",true,false) -> TRUE | K16: =if(E16,0.5,if(C16,1,0)) -> 0 | L16: =if(H16,"@" ,if(G16, if(J16,1-K16,K16),"-")) -> - | M16: =IFERROR(__xludf.DUMMYFUNCTION("split(A16,""-"")"),"TEAM") -> TEAM | N16: =IFERROR(__xludf.DUMMYFUNCTION("""COMPUTED_VALUE"""),2.0) -> 2 | O16: =IFERROR(__xludf.DUMMYFUNCTION("""COMPUTED_VALUE"""),7.0) -> 7
A17: ='アセスメント'!B18 -> TEAM-2-8 | B17: =criteria!D17 -> アンチパターン | C17: ='アセスメント'!F18 -> FALSE | D17: ='アセスメント'!G18 -> FALSE | E17: ='アセスメント'!H18 -> FALSE | F17: =not(and(C17,D17)) -> TRUE | G17: =or(C17,D17) -> FALSE | H17: =and(G17,not(F17)) -> FALSE | I17: =and(G17,F17) -> FALSE | J17: =if(B17="アンチパターン",true,false) -> TRUE | K17: =if(E17,0.5,if(C17,1,0)) -> 0 | L17: =if(H17,"@" ,if(G17, if(J17,1-K17,K17),"-")) -> - | M17: =IFERROR(__xludf.DUMMYFUNCTION("split(A17,""-"")"),"TEAM") -> TEAM | N17: =IFERROR(__xludf.DUMMYFUNCTION("""COMPUTED_VALUE"""),2.0) -> 2 | O17: =IFERROR(__xludf.DUMMYFUNCTION("""COMPUTED_VALUE"""),8.0) -> 8
A18: ='アセスメント'!B19 -> TEAM-3-1 | B18: =criteria!D18 -> メトリクスの計測 | C18: ='アセスメント'!F19 -> FALSE | D18: ='アセスメント'!G19 -> FALSE | E18: ='アセスメント'!H19 -> FALSE | F18: =not(and(C18,D18)) -> TRUE | G18: =or(C18,D18) -> FALSE | H18: =and(G18,not(F18)) -> FALSE | I18: =and(G18,F18) -> FALSE | J18: =if(B18="アンチパターン",true,false) -> FALSE | K18: =if(E18,0.5,if(C18,1,0)) -> 0 | L18: =if(H18,"@" ,if(G18, if(J18,1-K18,K18),"-")) -> - | M18: =IFERROR(__xludf.DUMMYFUNCTION("split(A18,""-"")"),"TEAM") -> TEAM | N18: =IFERROR(__xludf.DUMMYFUNCTION("""COMPUTED_VALUE"""),3.0) -> 3 | O18: =IFERROR(__xludf.DUMMYFUNCTION("""COMPUTED_VALUE"""),1.0) -> 1
A19: ='アセスメント'!B20 -> TEAM-3-2 | B19: =criteria!D19 -> 学習と改善 | C19: ='アセスメント'!F20 -> FALSE | D19: ='アセスメント'!G20 -> FALSE | E19: ='アセスメント'!H20 -> FALSE | F19: =not(and(C19,D19)) -> TRUE | G19: =or(C19,D19) -> FALSE | H19: =and(G19,not(F19)) -> FALSE | I19: =and(G19,F19) -> FALSE | J19: =if(B19="アンチパターン",true,false) -> FALSE | K19: =if(E19,0.5,if(C19,1,0)) -> 0 | L19: =if(H19,"@" ,if(G19, if(J19,1-K19,K19),"-")) -> - | M19: =IFERROR(__xludf.DUMMYFUNCTION("split(A19,""-"")"),"TEAM") -> TEAM | N19: =IFERROR(__xludf.DUMMYFUNCTION("""COMPUTED_VALUE"""),3.0) -> 3 | O19: =IFERROR(__xludf.DUMMYFUNCTION("""COMPUTED_VALUE"""),2.0) -> 2
A20: ='アセスメント'!B21 -> TEAM-3-3 | B20: =criteria!D20 -> プラクティス | C20: ='アセスメント'!F21 -> FALSE | D20: ='アセスメント'!G21 -> FALSE | E20: ='アセスメント'!H21 -> FALSE | F20: =not(and(C20,D20)) -> TRUE | G20: =or(C20,D20) -> FALSE | H20: =and(G20,not(F20)) -> FALSE | I20: =and(G20,F20) -> FALSE | J20: =if(B20="アンチパターン",true,false) -> FALSE | K20: =if(E20,0.5,if(C20,1,0)) -> 0 | L20: =if(H20,"@" ,if(G20, if(J20,1-K20,K20),"-")) -> - | M20: =IFERROR(__xludf.DUMMYFUNCTION("split(A20,""-"")"),"TEAM") -> TEAM | N20: =IFERROR(__xludf.DUMMYFUNCTION("""COMPUTED_VALUE"""),3.0) -> 3 | O20: =IFERROR(__xludf.DUMMYFUNCTION("""COMPUTED_VALUE"""),3.0) -> 3
A21: ='アセスメント'!B22 -> TEAM-3-4 | B21: =criteria!D21 -> プラクティス | C21: ='アセスメント'!F22 -> FALSE | D21: ='アセスメント'!G22 -> FALSE | E21: ='アセスメント'!H22 -> FALSE | F21: =not(and(C21,D21)) -> TRUE | G21: =or(C21,D21) -> FALSE | H21: =and(G21,not(F21)) -> FALSE | I21: =and(G21,F21) -> FALSE | J21: =if(B21="アンチパターン",true,false) -> FALSE | K21: =if(E21,0.5,if(C21,1,0)) -> 0 | L21: =if(H21,"@" ,if(G21, if(J21,1-K21,K21),"-")) -> - | M21: =IFERROR(__xludf.DUMMYFUNCTION("split(A21,""-"")"),"TEAM") -> TEAM | N21: =IFERROR(__xludf.DUMMYFUNCTION("""COMPUTED_VALUE"""),3.0) -> 3 | O21: =IFERROR(__xludf.DUMMYFUNCTION("""COMPUTED_VALUE"""),4.0) -> 4
A22: ='アセスメント'!B23 -> TEAM-3-5 | B22: =criteria!D22 -> プラクティス | C22: ='アセスメント'!F23 -> FALSE | D22: ='アセスメント'!G23 -> FALSE | E22: ='アセスメント'!H23 -> FALSE | F22: =not(and(C22,D22)) -> TRUE | G22: =or(C22,D22) -> FALSE | H22: =and(G22,not(F22)) -> FALSE | I22: =and(G22,F22) -> FALSE | J22: =if(B22="アンチパターン",true,false) -> FALSE | K22: =if(E22,0.5,if(C22,1,0)) -> 0 | L22: =if(H22,"@" ,if(G22, if(J22,1-K22,K22),"-")) -> - | M22: =IFERROR(__xludf.DUMMYFUNCTION("split(A22,""-"")"),"TEAM") -> TEAM | N22: =IFERROR(__xludf.DUMMYFUNCTION("""COMPUTED_VALUE"""),3.0) -> 3 | O22: =IFERROR(__xludf.DUMMYFUNCTION("""COMPUTED_VALUE"""),5.0) -> 5
A23: ='アセスメント'!B24 -> TEAM-3-6 | B23: =criteria!D23 -> アンチパターン | C23: ='アセスメント'!F24 -> FALSE | D23: ='アセスメント'!G24 -> FALSE | E23: ='アセスメント'!H24 -> FALSE | F23: =not(and(C23,D23)) -> TRUE | G23: =or(C23,D23) -> FALSE | H23: =and(G23,not(F23)) -> FALSE | I23: =and(G23,F23) -> FALSE | J23: =if(B23="アンチパターン",true,false) -> TRUE | K23: =if(E23,0.5,if(C23,1,0)) -> 0 | L23: =if(H23,"@" ,if(G23, if(J23,1-K23,K23),"-")) -> - | M23: =IFERROR(__xludf.DUMMYFUNCTION("split(A23,""-"")"),"TEAM") -> TEAM | N23: =IFERROR(__xludf.DUMMYFUNCTION("""COMPUTED_VALUE"""),3.0) -> 3 | O23: =IFERROR(__xludf.DUMMYFUNCTION("""COMPUTED_VALUE"""),6.0) -> 6
A24: ='アセスメント'!B25 -> TEAM-3-7 | B24: =criteria!D24 -> アンチパターン | C24: ='アセスメント'!F25 -> FALSE | D24: ='アセスメント'!G25 -> FALSE | E24: ='アセスメント'!H25 -> FALSE | F24: =not(and(C24,D24)) -> TRUE | G24: =or(C24,D24) -> FALSE | H24: =and(G24,not(F24)) -> FALSE | I24: =and(G24,F24) -> FALSE | J24: =if(B24="アンチパターン",true,false) -> TRUE | K24: =if(E24,0.5,if(C24,1,0)) -> 0 | L24: =if(H24,"@" ,if(G24, if(J24,1-K24,K24),"-")) -> - | M24: =IFERROR(__xludf.DUMMYFUNCTION("split(A24,""-"")"),"TEAM") -> TEAM | N24: =IFERROR(__xludf.DUMMYFUNCTION("""COMPUTED_VALUE"""),3.0) -> 3 | O24: =IFERROR(__xludf.DUMMYFUNCTION("""COMPUTED_VALUE"""),7.0) -> 7
A25: ='アセスメント'!B26 -> TEAM-3-8 | B25: =criteria!D25 -> アンチパターン | C25: ='アセスメント'!F26 -> FALSE | D25: ='アセスメント'!G26 -> FALSE | E25: ='アセスメント'!H26 -> FALSE | F25: =not(and(C25,D25)) -> TRUE | G25: =or(C25,D25) -> FALSE | H25: =and(G25,not(F25)) -> FALSE | I25: =and(G25,F25) -> FALSE | J25: =if(B25="アンチパターン",true,false) -> TRUE | K25: =if(E25,0.5,if(C25,1,0)) -> 0 | L25: =if(H25,"@" ,if(G25, if(J25,1-K25,K25),"-")) -> - | M25: =IFERROR(__xludf.DUMMYFUNCTION("split(A25,""-"")"),"TEAM") -> TEAM | N25: =IFERROR(__xludf.DUMMYFUNCTION("""COMPUTED_VALUE"""),3.0) -> 3 | O25: =IFERROR(__xludf.DUMMYFUNCTION("""COMPUTED_VALUE"""),8.0) -> 8
A26: ='アセスメント'!B27 -> TEAM-4-1 | B26: =criteria!D26 -> メトリクスの計測 | C26: ='アセスメント'!F27 -> FALSE | D26: ='アセスメント'!G27 -> FALSE | E26: ='アセスメント'!H27 -> FALSE | F26: =not(and(C26,D26)) -> TRUE | G26: =or(C26,D26) -> FALSE | H26: =and(G26,not(F26)) -> FALSE | I26: =and(G26,F26) -> FALSE | J26: =if(B26="アンチパターン",true,false) -> FALSE | K26: =if(E26,0.5,if(C26,1,0)) -> 0 | L26: =if(H26,"@" ,if(G26, if(J26,1-K26,K26),"-")) -> - | M26: =IFERROR(__xludf.DUMMYFUNCTION("split(A26,""-"")"),"TEAM") -> TEAM | N26: =IFERROR(__xludf.DUMMYFUNCTION("""COMPUTED_VALUE"""),4.0) -> 4 | O26: =IFERROR(__xludf.DUMMYFUNCTION("""COMPUTED_VALUE"""),1.0) -> 1
A27: ='アセスメント'!B28 -> TEAM-4-2 | B27: =criteria!D27 -> 学習と改善 | C27: ='アセスメント'!F28 -> FALSE | D27: ='アセスメント'!G28 -> FALSE | E27: ='アセスメント'!H28 -> FALSE | F27: =not(and(C27,D27)) -> TRUE | G27: =or(C27,D27) -> FALSE | H27: =and(G27,not(F27)) -> FALSE | I27: =and(G27,F27) -> FALSE | J27: =if(B27="アンチパターン",true,false) -> FALSE | K27: =if(E27,0.5,if(C27,1,0)) -> 0 | L27: =if(H27,"@" ,if(G27, if(J27,1-K27,K27),"-")) -> - | M27: =IFERROR(__xludf.DUMMYFUNCTION("split(A27,""-"")"),"TEAM") -> TEAM | N27: =IFERROR(__xludf.DUMMYFUNCTION("""COMPUTED_VALUE"""),4.0) -> 4 | O27: =IFERROR(__xludf.DUMMYFUNCTION("""COMPUTED_VALUE"""),2.0) -> 2
A28: ='アセスメント'!B29 -> TEAM-4-3 | B28: =criteria!D28 -> プラクティス | C28: ='アセスメント'!F29 -> FALSE | D28: ='アセスメント'!G29 -> FALSE | E28: ='アセスメント'!H29 -> FALSE | F28: =not(and(C28,D28)) -> TRUE | G28: =or(C28,D28) -> FALSE | H28: =and(G28,not(F28)) -> FALSE | I28: =and(G28,F28) -> FALSE | J28: =if(B28="アンチパターン",true,false) -> FALSE | K28: =if(E28,0.5,if(C28,1,0)) -> 0 | L28: =if(H28,"@" ,if(G28, if(J28,1-K28,K28),"-")) -> - | M28: =IFERROR(__xludf.DUMMYFUNCTION("split(A28,""-"")"),"TEAM") -> TEAM | N28: =IFERROR(__xludf.DUMMYFUNCTION("""COMPUTED_VALUE"""),4.0) -> 4 | O28: =IFERROR(__xludf.DUMMYFUNCTION("""COMPUTED_VALUE"""),3.0) -> 3
A29: ='アセスメント'!B30 -> TEAM-4-4 | B29: =criteria!D29 -> プラクティス | C29: ='アセスメント'!F30 -> FALSE | D29: ='アセスメント'!G30 -> FALSE | E29: ='アセスメント'!H30 -> FALSE | F29: =not(and(C29,D29)) -> TRUE | G29: =or(C29,D29) -> FALSE | H29: =and(G29,not(F29)) -> FALSE | I29: =and(G29,F29) -> FALSE | J29: =if(B29="アンチパターン",true,false) -> FALSE | K29: =if(E29,0.5,if(C29,1,0)) -> 0 | L29: =if(H29,"@" ,if(G29, if(J29,1-K29,K29),"-")) -> - | M29: =IFERROR(__xludf.DUMMYFUNCTION("split(A29,""-"")"),"TEAM") -> TEAM | N29: =IFERROR(__xludf.DUMMYFUNCTION("""COMPUTED_VALUE"""),4.0) -> 4 | O29: =IFERROR(__xludf.DUMMYFUNCTION("""COMPUTED_VALUE"""),4.0) -> 4
A30: ='アセスメント'!B31 -> TEAM-4-5 | B30: =criteria!D30 -> プラクティス | C30: ='アセスメント'!F31 -> FALSE | D30: ='アセスメント'!G31 -> FALSE | E30: ='アセスメント'!H31 -> FALSE | F30: =not(and(C30,D30)) -> TRUE | G30: =or(C30,D30) -> FALSE | H30: =and(G30,not(F30)) -> FALSE | I30: =and(G30,F30) -> FALSE | J30: =if(B30="アンチパターン",true,false) -> FALSE | K30: =if(E30,0.5,if(C30,1,0)) -> 0 | L30: =if(H30,"@" ,if(G30, if(J30,1-K30,K30),"-")) -> - | M30: =IFERROR(__xludf.DUMMYFUNCTION("split(A30,""-"")"),"TEAM") -> TEAM | N30: =IFERROR(__xludf.DUMMYFUNCTION("""COMPUTED_VALUE"""),4.0) -> 4 | O30: =IFERROR(__xludf.DUMMYFUNCTION("""COMPUTED_VALUE"""),5.0) -> 5
A31: ='アセスメント'!B32 -> TEAM-4-6 | B31: =criteria!D31 -> アンチパターン | C31: ='アセスメント'!F32 -> FALSE | D31: ='アセスメント'!G32 -> FALSE | E31: ='アセスメント'!H32 -> FALSE | F31: =not(and(C31,D31)) -> TRUE | G31: =or(C31,D31) -> FALSE | H31: =and(G31,not(F31)) -> FALSE | I31: =and(G31,F31) -> FALSE | J31: =if(B31="アンチパターン",true,false) -> TRUE | K31: =if(E31,0.5,if(C31,1,0)) -> 0 | L31: =if(H31,"@" ,if(G31, if(J31,1-K31,K31),"-")) -> - | M31: =IFERROR(__xludf.DUMMYFUNCTION("split(A31,""-"")"),"TEAM") -> TEAM | N31: =IFERROR(__xludf.DUMMYFUNCTION("""COMPUTED_VALUE"""),4.0) -> 4 | O31: =IFERROR(__xludf.DUMMYFUNCTION("""COMPUTED_VALUE"""),6.0) -> 6
A32: ='アセスメント'!B33 -> TEAM-4-7 | B32: =criteria!D32 -> アンチパターン | C32: ='アセスメント'!F33 -> FALSE | D32: ='アセスメント'!G33 -> FALSE | E32: ='アセスメント'!H33 -> FALSE | F32: =not(and(C32,D32)) -> TRUE | G32: =or(C32,D32) -> FALSE | H32: =and(G32,not(F32)) -> FALSE | I32: =and(G32,F32) -> FALSE | J32: =if(B32="アンチパターン",true,false) -> TRUE | K32: =if(E32,0.5,if(C32,1,0)) -> 0 | L32: =if(H32,"@" ,if(G32, if(J32,1-K32,K32),"-")) -> - | M32: =IFERROR(__xludf.DUMMYFUNCTION("split(A32,""-"")"),"TEAM") -> TEAM | N32: =IFERROR(__xludf.DUMMYFUNCTION("""COMPUTED_VALUE"""),4.0) -> 4 | O32: =IFERROR(__xludf.DUMMYFUNCTION("""COMPUTED_VALUE"""),7.0) -> 7
A33: ='アセスメント'!B34 -> TEAM-4-8 | B33: =criteria!D33 -> アンチパターン | C33: ='アセスメント'!F34 -> FALSE | D33: ='アセスメント'!G34 -> FALSE | E33: ='アセスメント'!H34 -> FALSE | F33: =not(and(C33,D33)) -> TRUE | G33: =or(C33,D33) -> FALSE | H33: =and(G33,not(F33)) -> FALSE | I33: =and(G33,F33) -> FALSE | J33: =if(B33="アンチパターン",true,false) -> TRUE | K33: =if(E33,0.5,if(C33,1,0)) -> 0 | L33: =if(H33,"@" ,if(G33, if(J33,1-K33,K33),"-")) -> - | M33: =IFERROR(__xludf.DUMMYFUNCTION("split(A33,""-"")"),"TEAM") -> TEAM | N33: =IFERROR(__xludf.DUMMYFUNCTION("""COMPUTED_VALUE"""),4.0) -> 4 | O33: =IFERROR(__xludf.DUMMYFUNCTION("""COMPUTED_VALUE"""),8.0) -> 8
A34: ='アセスメント'!B35 -> TEAM-5-1 | B34: =criteria!D34 -> メトリクスの計測 | C34: ='アセスメント'!F35 -> FALSE | D34: ='アセスメント'!G35 -> FALSE | E34: ='アセスメント'!H35 -> FALSE | F34: =not(and(C34,D34)) -> TRUE | G34: =or(C34,D34) -> FALSE | H34: =and(G34,not(F34)) -> FALSE | I34: =and(G34,F34) -> FALSE | J34: =if(B34="アンチパターン",true,false) -> FALSE | K34: =if(E34,0.5,if(C34,1,0)) -> 0 | L34: =if(H34,"@" ,if(G34, if(J34,1-K34,K34),"-")) -> - | M34: =IFERROR(__xludf.DUMMYFUNCTION("split(A34,""-"")"),"TEAM") -> TEAM | N34: =IFERROR(__xludf.DUMMYFUNCTION("""COMPUTED_VALUE"""),5.0) -> 5 | O34: =IFERROR(__xludf.DUMMYFUNCTION("""COMPUTED_VALUE"""),1.0) -> 1
A35: ='アセスメント'!B36 -> TEAM-5-2 | B35: =criteria!D35 -> 学習と改善 | C35: ='アセスメント'!F36 -> FALSE | D35: ='アセスメント'!G36 -> FALSE | E35: ='アセスメント'!H36 -> FALSE | F35: =not(and(C35,D35)) -> TRUE | G35: =or(C35,D35) -> FALSE | H35: =and(G35,not(F35)) -> FALSE | I35: =and(G35,F35) -> FALSE | J35: =if(B35="アンチパターン",true,false) -> FALSE | K35: =if(E35,0.5,if(C35,1,0)) -> 0 | L35: =if(H35,"@" ,if(G35, if(J35,1-K35,K35),"-")) -> - | M35: =IFERROR(__xludf.DUMMYFUNCTION("split(A35,""-"")"),"TEAM") -> TEAM | N35: =IFERROR(__xludf.DUMMYFUNCTION("""COMPUTED_VALUE"""),5.0) -> 5 | O35: =IFERROR(__xludf.DUMMYFUNCTION("""COMPUTED_VALUE"""),2.0) -> 2
A36: ='アセスメント'!B37 -> TEAM-5-3 | B36: =criteria!D36 -> プラクティス | C36: ='アセスメント'!F37 -> FALSE | D36: ='アセスメント'!G37 -> FALSE | E36: ='アセスメント'!H37 -> FALSE | F36: =not(and(C36,D36)) -> TRUE | G36: =or(C36,D36) -> FALSE | H36: =and(G36,not(F36)) -> FALSE | I36: =and(G36,F36) -> FALSE | J36: =if(B36="アンチパターン",true,false) -> FALSE | K36: =if(E36,0.5,if(C36,1,0)) -> 0 | L36: =if(H36,"@" ,if(G36, if(J36,1-K36,K36),"-")) -> - | M36: =IFERROR(__xludf.DUMMYFUNCTION("split(A36,""-"")"),"TEAM") -> TEAM | N36: =IFERROR(__xludf.DUMMYFUNCTION("""COMPUTED_VALUE"""),5.0) -> 5 | O36: =IFERROR(__xludf.DUMMYFUNCTION("""COMPUTED_VALUE"""),3.0) -> 3
A37: ='アセスメント'!B38 -> TEAM-5-4 | B37: =criteria!D37 -> プラクティス | C37: ='アセスメント'!F38 -> FALSE | D37: ='アセスメント'!G38 -> FALSE | E37: ='アセスメント'!H38 -> FALSE | F37: =not(and(C37,D37)) -> TRUE | G37: =or(C37,D37) -> FALSE | H37: =and(G37,not(F37)) -> FALSE | I37: =and(G37,F37) -> FALSE | J37: =if(B37="アンチパターン",true,false) -> FALSE | K37: =if(E37,0.5,if(C37,1,0)) -> 0 | L37: =if(H37,"@" ,if(G37, if(J37,1-K37,K37),"-")) -> - | M37: =IFERROR(__xludf.DUMMYFUNCTION("split(A37,""-"")"),"TEAM") -> TEAM | N37: =IFERROR(__xludf.DUMMYFUNCTION("""COMPUTED_VALUE"""),5.0) -> 5 | O37: =IFERROR(__xludf.DUMMYFUNCTION("""COMPUTED_VALUE"""),4.0) -> 4
A38: ='アセスメント'!B39 -> TEAM-5-5 | B38: =criteria!D38 -> プラクティス | C38: ='アセスメント'!F39 -> FALSE | D38: ='アセスメント'!G39 -> FALSE | E38: ='アセスメント'!H39 -> FALSE | F38: =not(and(C38,D38)) -> TRUE | G38: =or(C38,D38) -> FALSE | H38: =and(G38,not(F38)) -> FALSE | I38: =and(G38,F38) -> FALSE | J38: =if(B38="アンチパターン",true,false) -> FALSE | K38: =if(E38,0.5,if(C38,1,0)) -> 0 | L38: =if(H38,"@" ,if(G38, if(J38,1-K38,K38),"-")) -> - | M38: =IFERROR(__xludf.DUMMYFUNCTION("split(A38,""-"")"),"TEAM") -> TEAM | N38: =IFERROR(__xludf.DUMMYFUNCTION("""COMPUTED_VALUE"""),5.0) -> 5 | O38: =IFERROR(__xludf.DUMMYFUNCTION("""COMPUTED_VALUE"""),5.0) -> 5
A39: ='アセスメント'!B40 -> TEAM-5-6 | B39: =criteria!D39 -> アンチパターン | C39: ='アセスメント'!F40 -> FALSE | D39: ='アセスメント'!G40 -> FALSE | E39: ='アセスメント'!H40 -> FALSE | F39: =not(and(C39,D39)) -> TRUE | G39: =or(C39,D39) -> FALSE | H39: =and(G39,not(F39)) -> FALSE | I39: =and(G39,F39) -> FALSE | J39: =if(B39="アンチパターン",true,false) -> TRUE | K39: =if(E39,0.5,if(C39,1,0)) -> 0 | L39: =if(H39,"@" ,if(G39, if(J39,1-K39,K39),"-")) -> - | M39: =IFERROR(__xludf.DUMMYFUNCTION("split(A39,""-"")"),"TEAM") -> TEAM | N39: =IFERROR(__xludf.DUMMYFUNCTION("""COMPUTED_VALUE"""),5.0) -> 5 | O39: =IFERROR(__xludf.DUMMYFUNCTION("""COMPUTED_VALUE"""),6.0) -> 6
A40: ='アセスメント'!B41 -> TEAM-5-7 | B40: =criteria!D40 -> アンチパターン | C40: ='アセスメント'!F41 -> FALSE | D40: ='アセスメント'!G41 -> FALSE | E40: ='アセスメント'!H41 -> FALSE | F40: =not(and(C40,D40)) -> TRUE | G40: =or(C40,D40) -> FALSE | H40: =and(G40,not(F40)) -> FALSE | I40: =and(G40,F40) -> FALSE | J40: =if(B40="アンチパターン",true,false) -> TRUE | K40: =if(E40,0.5,if(C40,1,0)) -> 0 | L40: =if(H40,"@" ,if(G40, if(J40,1-K40,K40),"-")) -> - | M40: =IFERROR(__xludf.DUMMYFUNCTION("split(A40,""-"")"),"TEAM") -> TEAM | N40: =IFERROR(__xludf.DUMMYFUNCTION("""COMPUTED_VALUE"""),5.0) -> 5 | O40: =IFERROR(__xludf.DUMMYFUNCTION("""COMPUTED_VALUE"""),7.0) -> 7
A41: ='アセスメント'!B42 -> TEAM-5-8 | B41: =criteria!D41 -> アンチパターン | C41: ='アセスメント'!F42 -> FALSE | D41: ='アセスメント'!G42 -> FALSE | E41: ='アセスメント'!H42 -> FALSE | F41: =not(and(C41,D41)) -> TRUE | G41: =or(C41,D41) -> FALSE | H41: =and(G41,not(F41)) -> FALSE | I41: =and(G41,F41) -> FALSE | J41: =if(B41="アンチパターン",true,false) -> TRUE | K41: =if(E41,0.5,if(C41,1,0)) -> 0 | L41: =if(H41,"@" ,if(G41, if(J41,1-K41,K41),"-")) -> - | M41: =IFERROR(__xludf.DUMMYFUNCTION("split(A41,""-"")"),"TEAM") -> TEAM | N41: =IFERROR(__xludf.DUMMYFUNCTION("""COMPUTED_VALUE"""),5.0) -> 5 | O41: =IFERROR(__xludf.DUMMYFUNCTION("""COMPUTED_VALUE"""),8.0) -> 8
A42: ='アセスメント'!B43 -> TEAM-6-1 | B42: =criteria!D42 -> メトリクスの計測 | C42: ='アセスメント'!F43 -> FALSE | D42: ='アセスメント'!G43 -> FALSE | E42: ='アセスメント'!H43 -> FALSE | F42: =not(and(C42,D42)) -> TRUE | G42: =or(C42,D42) -> FALSE | H42: =and(G42,not(F42)) -> FALSE | I42: =and(G42,F42) -> FALSE | J42: =if(B42="アンチパターン",true,false) -> FALSE | K42: =if(E42,0.5,if(C42,1,0)) -> 0 | L42: =if(H42,"@" ,if(G42, if(J42,1-K42,K42),"-")) -> - | M42: =IFERROR(__xludf.DUMMYFUNCTION("split(A42,""-"")"),"TEAM") -> TEAM | N42: =IFERROR(__xludf.DUMMYFUNCTION("""COMPUTED_VALUE"""),6.0) -> 6 | O42: =IFERROR(__xludf.DUMMYFUNCTION("""COMPUTED_VALUE"""),1.0) -> 1
A43: ='アセスメント'!B44 -> TEAM-6-2 | B43: =criteria!D43 -> 学習と改善 | C43: ='アセスメント'!F44 -> FALSE | D43: ='アセスメント'!G44 -> FALSE | E43: ='アセスメント'!H44 -> FALSE | F43: =not(and(C43,D43)) -> TRUE | G43: =or(C43,D43) -> FALSE | H43: =and(G43,not(F43)) -> FALSE | I43: =and(G43,F43) -> FALSE | J43: =if(B43="アンチパターン",true,false) -> FALSE | K43: =if(E43,0.5,if(C43,1,0)) -> 0 | L43: =if(H43,"@" ,if(G43, if(J43,1-K43,K43),"-")) -> - | M43: =IFERROR(__xludf.DUMMYFUNCTION("split(A43,""-"")"),"TEAM") -> TEAM | N43: =IFERROR(__xludf.DUMMYFUNCTION("""COMPUTED_VALUE"""),6.0) -> 6 | O43: =IFERROR(__xludf.DUMMYFUNCTION("""COMPUTED_VALUE"""),2.0) -> 2
A44: ='アセスメント'!B45 -> TEAM-6-3 | B44: =criteria!D44 -> プラクティス | C44: ='アセスメント'!F45 -> FALSE | D44: ='アセスメント'!G45 -> FALSE | E44: ='アセスメント'!H45 -> FALSE | F44: =not(and(C44,D44)) -> TRUE | G44: =or(C44,D44) -> FALSE | H44: =and(G44,not(F44)) -> FALSE | I44: =and(G44,F44) -> FALSE | J44: =if(B44="アンチパターン",true,false) -> FALSE | K44: =if(E44,0.5,if(C44,1,0)) -> 0 | L44: =if(H44,"@" ,if(G44, if(J44,1-K44,K44),"-")) -> - | M44: =IFERROR(__xludf.DUMMYFUNCTION("split(A44,""-"")"),"TEAM") -> TEAM | N44: =IFERROR(__xludf.DUMMYFUNCTION("""COMPUTED_VALUE"""),6.0) -> 6 | O44: =IFERROR(__xludf.DUMMYFUNCTION("""COMPUTED_VALUE"""),3.0) -> 3
A45: ='アセスメント'!B46 -> TEAM-6-4 | B45: =criteria!D45 -> プラクティス | C45: ='アセスメント'!F46 -> FALSE | D45: ='アセスメント'!G46 -> FALSE | E45: ='アセスメント'!H46 -> FALSE | F45: =not(and(C45,D45)) -> TRUE | G45: =or(C45,D45) -> FALSE | H45: =and(G45,not(F45)) -> FALSE | I45: =and(G45,F45) -> FALSE | J45: =if(B45="アンチパターン",true,false) -> FALSE | K45: =if(E45,0.5,if(C45,1,0)) -> 0 | L45: =if(H45,"@" ,if(G45, if(J45,1-K45,K45),"-")) -> - | M45: =IFERROR(__xludf.DUMMYFUNCTION("split(A45,""-"")"),"TEAM") -> TEAM | N45: =IFERROR(__xludf.DUMMYFUNCTION("""COMPUTED_VALUE"""),6.0) -> 6 | O45: =IFERROR(__xludf.DUMMYFUNCTION("""COMPUTED_VALUE"""),4.0) -> 4
A46: ='アセスメント'!B47 -> TEAM-6-5 | B46: =criteria!D46 -> プラクティス | C46: ='アセスメント'!F47 -> FALSE | D46: ='アセスメント'!G47 -> FALSE | E46: ='アセスメント'!H47 -> FALSE | F46: =not(and(C46,D46)) -> TRUE | G46: =or(C46,D46) -> FALSE | H46: =and(G46,not(F46)) -> FALSE | I46: =and(G46,F46) -> FALSE | J46: =if(B46="アンチパターン",true,false) -> FALSE | K46: =if(E46,0.5,if(C46,1,0)) -> 0 | L46: =if(H46,"@" ,if(G46, if(J46,1-K46,K46),"-")) -> - | M46: =IFERROR(__xludf.DUMMYFUNCTION("split(A46,""-"")"),"TEAM") -> TEAM | N46: =IFERROR(__xludf.DUMMYFUNCTION("""COMPUTED_VALUE"""),6.0) -> 6 | O46: =IFERROR(__xludf.DUMMYFUNCTION("""COMPUTED_VALUE"""),5.0) -> 5
A47: ='アセスメント'!B48 -> TEAM-6-6 | B47: =criteria!D47 -> アンチパターン | C47: ='アセスメント'!F48 -> FALSE | D47: ='アセスメント'!G48 -> FALSE | E47: ='アセスメント'!H48 -> FALSE | F47: =not(and(C47,D47)) -> TRUE | G47: =or(C47,D47) -> FALSE | H47: =and(G47,not(F47)) -> FALSE | I47: =and(G47,F47) -> FALSE | J47: =if(B47="アンチパターン",true,false) -> TRUE | K47: =if(E47,0.5,if(C47,1,0)) -> 0 | L47: =if(H47,"@" ,if(G47, if(J47,1-K47,K47),"-")) -> - | M47: =IFERROR(__xludf.DUMMYFUNCTION("split(A47,""-"")"),"TEAM") -> TEAM | N47: =IFERROR(__xludf.DUMMYFUNCTION("""COMPUTED_VALUE"""),6.0) -> 6 | O47: =IFERROR(__xludf.DUMMYFUNCTION("""COMPUTED_VALUE"""),6.0) -> 6
A48: ='アセスメント'!B49 -> TEAM-6-7 | B48: =criteria!D48 -> アンチパターン | C48: ='アセスメント'!F49 -> FALSE | D48: ='アセスメント'!G49 -> FALSE | E48: ='アセスメント'!H49 -> FALSE | F48: =not(and(C48,D48)) -> TRUE | G48: =or(C48,D48) -> FALSE | H48: =and(G48,not(F48)) -> FALSE | I48: =and(G48,F48) -> FALSE | J48: =if(B48="アンチパターン",true,false) -> TRUE | K48: =if(E48,0.5,if(C48,1,0)) -> 0 | L48: =if(H48,"@" ,if(G48, if(J48,1-K48,K48),"-")) -> - | M48: =IFERROR(__xludf.DUMMYFUNCTION("split(A48,""-"")"),"TEAM") -> TEAM | N48: =IFERROR(__xludf.DUMMYFUNCTION("""COMPUTED_VALUE"""),6.0) -> 6 | O48: =IFERROR(__xludf.DUMMYFUNCTION("""COMPUTED_VALUE"""),7.0) -> 7
A49: ='アセスメント'!B50 -> TEAM-6-8 | B49: =criteria!D49 -> アンチパターン | C49: ='アセスメント'!F50 -> FALSE | D49: ='アセスメント'!G50 -> FALSE | E49: ='アセスメント'!H50 -> FALSE | F49: =not(and(C49,D49)) -> TRUE | G49: =or(C49,D49) -> FALSE | H49: =and(G49,not(F49)) -> FALSE | I49: =and(G49,F49) -> FALSE | J49: =if(B49="アンチパターン",true,false) -> TRUE | K49: =if(E49,0.5,if(C49,1,0)) -> 0 | L49: =if(H49,"@" ,if(G49, if(J49,1-K49,K49),"-")) -> - | M49: =IFERROR(__xludf.DUMMYFUNCTION("split(A49,""-"")"),"TEAM") -> TEAM | N49: =IFERROR(__xludf.DUMMYFUNCTION("""COMPUTED_VALUE"""),6.0) -> 6 | O49: =IFERROR(__xludf.DUMMYFUNCTION("""COMPUTED_VALUE"""),8.0) -> 8
A50: ='アセスメント'!B51 -> TEAM-7-1 | B50: =criteria!D50 -> メトリクスの計測 | C50: ='アセスメント'!F51 -> FALSE | D50: ='アセスメント'!G51 -> FALSE | E50: ='アセスメント'!H51 -> FALSE | F50: =not(and(C50,D50)) -> TRUE | G50: =or(C50,D50) -> FALSE | H50: =and(G50,not(F50)) -> FALSE | I50: =and(G50,F50) -> FALSE | J50: =if(B50="アンチパターン",true,false) -> FALSE | K50: =if(E50,0.5,if(C50,1,0)) -> 0 | L50: =if(H50,"@" ,if(G50, if(J50,1-K50,K50),"-")) -> - | M50: =IFERROR(__xludf.DUMMYFUNCTION("split(A50,""-"")"),"TEAM") -> TEAM | N50: =IFERROR(__xludf.DUMMYFUNCTION("""COMPUTED_VALUE"""),7.0) -> 7 | O50: =IFERROR(__xludf.DUMMYFUNCTION("""COMPUTED_VALUE"""),1.0) -> 1
A51: ='アセスメント'!B52 -> TEAM-7-2 | B51: =criteria!D51 -> 学習と改善 | C51: ='アセスメント'!F52 -> FALSE | D51: ='アセスメント'!G52 -> FALSE | E51: ='アセスメント'!H52 -> FALSE | F51: =not(and(C51,D51)) -> TRUE | G51: =or(C51,D51) -> FALSE | H51: =and(G51,not(F51)) -> FALSE | I51: =and(G51,F51) -> FALSE | J51: =if(B51="アンチパターン",true,false) -> FALSE | K51: =if(E51,0.5,if(C51,1,0)) -> 0 | L51: =if(H51,"@" ,if(G51, if(J51,1-K51,K51),"-")) -> - | M51: =IFERROR(__xludf.DUMMYFUNCTION("split(A51,""-"")"),"TEAM") -> TEAM | N51: =IFERROR(__xludf.DUMMYFUNCTION("""COMPUTED_VALUE"""),7.0) -> 7 | O51: =IFERROR(__xludf.DUMMYFUNCTION("""COMPUTED_VALUE"""),2.0) -> 2
A52: ='アセスメント'!B53 -> TEAM-7-3 | B52: =criteria!D52 -> プラクティス | C52: ='アセスメント'!F53 -> FALSE | D52: ='アセスメント'!G53 -> FALSE | E52: ='アセスメント'!H53 -> FALSE | F52: =not(and(C52,D52)) -> TRUE | G52: =or(C52,D52) -> FALSE | H52: =and(G52,not(F52)) -> FALSE | I52: =and(G52,F52) -> FALSE | J52: =if(B52="アンチパターン",true,false) -> FALSE | K52: =if(E52,0.5,if(C52,1,0)) -> 0 | L52: =if(H52,"@" ,if(G52, if(J52,1-K52,K52),"-")) -> - | M52: =IFERROR(__xludf.DUMMYFUNCTION("split(A52,""-"")"),"TEAM") -> TEAM | N52: =IFERROR(__xludf.DUMMYFUNCTION("""COMPUTED_VALUE"""),7.0) -> 7 | O52: =IFERROR(__xludf.DUMMYFUNCTION("""COMPUTED_VALUE"""),3.0) -> 3
A53: ='アセスメント'!B54 -> TEAM-7-4 | B53: =criteria!D53 -> プラクティス | C53: ='アセスメント'!F54 -> FALSE | D53: ='アセスメント'!G54 -> FALSE | E53: ='アセスメント'!H54 -> FALSE | F53: =not(and(C53,D53)) -> TRUE | G53: =or(C53,D53) -> FALSE | H53: =and(G53,not(F53)) -> FALSE | I53: =and(G53,F53) -> FALSE | J53: =if(B53="アンチパターン",true,false) -> FALSE | K53: =if(E53,0.5,if(C53,1,0)) -> 0 | L53: =if(H53,"@" ,if(G53, if(J53,1-K53,K53),"-")) -> - | M53: =IFERROR(__xludf.DUMMYFUNCTION("split(A53,""-"")"),"TEAM") -> TEAM | N53: =IFERROR(__xludf.DUMMYFUNCTION("""COMPUTED_VALUE"""),7.0) -> 7 | O53: =IFERROR(__xludf.DUMMYFUNCTION("""COMPUTED_VALUE"""),4.0) -> 4
A54: ='アセスメント'!B55 -> TEAM-7-5 | B54: =criteria!D54 -> プラクティス | C54: ='アセスメント'!F55 -> FALSE | D54: ='アセスメント'!G55 -> FALSE | E54: ='アセスメント'!H55 -> FALSE | F54: =not(and(C54,D54)) -> TRUE | G54: =or(C54,D54) -> FALSE | H54: =and(G54,not(F54)) -> FALSE | I54: =and(G54,F54) -> FALSE | J54: =if(B54="アンチパターン",true,false) -> FALSE | K54: =if(E54,0.5,if(C54,1,0)) -> 0 | L54: =if(H54,"@" ,if(G54, if(J54,1-K54,K54),"-")) -> - | M54: =IFERROR(__xludf.DUMMYFUNCTION("split(A54,""-"")"),"TEAM") -> TEAM | N54: =IFERROR(__xludf.DUMMYFUNCTION("""COMPUTED_VALUE"""),7.0) -> 7 | O54: =IFERROR(__xludf.DUMMYFUNCTION("""COMPUTED_VALUE"""),5.0) -> 5
A55: ='アセスメント'!B56 -> TEAM-7-6 | B55: =criteria!D55 -> アンチパターン | C55: ='アセスメント'!F56 -> FALSE | D55: ='アセスメント'!G56 -> FALSE | E55: ='アセスメント'!H56 -> FALSE | F55: =not(and(C55,D55)) -> TRUE | G55: =or(C55,D55) -> FALSE | H55: =and(G55,not(F55)) -> FALSE | I55: =and(G55,F55) -> FALSE | J55: =if(B55="アンチパターン",true,false) -> TRUE | K55: =if(E55,0.5,if(C55,1,0)) -> 0 | L55: =if(H55,"@" ,if(G55, if(J55,1-K55,K55),"-")) -> - | M55: =IFERROR(__xludf.DUMMYFUNCTION("split(A55,""-"")"),"TEAM") -> TEAM | N55: =IFERROR(__xludf.DUMMYFUNCTION("""COMPUTED_VALUE"""),7.0) -> 7 | O55: =IFERROR(__xludf.DUMMYFUNCTION("""COMPUTED_VALUE"""),6.0) -> 6
A56: ='アセスメント'!B57 -> TEAM-7-7 | B56: =criteria!D56 -> アンチパターン | C56: ='アセスメント'!F57 -> FALSE | D56: ='アセスメント'!G57 -> FALSE | E56: ='アセスメント'!H57 -> FALSE | F56: =not(and(C56,D56)) -> TRUE | G56: =or(C56,D56) -> FALSE | H56: =and(G56,not(F56)) -> FALSE | I56: =and(G56,F56) -> FALSE | J56: =if(B56="アンチパターン",true,false) -> TRUE | K56: =if(E56,0.5,if(C56,1,0)) -> 0 | L56: =if(H56,"@" ,if(G56, if(J56,1-K56,K56),"-")) -> - | M56: =IFERROR(__xludf.DUMMYFUNCTION("split(A56,""-"")"),"TEAM") -> TEAM | N56: =IFERROR(__xludf.DUMMYFUNCTION("""COMPUTED_VALUE"""),7.0) -> 7 | O56: =IFERROR(__xludf.DUMMYFUNCTION("""COMPUTED_VALUE"""),7.0) -> 7
A57: ='アセスメント'!B58 -> TEAM-7-8 | B57: =criteria!D57 -> アンチパターン | C57: ='アセスメント'!F58 -> FALSE | D57: ='アセスメント'!G58 -> FALSE | E57: ='アセスメント'!H58 -> FALSE | F57: =not(and(C57,D57)) -> TRUE | G57: =or(C57,D57) -> FALSE | H57: =and(G57,not(F57)) -> FALSE | I57: =and(G57,F57) -> FALSE | J57: =if(B57="アンチパターン",true,false) -> TRUE | K57: =if(E57,0.5,if(C57,1,0)) -> 0 | L57: =if(H57,"@" ,if(G57, if(J57,1-K57,K57),"-")) -> - | M57: =IFERROR(__xludf.DUMMYFUNCTION("split(A57,""-"")"),"TEAM") -> TEAM | N57: =IFERROR(__xludf.DUMMYFUNCTION("""COMPUTED_VALUE"""),7.0) -> 7 | O57: =IFERROR(__xludf.DUMMYFUNCTION("""COMPUTED_VALUE"""),8.0) -> 8
A58: ='アセスメント'!B59 -> TEAM-8-1 | B58: =criteria!D58 -> メトリクスの計測 | C58: ='アセスメント'!F59 -> FALSE | D58: ='アセスメント'!G59 -> FALSE | E58: ='アセスメント'!H59 -> FALSE | F58: =not(and(C58,D58)) -> TRUE | G58: =or(C58,D58) -> FALSE | H58: =and(G58,not(F58)) -> FALSE | I58: =and(G58,F58) -> FALSE | J58: =if(B58="アンチパターン",true,false) -> FALSE | K58: =if(E58,0.5,if(C58,1,0)) -> 0 | L58: =if(H58,"@" ,if(G58, if(J58,1-K58,K58),"-")) -> - | M58: =IFERROR(__xludf.DUMMYFUNCTION("split(A58,""-"")"),"TEAM") -> TEAM | N58: =IFERROR(__xludf.DUMMYFUNCTION("""COMPUTED_VALUE"""),8.0) -> 8 | O58: =IFERROR(__xludf.DUMMYFUNCTION("""COMPUTED_VALUE"""),1.0) -> 1
A59: ='アセスメント'!B60 -> TEAM-8-2 | B59: =criteria!D59 -> 学習と改善 | C59: ='アセスメント'!F60 -> FALSE | D59: ='アセスメント'!G60 -> FALSE | E59: ='アセスメント'!H60 -> FALSE | F59: =not(and(C59,D59)) -> TRUE | G59: =or(C59,D59) -> FALSE | H59: =and(G59,not(F59)) -> FALSE | I59: =and(G59,F59) -> FALSE | J59: =if(B59="アンチパターン",true,false) -> FALSE | K59: =if(E59,0.5,if(C59,1,0)) -> 0 | L59: =if(H59,"@" ,if(G59, if(J59,1-K59,K59),"-")) -> - | M59: =IFERROR(__xludf.DUMMYFUNCTION("split(A59,""-"")"),"TEAM") -> TEAM | N59: =IFERROR(__xludf.DUMMYFUNCTION("""COMPUTED_VALUE"""),8.0) -> 8 | O59: =IFERROR(__xludf.DUMMYFUNCTION("""COMPUTED_VALUE"""),2.0) -> 2
A60: ='アセスメント'!B61 -> TEAM-8-3 | B60: =criteria!D60 -> プラクティス | C60: ='アセスメント'!F61 -> FALSE | D60: ='アセスメント'!G61 -> FALSE | E60: ='アセスメント'!H61 -> FALSE | F60: =not(and(C60,D60)) -> TRUE | G60: =or(C60,D60) -> FALSE | H60: =and(G60,not(F60)) -> FALSE | I60: =and(G60,F60) -> FALSE | J60: =if(B60="アンチパターン",true,false) -> FALSE | K60: =if(E60,0.5,if(C60,1,0)) -> 0 | L60: =if(H60,"@" ,if(G60, if(J60,1-K60,K60),"-")) -> - | M60: =IFERROR(__xludf.DUMMYFUNCTION("split(A60,""-"")"),"TEAM") -> TEAM | N60: =IFERROR(__xludf.DUMMYFUNCTION("""COMPUTED_VALUE"""),8.0) -> 8 | O60: =IFERROR(__xludf.DUMMYFUNCTION("""COMPUTED_VALUE"""),3.0) -> 3
A61: ='アセスメント'!B62 -> TEAM-8-4 | B61: =criteria!D61 -> プラクティス | C61: ='アセスメント'!F62 -> FALSE | D61: ='アセスメント'!G62 -> FALSE | E61: ='アセスメント'!H62 -> FALSE | F61: =not(and(C61,D61)) -> TRUE | G61: =or(C61,D61) -> FALSE | H61: =and(G61,not(F61)) -> FALSE | I61: =and(G61,F61) -> FALSE | J61: =if(B61="アンチパターン",true,false) -> FALSE | K61: =if(E61,0.5,if(C61,1,0)) -> 0 | L61: =if(H61,"@" ,if(G61, if(J61,1-K61,K61),"-")) -> - | M61: =IFERROR(__xludf.DUMMYFUNCTION("split(A61,""-"")"),"TEAM") -> TEAM | N61: =IFERROR(__xludf.DUMMYFUNCTION("""COMPUTED_VALUE"""),8.0) -> 8 | O61: =IFERROR(__xludf.DUMMYFUNCTION("""COMPUTED_VALUE"""),4.0) -> 4
A62: ='アセスメント'!B63 -> TEAM-8-5 | B62: =criteria!D62 -> プラクティス | C62: ='アセスメント'!F63 -> FALSE | D62: ='アセスメント'!G63 -> FALSE | E62: ='アセスメント'!H63 -> FALSE | F62: =not(and(C62,D62)) -> TRUE | G62: =or(C62,D62) -> FALSE | H62: =and(G62,not(F62)) -> FALSE | I62: =and(G62,F62) -> FALSE | J62: =if(B62="アンチパターン",true,false) -> FALSE | K62: =if(E62,0.5,if(C62,1,0)) -> 0 | L62: =if(H62,"@" ,if(G62, if(J62,1-K62,K62),"-")) -> - | M62: =IFERROR(__xludf.DUMMYFUNCTION("split(A62,""-"")"),"TEAM") -> TEAM | N62: =IFERROR(__xludf.DUMMYFUNCTION("""COMPUTED_VALUE"""),8.0) -> 8 | O62: =IFERROR(__xludf.DUMMYFUNCTION("""COMPUTED_VALUE"""),5.0) -> 5
A63: ='アセスメント'!B64 -> TEAM-8-6 | B63: =criteria!D63 -> アンチパターン | C63: ='アセスメント'!F64 -> FALSE | D63: ='アセスメント'!G64 -> FALSE | E63: ='アセスメント'!H64 -> FALSE | F63: =not(and(C63,D63)) -> TRUE | G63: =or(C63,D63) -> FALSE | H63: =and(G63,not(F63)) -> FALSE | I63: =and(G63,F63) -> FALSE | J63: =if(B63="アンチパターン",true,false) -> TRUE | K63: =if(E63,0.5,if(C63,1,0)) -> 0 | L63: =if(H63,"@" ,if(G63, if(J63,1-K63,K63),"-")) -> - | M63: =IFERROR(__xludf.DUMMYFUNCTION("split(A63,""-"")"),"TEAM") -> TEAM | N63: =IFERROR(__xludf.DUMMYFUNCTION("""COMPUTED_VALUE"""),8.0) -> 8 | O63: =IFERROR(__xludf.DUMMYFUNCTION("""COMPUTED_VALUE"""),6.0) -> 6
A64: ='アセスメント'!B65 -> TEAM-8-7 | B64: =criteria!D64 -> アンチパターン | C64: ='アセスメント'!F65 -> FALSE | D64: ='アセスメント'!G65 -> FALSE | E64: ='アセスメント'!H65 -> FALSE | F64: =not(and(C64,D64)) -> TRUE | G64: =or(C64,D64) -> FALSE | H64: =and(G64,not(F64)) -> FALSE | I64: =and(G64,F64) -> FALSE | J64: =if(B64="アンチパターン",true,false) -> TRUE | K64: =if(E64,0.5,if(C64,1,0)) -> 0 | L64: =if(H64,"@" ,if(G64, if(J64,1-K64,K64),"-")) -> - | M64: =IFERROR(__xludf.DUMMYFUNCTION("split(A64,""-"")"),"TEAM") -> TEAM | N64: =IFERROR(__xludf.DUMMYFUNCTION("""COMPUTED_VALUE"""),8.0) -> 8 | O64: =IFERROR(__xludf.DUMMYFUNCTION("""COMPUTED_VALUE"""),7.0) -> 7
A65: ='アセスメント'!B66 -> TEAM-8-8 | B65: =criteria!D65 -> アンチパターン | C65: ='アセスメント'!F66 -> FALSE | D65: ='アセスメント'!G66 -> FALSE | E65: ='アセスメント'!H66 -> FALSE | F65: =not(and(C65,D65)) -> TRUE | G65: =or(C65,D65) -> FALSE | H65: =and(G65,not(F65)) -> FALSE | I65: =and(G65,F65) -> FALSE | J65: =if(B65="アンチパターン",true,false) -> TRUE | K65: =if(E65,0.5,if(C65,1,0)) -> 0 | L65: =if(H65,"@" ,if(G65, if(J65,1-K65,K65),"-")) -> - | M65: =IFERROR(__xludf.DUMMYFUNCTION("split(A65,""-"")"),"TEAM") -> TEAM | N65: =IFERROR(__xludf.DUMMYFUNCTION("""COMPUTED_VALUE"""),8.0) -> 8 | O65: =IFERROR(__xludf.DUMMYFUNCTION("""COMPUTED_VALUE"""),8.0) -> 8
A66: ='アセスメント'!B67 -> SYSTEM-1-1 | B66: =criteria!D66 -> メトリクスの計測 | C66: ='アセスメント'!F67 -> FALSE | D66: ='アセスメント'!G67 -> FALSE | E66: ='アセスメント'!H67 -> FALSE | F66: =not(and(C66,D66)) -> TRUE | G66: =or(C66,D66) -> FALSE | H66: =and(G66,not(F66)) -> FALSE | I66: =and(G66,F66) -> FALSE | J66: =if(B66="アンチパターン",true,false) -> FALSE | K66: =if(E66,0.5,if(C66,1,0)) -> 0 | L66: =if(H66,"@" ,if(G66, if(J66,1-K66,K66),"-")) -> - | M66: =IFERROR(__xludf.DUMMYFUNCTION("split(A66,""-"")"),"SYSTEM") -> SYSTEM | N66: =IFERROR(__xludf.DUMMYFUNCTION("""COMPUTED_VALUE"""),1.0) -> 1 | O66: =IFERROR(__xludf.DUMMYFUNCTION("""COMPUTED_VALUE"""),1.0) -> 1
A67: ='アセスメント'!B68 -> SYSTEM-1-2 | B67: =criteria!D67 -> 学習と改善 | C67: ='アセスメント'!F68 -> FALSE | D67: ='アセスメント'!G68 -> FALSE | E67: ='アセスメント'!H68 -> FALSE | F67: =not(and(C67,D67)) -> TRUE | G67: =or(C67,D67) -> FALSE | H67: =and(G67,not(F67)) -> FALSE | I67: =and(G67,F67) -> FALSE | J67: =if(B67="アンチパターン",true,false) -> FALSE | K67: =if(E67,0.5,if(C67,1,0)) -> 0 | L67: =if(H67,"@" ,if(G67, if(J67,1-K67,K67),"-")) -> - | M67: =IFERROR(__xludf.DUMMYFUNCTION("split(A67,""-"")"),"SYSTEM") -> SYSTEM | N67: =IFERROR(__xludf.DUMMYFUNCTION("""COMPUTED_VALUE"""),1.0) -> 1 | O67: =IFERROR(__xludf.DUMMYFUNCTION("""COMPUTED_VALUE"""),2.0) -> 2
A68: ='アセスメント'!B69 -> SYSTEM-1-3 | B68: =criteria!D68 -> プラクティス | C68: ='アセスメント'!F69 -> FALSE | D68: ='アセスメント'!G69 -> FALSE | E68: ='アセスメント'!H69 -> FALSE | F68: =not(and(C68,D68)) -> TRUE | G68: =or(C68,D68) -> FALSE | H68: =and(G68,not(F68)) -> FALSE | I68: =and(G68,F68) -> FALSE | J68: =if(B68="アンチパターン",true,false) -> FALSE | K68: =if(E68,0.5,if(C68,1,0)) -> 0 | L68: =if(H68,"@" ,if(G68, if(J68,1-K68,K68),"-")) -> - | M68: =IFERROR(__xludf.DUMMYFUNCTION("split(A68,""-"")"),"SYSTEM") -> SYSTEM | N68: =IFERROR(__xludf.DUMMYFUNCTION("""COMPUTED_VALUE"""),1.0) -> 1 | O68: =IFERROR(__xludf.DUMMYFUNCTION("""COMPUTED_VALUE"""),3.0) -> 3
A69: ='アセスメント'!B70 -> SYSTEM-1-4 | B69: =criteria!D69 -> プラクティス | C69: ='アセスメント'!F70 -> FALSE | D69: ='アセスメント'!G70 -> FALSE | E69: ='アセスメント'!H70 -> FALSE | F69: =not(and(C69,D69)) -> TRUE | G69: =or(C69,D69) -> FALSE | H69: =and(G69,not(F69)) -> FALSE | I69: =and(G69,F69) -> FALSE | J69: =if(B69="アンチパターン",true,false) -> FALSE | K69: =if(E69,0.5,if(C69,1,0)) -> 0 | L69: =if(H69,"@" ,if(G69, if(J69,1-K69,K69),"-")) -> - | M69: =IFERROR(__xludf.DUMMYFUNCTION("split(A69,""-"")"),"SYSTEM") -> SYSTEM | N69: =IFERROR(__xludf.DUMMYFUNCTION("""COMPUTED_VALUE"""),1.0) -> 1 | O69: =IFERROR(__xludf.DUMMYFUNCTION("""COMPUTED_VALUE"""),4.0) -> 4
A70: ='アセスメント'!B71 -> SYSTEM-1-5 | B70: =criteria!D70 -> プラクティス | C70: ='アセスメント'!F71 -> FALSE | D70: ='アセスメント'!G71 -> FALSE | E70: ='アセスメント'!H71 -> FALSE | F70: =not(and(C70,D70)) -> TRUE | G70: =or(C70,D70) -> FALSE | H70: =and(G70,not(F70)) -> FALSE | I70: =and(G70,F70) -> FALSE | J70: =if(B70="アンチパターン",true,false) -> FALSE | K70: =if(E70,0.5,if(C70,1,0)) -> 0 | L70: =if(H70,"@" ,if(G70, if(J70,1-K70,K70),"-")) -> - | M70: =IFERROR(__xludf.DUMMYFUNCTION("split(A70,""-"")"),"SYSTEM") -> SYSTEM | N70: =IFERROR(__xludf.DUMMYFUNCTION("""COMPUTED_VALUE"""),1.0) -> 1 | O70: =IFERROR(__xludf.DUMMYFUNCTION("""COMPUTED_VALUE"""),5.0) -> 5
A71: ='アセスメント'!B72 -> SYSTEM-1-6 | B71: =criteria!D71 -> アンチパターン | C71: ='アセスメント'!F72 -> FALSE | D71: ='アセスメント'!G72 -> FALSE | E71: ='アセスメント'!H72 -> FALSE | F71: =not(and(C71,D71)) -> TRUE | G71: =or(C71,D71) -> FALSE | H71: =and(G71,not(F71)) -> FALSE | I71: =and(G71,F71) -> FALSE | J71: =if(B71="アンチパターン",true,false) -> TRUE | K71: =if(E71,0.5,if(C71,1,0)) -> 0 | L71: =if(H71,"@" ,if(G71, if(J71,1-K71,K71),"-")) -> - | M71: =IFERROR(__xludf.DUMMYFUNCTION("split(A71,""-"")"),"SYSTEM") -> SYSTEM | N71: =IFERROR(__xludf.DUMMYFUNCTION("""COMPUTED_VALUE"""),1.0) -> 1 | O71: =IFERROR(__xludf.DUMMYFUNCTION("""COMPUTED_VALUE"""),6.0) -> 6
A72: ='アセスメント'!B73 -> SYSTEM-1-7 | B72: =criteria!D72 -> アンチパターン | C72: ='アセスメント'!F73 -> FALSE | D72: ='アセスメント'!G73 -> FALSE | E72: ='アセスメント'!H73 -> FALSE | F72: =not(and(C72,D72)) -> TRUE | G72: =or(C72,D72) -> FALSE | H72: =and(G72,not(F72)) -> FALSE | I72: =and(G72,F72) -> FALSE | J72: =if(B72="アンチパターン",true,false) -> TRUE | K72: =if(E72,0.5,if(C72,1,0)) -> 0 | L72: =if(H72,"@" ,if(G72, if(J72,1-K72,K72),"-")) -> - | M72: =IFERROR(__xludf.DUMMYFUNCTION("split(A72,""-"")"),"SYSTEM") -> SYSTEM | N72: =IFERROR(__xludf.DUMMYFUNCTION("""COMPUTED_VALUE"""),1.0) -> 1 | O72: =IFERROR(__xludf.DUMMYFUNCTION("""COMPUTED_VALUE"""),7.0) -> 7
A73: ='アセスメント'!B74 -> SYSTEM-1-8 | B73: =criteria!D73 -> アンチパターン | C73: ='アセスメント'!F74 -> FALSE | D73: ='アセスメント'!G74 -> FALSE | E73: ='アセスメント'!H74 -> FALSE | F73: =not(and(C73,D73)) -> TRUE | G73: =or(C73,D73) -> FALSE | H73: =and(G73,not(F73)) -> FALSE | I73: =and(G73,F73) -> FALSE | J73: =if(B73="アンチパターン",true,false) -> TRUE | K73: =if(E73,0.5,if(C73,1,0)) -> 0 | L73: =if(H73,"@" ,if(G73, if(J73,1-K73,K73),"-")) -> - | M73: =IFERROR(__xludf.DUMMYFUNCTION("split(A73,""-"")"),"SYSTEM") -> SYSTEM | N73: =IFERROR(__xludf.DUMMYFUNCTION("""COMPUTED_VALUE"""),1.0) -> 1 | O73: =IFERROR(__xludf.DUMMYFUNCTION("""COMPUTED_VALUE"""),8.0) -> 8
A74: ='アセスメント'!B75 -> SYSTEM-2-1 | B74: =criteria!D74 -> メトリクスの計測 | C74: ='アセスメント'!F75 -> FALSE | D74: ='アセスメント'!G75 -> FALSE | E74: ='アセスメント'!H75 -> FALSE | F74: =not(and(C74,D74)) -> TRUE | G74: =or(C74,D74) -> FALSE | H74: =and(G74,not(F74)) -> FALSE | I74: =and(G74,F74) -> FALSE | J74: =if(B74="アンチパターン",true,false) -> FALSE | K74: =if(E74,0.5,if(C74,1,0)) -> 0 | L74: =if(H74,"@" ,if(G74, if(J74,1-K74,K74),"-")) -> - | M74: =IFERROR(__xludf.DUMMYFUNCTION("split(A74,""-"")"),"SYSTEM") -> SYSTEM | N74: =IFERROR(__xludf.DUMMYFUNCTION("""COMPUTED_VALUE"""),2.0) -> 2 | O74: =IFERROR(__xludf.DUMMYFUNCTION("""COMPUTED_VALUE"""),1.0) -> 1
A75: ='アセスメント'!B76 -> SYSTEM-2-2 | B75: =criteria!D75 -> 学習と改善 | C75: ='アセスメント'!F76 -> FALSE | D75: ='アセスメント'!G76 -> FALSE | E75: ='アセスメント'!H76 -> FALSE | F75: =not(and(C75,D75)) -> TRUE | G75: =or(C75,D75) -> FALSE | H75: =and(G75,not(F75)) -> FALSE | I75: =and(G75,F75) -> FALSE | J75: =if(B75="アンチパターン",true,false) -> FALSE | K75: =if(E75,0.5,if(C75,1,0)) -> 0 | L75: =if(H75,"@" ,if(G75, if(J75,1-K75,K75),"-")) -> - | M75: =IFERROR(__xludf.DUMMYFUNCTION("split(A75,""-"")"),"SYSTEM") -> SYSTEM | N75: =IFERROR(__xludf.DUMMYFUNCTION("""COMPUTED_VALUE"""),2.0) -> 2 | O75: =IFERROR(__xludf.DUMMYFUNCTION("""COMPUTED_VALUE"""),2.0) -> 2
A76: ='アセスメント'!B77 -> SYSTEM-2-3 | B76: =criteria!D76 -> プラクティス | C76: ='アセスメント'!F77 -> FALSE | D76: ='アセスメント'!G77 -> FALSE | E76: ='アセスメント'!H77 -> FALSE | F76: =not(and(C76,D76)) -> TRUE | G76: =or(C76,D76) -> FALSE | H76: =and(G76,not(F76)) -> FALSE | I76: =and(G76,F76) -> FALSE | J76: =if(B76="アンチパターン",true,false) -> FALSE | K76: =if(E76,0.5,if(C76,1,0)) -> 0 | L76: =if(H76,"@" ,if(G76, if(J76,1-K76,K76),"-")) -> - | M76: =IFERROR(__xludf.DUMMYFUNCTION("split(A76,""-"")"),"SYSTEM") -> SYSTEM | N76: =IFERROR(__xludf.DUMMYFUNCTION("""COMPUTED_VALUE"""),2.0) -> 2 | O76: =IFERROR(__xludf.DUMMYFUNCTION("""COMPUTED_VALUE"""),3.0) -> 3
A77: ='アセスメント'!B78 -> SYSTEM-2-4 | B77: =criteria!D77 -> プラクティス | C77: ='アセスメント'!F78 -> FALSE | D77: ='アセスメント'!G78 -> FALSE | E77: ='アセスメント'!H78 -> FALSE | F77: =not(and(C77,D77)) -> TRUE | G77: =or(C77,D77) -> FALSE | H77: =and(G77,not(F77)) -> FALSE | I77: =and(G77,F77) -> FALSE | J77: =if(B77="アンチパターン",true,false) -> FALSE | K77: =if(E77,0.5,if(C77,1,0)) -> 0 | L77: =if(H77,"@" ,if(G77, if(J77,1-K77,K77),"-")) -> - | M77: =IFERROR(__xludf.DUMMYFUNCTION("split(A77,""-"")"),"SYSTEM") -> SYSTEM | N77: =IFERROR(__xludf.DUMMYFUNCTION("""COMPUTED_VALUE"""),2.0) -> 2 | O77: =IFERROR(__xludf.DUMMYFUNCTION("""COMPUTED_VALUE"""),4.0) -> 4
A78: ='アセスメント'!B79 -> SYSTEM-2-5 | B78: =criteria!D78 -> プラクティス | C78: ='アセスメント'!F79 -> FALSE | D78: ='アセスメント'!G79 -> FALSE | E78: ='アセスメント'!H79 -> FALSE | F78: =not(and(C78,D78)) -> TRUE | G78: =or(C78,D78) -> FALSE | H78: =and(G78,not(F78)) -> FALSE | I78: =and(G78,F78) -> FALSE | J78: =if(B78="アンチパターン",true,false) -> FALSE | K78: =if(E78,0.5,if(C78,1,0)) -> 0 | L78: =if(H78,"@" ,if(G78, if(J78,1-K78,K78),"-")) -> - | M78: =IFERROR(__xludf.DUMMYFUNCTION("split(A78,""-"")"),"SYSTEM") -> SYSTEM | N78: =IFERROR(__xludf.DUMMYFUNCTION("""COMPUTED_VALUE"""),2.0) -> 2 | O78: =IFERROR(__xludf.DUMMYFUNCTION("""COMPUTED_VALUE"""),5.0) -> 5
A79: ='アセスメント'!B80 -> SYSTEM-2-6 | B79: =criteria!D79 -> アンチパターン | C79: ='アセスメント'!F80 -> FALSE | D79: ='アセスメント'!G80 -> FALSE | E79: ='アセスメント'!H80 -> FALSE | F79: =not(and(C79,D79)) -> TRUE | G79: =or(C79,D79) -> FALSE | H79: =and(G79,not(F79)) -> FALSE | I79: =and(G79,F79) -> FALSE | J79: =if(B79="アンチパターン",true,false) -> TRUE | K79: =if(E79,0.5,if(C79,1,0)) -> 0 | L79: =if(H79,"@" ,if(G79, if(J79,1-K79,K79),"-")) -> - | M79: =IFERROR(__xludf.DUMMYFUNCTION("split(A79,""-"")"),"SYSTEM") -> SYSTEM | N79: =IFERROR(__xludf.DUMMYFUNCTION("""COMPUTED_VALUE"""),2.0) -> 2 | O79: =IFERROR(__xludf.DUMMYFUNCTION("""COMPUTED_VALUE"""),6.0) -> 6
A80: ='アセスメント'!B81 -> SYSTEM-2-7 | B80: =criteria!D80 -> アンチパターン | C80: ='アセスメント'!F81 -> FALSE | D80: ='アセスメント'!G81 -> FALSE | E80: ='アセスメント'!H81 -> FALSE | F80: =not(and(C80,D80)) -> TRUE | G80: =or(C80,D80) -> FALSE | H80: =and(G80,not(F80)) -> FALSE | I80: =and(G80,F80) -> FALSE | J80: =if(B80="アンチパターン",true,false) -> TRUE | K80: =if(E80,0.5,if(C80,1,0)) -> 0 | L80: =if(H80,"@" ,if(G80, if(J80,1-K80,K80),"-")) -> - | M80: =IFERROR(__xludf.DUMMYFUNCTION("split(A80,""-"")"),"SYSTEM") -> SYSTEM | N80: =IFERROR(__xludf.DUMMYFUNCTION("""COMPUTED_VALUE"""),2.0) -> 2 | O80: =IFERROR(__xludf.DUMMYFUNCTION("""COMPUTED_VALUE"""),7.0) -> 7
A81: ='アセスメント'!B82 -> SYSTEM-2-8 | B81: =criteria!D81 -> アンチパターン | C81: ='アセスメント'!F82 -> FALSE | D81: ='アセスメント'!G82 -> FALSE | E81: ='アセスメント'!H82 -> FALSE | F81: =not(and(C81,D81)) -> TRUE | G81: =or(C81,D81) -> FALSE | H81: =and(G81,not(F81)) -> FALSE | I81: =and(G81,F81) -> FALSE | J81: =if(B81="アンチパターン",true,false) -> TRUE | K81: =if(E81,0.5,if(C81,1,0)) -> 0 | L81: =if(H81,"@" ,if(G81, if(J81,1-K81,K81),"-")) -> - | M81: =IFERROR(__xludf.DUMMYFUNCTION("split(A81,""-"")"),"SYSTEM") -> SYSTEM | N81: =IFERROR(__xludf.DUMMYFUNCTION("""COMPUTED_VALUE"""),2.0) -> 2 | O81: =IFERROR(__xludf.DUMMYFUNCTION("""COMPUTED_VALUE"""),8.0) -> 8
A82: ='アセスメント'!B83 -> SYSTEM-3-1 | B82: =criteria!D82 -> メトリクスの計測 | C82: ='アセスメント'!F83 -> FALSE | D82: ='アセスメント'!G83 -> FALSE | E82: ='アセスメント'!H83 -> FALSE | F82: =not(and(C82,D82)) -> TRUE | G82: =or(C82,D82) -> FALSE | H82: =and(G82,not(F82)) -> FALSE | I82: =and(G82,F82) -> FALSE | J82: =if(B82="アンチパターン",true,false) -> FALSE | K82: =if(E82,0.5,if(C82,1,0)) -> 0 | L82: =if(H82,"@" ,if(G82, if(J82,1-K82,K82),"-")) -> - | M82: =IFERROR(__xludf.DUMMYFUNCTION("split(A82,""-"")"),"SYSTEM") -> SYSTEM | N82: =IFERROR(__xludf.DUMMYFUNCTION("""COMPUTED_VALUE"""),3.0) -> 3 | O82: =IFERROR(__xludf.DUMMYFUNCTION("""COMPUTED_VALUE"""),1.0) -> 1
A83: ='アセスメント'!B84 -> SYSTEM-3-2 | B83: =criteria!D83 -> 学習と改善 | C83: ='アセスメント'!F84 -> FALSE | D83: ='アセスメント'!G84 -> FALSE | E83: ='アセスメント'!H84 -> FALSE | F83: =not(and(C83,D83)) -> TRUE | G83: =or(C83,D83) -> FALSE | H83: =and(G83,not(F83)) -> FALSE | I83: =and(G83,F83) -> FALSE | J83: =if(B83="アンチパターン",true,false) -> FALSE | K83: =if(E83,0.5,if(C83,1,0)) -> 0 | L83: =if(H83,"@" ,if(G83, if(J83,1-K83,K83),"-")) -> - | M83: =IFERROR(__xludf.DUMMYFUNCTION("split(A83,""-"")"),"SYSTEM") -> SYSTEM | N83: =IFERROR(__xludf.DUMMYFUNCTION("""COMPUTED_VALUE"""),3.0) -> 3 | O83: =IFERROR(__xludf.DUMMYFUNCTION("""COMPUTED_VALUE"""),2.0) -> 2
A84: ='アセスメント'!B85 -> SYSTEM-3-3 | B84: =criteria!D84 -> プラクティス | C84: ='アセスメント'!F85 -> FALSE | D84: ='アセスメント'!G85 -> FALSE | E84: ='アセスメント'!H85 -> FALSE | F84: =not(and(C84,D84)) -> TRUE | G84: =or(C84,D84) -> FALSE | H84: =and(G84,not(F84)) -> FALSE | I84: =and(G84,F84) -> FALSE | J84: =if(B84="アンチパターン",true,false) -> FALSE | K84: =if(E84,0.5,if(C84,1,0)) -> 0 | L84: =if(H84,"@" ,if(G84, if(J84,1-K84,K84),"-")) -> - | M84: =IFERROR(__xludf.DUMMYFUNCTION("split(A84,""-"")"),"SYSTEM") -> SYSTEM | N84: =IFERROR(__xludf.DUMMYFUNCTION("""COMPUTED_VALUE"""),3.0) -> 3 | O84: =IFERROR(__xludf.DUMMYFUNCTION("""COMPUTED_VALUE"""),3.0) -> 3
A85: ='アセスメント'!B86 -> SYSTEM-3-4 | B85: =criteria!D85 -> プラクティス | C85: ='アセスメント'!F86 -> FALSE | D85: ='アセスメント'!G86 -> FALSE | E85: ='アセスメント'!H86 -> FALSE | F85: =not(and(C85,D85)) -> TRUE | G85: =or(C85,D85) -> FALSE | H85: =and(G85,not(F85)) -> FALSE | I85: =and(G85,F85) -> FALSE | J85: =if(B85="アンチパターン",true,false) -> FALSE | K85: =if(E85,0.5,if(C85,1,0)) -> 0 | L85: =if(H85,"@" ,if(G85, if(J85,1-K85,K85),"-")) -> - | M85: =IFERROR(__xludf.DUMMYFUNCTION("split(A85,""-"")"),"SYSTEM") -> SYSTEM | N85: =IFERROR(__xludf.DUMMYFUNCTION("""COMPUTED_VALUE"""),3.0) -> 3 | O85: =IFERROR(__xludf.DUMMYFUNCTION("""COMPUTED_VALUE"""),4.0) -> 4
A86: ='アセスメント'!B87 -> SYSTEM-3-5 | B86: =criteria!D86 -> プラクティス | C86: ='アセスメント'!F87 -> FALSE | D86: ='アセスメント'!G87 -> FALSE | E86: ='アセスメント'!H87 -> FALSE | F86: =not(and(C86,D86)) -> TRUE | G86: =or(C86,D86) -> FALSE | H86: =and(G86,not(F86)) -> FALSE | I86: =and(G86,F86) -> FALSE | J86: =if(B86="アンチパターン",true,false) -> FALSE | K86: =if(E86,0.5,if(C86,1,0)) -> 0 | L86: =if(H86,"@" ,if(G86, if(J86,1-K86,K86),"-")) -> - | M86: =IFERROR(__xludf.DUMMYFUNCTION("split(A86,""-"")"),"SYSTEM") -> SYSTEM | N86: =IFERROR(__xludf.DUMMYFUNCTION("""COMPUTED_VALUE"""),3.0) -> 3 | O86: =IFERROR(__xludf.DUMMYFUNCTION("""COMPUTED_VALUE"""),5.0) -> 5
A87: ='アセスメント'!B88 -> SYSTEM-3-6 | B87: =criteria!D87 -> アンチパターン | C87: ='アセスメント'!F88 -> FALSE | D87: ='アセスメント'!G88 -> FALSE | E87: ='アセスメント'!H88 -> FALSE | F87: =not(and(C87,D87)) -> TRUE | G87: =or(C87,D87) -> FALSE | H87: =and(G87,not(F87)) -> FALSE | I87: =and(G87,F87) -> FALSE | J87: =if(B87="アンチパターン",true,false) -> TRUE | K87: =if(E87,0.5,if(C87,1,0)) -> 0 | L87: =if(H87,"@" ,if(G87, if(J87,1-K87,K87),"-")) -> - | M87: =IFERROR(__xludf.DUMMYFUNCTION("split(A87,""-"")"),"SYSTEM") -> SYSTEM | N87: =IFERROR(__xludf.DUMMYFUNCTION("""COMPUTED_VALUE"""),3.0) -> 3 | O87: =IFERROR(__xludf.DUMMYFUNCTION("""COMPUTED_VALUE"""),6.0) -> 6
A88: ='アセスメント'!B89 -> SYSTEM-3-7 | B88: =criteria!D88 -> アンチパターン | C88: ='アセスメント'!F89 -> FALSE | D88: ='アセスメント'!G89 -> FALSE | E88: ='アセスメント'!H89 -> FALSE | F88: =not(and(C88,D88)) -> TRUE | G88: =or(C88,D88) -> FALSE | H88: =and(G88,not(F88)) -> FALSE | I88: =and(G88,F88) -> FALSE | J88: =if(B88="アンチパターン",true,false) -> TRUE | K88: =if(E88,0.5,if(C88,1,0)) -> 0 | L88: =if(H88,"@" ,if(G88, if(J88,1-K88,K88),"-")) -> - | M88: =IFERROR(__xludf.DUMMYFUNCTION("split(A88,""-"")"),"SYSTEM") -> SYSTEM | N88: =IFERROR(__xludf.DUMMYFUNCTION("""COMPUTED_VALUE"""),3.0) -> 3 | O88: =IFERROR(__xludf.DUMMYFUNCTION("""COMPUTED_VALUE"""),7.0) -> 7
A89: ='アセスメント'!B90 -> SYSTEM-3-8 | B89: =criteria!D89 -> アンチパターン | C89: ='アセスメント'!F90 -> FALSE | D89: ='アセスメント'!G90 -> FALSE | E89: ='アセスメント'!H90 -> FALSE | F89: =not(and(C89,D89)) -> TRUE | G89: =or(C89,D89) -> FALSE | H89: =and(G89,not(F89)) -> FALSE | I89: =and(G89,F89) -> FALSE | J89: =if(B89="アンチパターン",true,false) -> TRUE | K89: =if(E89,0.5,if(C89,1,0)) -> 0 | L89: =if(H89,"@" ,if(G89, if(J89,1-K89,K89),"-")) -> - | M89: =IFERROR(__xludf.DUMMYFUNCTION("split(A89,""-"")"),"SYSTEM") -> SYSTEM | N89: =IFERROR(__xludf.DUMMYFUNCTION("""COMPUTED_VALUE"""),3.0) -> 3 | O89: =IFERROR(__xludf.DUMMYFUNCTION("""COMPUTED_VALUE"""),8.0) -> 8
A90: ='アセスメント'!B91 -> SYSTEM-4-1 | B90: =criteria!D90 -> メトリクスの計測 | C90: ='アセスメント'!F91 -> FALSE | D90: ='アセスメント'!G91 -> FALSE | E90: ='アセスメント'!H91 -> FALSE | F90: =not(and(C90,D90)) -> TRUE | G90: =or(C90,D90) -> FALSE | H90: =and(G90,not(F90)) -> FALSE | I90: =and(G90,F90) -> FALSE | J90: =if(B90="アンチパターン",true,false) -> FALSE | K90: =if(E90,0.5,if(C90,1,0)) -> 0 | L90: =if(H90,"@" ,if(G90, if(J90,1-K90,K90),"-")) -> - | M90: =IFERROR(__xludf.DUMMYFUNCTION("split(A90,""-"")"),"SYSTEM") -> SYSTEM | N90: =IFERROR(__xludf.DUMMYFUNCTION("""COMPUTED_VALUE"""),4.0) -> 4 | O90: =IFERROR(__xludf.DUMMYFUNCTION("""COMPUTED_VALUE"""),1.0) -> 1
A91: ='アセスメント'!B92 -> SYSTEM-4-2 | B91: =criteria!D91 -> 学習と改善 | C91: ='アセスメント'!F92 -> FALSE | D91: ='アセスメント'!G92 -> FALSE | E91: ='アセスメント'!H92 -> FALSE | F91: =not(and(C91,D91)) -> TRUE | G91: =or(C91,D91) -> FALSE | H91: =and(G91,not(F91)) -> FALSE | I91: =and(G91,F91) -> FALSE | J91: =if(B91="アンチパターン",true,false) -> FALSE | K91: =if(E91,0.5,if(C91,1,0)) -> 0 | L91: =if(H91,"@" ,if(G91, if(J91,1-K91,K91),"-")) -> - | M91: =IFERROR(__xludf.DUMMYFUNCTION("split(A91,""-"")"),"SYSTEM") -> SYSTEM | N91: =IFERROR(__xludf.DUMMYFUNCTION("""COMPUTED_VALUE"""),4.0) -> 4 | O91: =IFERROR(__xludf.DUMMYFUNCTION("""COMPUTED_VALUE"""),2.0) -> 2
A92: ='アセスメント'!B93 -> SYSTEM-4-3 | B92: =criteria!D92 -> プラクティス | C92: ='アセスメント'!F93 -> FALSE | D92: ='アセスメント'!G93 -> FALSE | E92: ='アセスメント'!H93 -> FALSE | F92: =not(and(C92,D92)) -> TRUE | G92: =or(C92,D92) -> FALSE | H92: =and(G92,not(F92)) -> FALSE | I92: =and(G92,F92) -> FALSE | J92: =if(B92="アンチパターン",true,false) -> FALSE | K92: =if(E92,0.5,if(C92,1,0)) -> 0 | L92: =if(H92,"@" ,if(G92, if(J92,1-K92,K92),"-")) -> - | M92: =IFERROR(__xludf.DUMMYFUNCTION("split(A92,""-"")"),"SYSTEM") -> SYSTEM | N92: =IFERROR(__xludf.DUMMYFUNCTION("""COMPUTED_VALUE"""),4.0) -> 4 | O92: =IFERROR(__xludf.DUMMYFUNCTION("""COMPUTED_VALUE"""),3.0) -> 3
A93: ='アセスメント'!B94 -> SYSTEM-4-4 | B93: =criteria!D93 -> プラクティス | C93: ='アセスメント'!F94 -> FALSE | D93: ='アセスメント'!G94 -> FALSE | E93: ='アセスメント'!H94 -> FALSE | F93: =not(and(C93,D93)) -> TRUE | G93: =or(C93,D93) -> FALSE | H93: =and(G93,not(F93)) -> FALSE | I93: =and(G93,F93) -> FALSE | J93: =if(B93="アンチパターン",true,false) -> FALSE | K93: =if(E93,0.5,if(C93,1,0)) -> 0 | L93: =if(H93,"@" ,if(G93, if(J93,1-K93,K93),"-")) -> - | M93: =IFERROR(__xludf.DUMMYFUNCTION("split(A93,""-"")"),"SYSTEM") -> SYSTEM | N93: =IFERROR(__xludf.DUMMYFUNCTION("""COMPUTED_VALUE"""),4.0) -> 4 | O93: =IFERROR(__xludf.DUMMYFUNCTION("""COMPUTED_VALUE"""),4.0) -> 4
A94: ='アセスメント'!B95 -> SYSTEM-4-5 | B94: =criteria!D94 -> プラクティス | C94: ='アセスメント'!F95 -> FALSE | D94: ='アセスメント'!G95 -> FALSE | E94: ='アセスメント'!H95 -> FALSE | F94: =not(and(C94,D94)) -> TRUE | G94: =or(C94,D94) -> FALSE | H94: =and(G94,not(F94)) -> FALSE | I94: =and(G94,F94) -> FALSE | J94: =if(B94="アンチパターン",true,false) -> FALSE | K94: =if(E94,0.5,if(C94,1,0)) -> 0 | L94: =if(H94,"@" ,if(G94, if(J94,1-K94,K94),"-")) -> - | M94: =IFERROR(__xludf.DUMMYFUNCTION("split(A94,""-"")"),"SYSTEM") -> SYSTEM | N94: =IFERROR(__xludf.DUMMYFUNCTION("""COMPUTED_VALUE"""),4.0) -> 4 | O94: =IFERROR(__xludf.DUMMYFUNCTION("""COMPUTED_VALUE"""),5.0) -> 5
A95: ='アセスメント'!B96 -> SYSTEM-4-6 | B95: =criteria!D95 -> アンチパターン | C95: ='アセスメント'!F96 -> FALSE | D95: ='アセスメント'!G96 -> FALSE | E95: ='アセスメント'!H96 -> FALSE | F95: =not(and(C95,D95)) -> TRUE | G95: =or(C95,D95) -> FALSE | H95: =and(G95,not(F95)) -> FALSE | I95: =and(G95,F95) -> FALSE | J95: =if(B95="アンチパターン",true,false) -> TRUE | K95: =if(E95,0.5,if(C95,1,0)) -> 0 | L95: =if(H95,"@" ,if(G95, if(J95,1-K95,K95),"-")) -> - | M95: =IFERROR(__xludf.DUMMYFUNCTION("split(A95,""-"")"),"SYSTEM") -> SYSTEM | N95: =IFERROR(__xludf.DUMMYFUNCTION("""COMPUTED_VALUE"""),4.0) -> 4 | O95: =IFERROR(__xludf.DUMMYFUNCTION("""COMPUTED_VALUE"""),6.0) -> 6
A96: ='アセスメント'!B97 -> SYSTEM-4-7 | B96: =criteria!D96 -> アンチパターン | C96: ='アセスメント'!F97 -> FALSE | D96: ='アセスメント'!G97 -> FALSE | E96: ='アセスメント'!H97 -> FALSE | F96: =not(and(C96,D96)) -> TRUE | G96: =or(C96,D96) -> FALSE | H96: =and(G96,not(F96)) -> FALSE | I96: =and(G96,F96) -> FALSE | J96: =if(B96="アンチパターン",true,false) -> TRUE | K96: =if(E96,0.5,if(C96,1,0)) -> 0 | L96: =if(H96,"@" ,if(G96, if(J96,1-K96,K96),"-")) -> - | M96: =IFERROR(__xludf.DUMMYFUNCTION("split(A96,""-"")"),"SYSTEM") -> SYSTEM | N96: =IFERROR(__xludf.DUMMYFUNCTION("""COMPUTED_VALUE"""),4.0) -> 4 | O96: =IFERROR(__xludf.DUMMYFUNCTION("""COMPUTED_VALUE"""),7.0) -> 7
A97: ='アセスメント'!B98 -> SYSTEM-4-8 | B97: =criteria!D97 -> アンチパターン | C97: ='アセスメント'!F98 -> FALSE | D97: ='アセスメント'!G98 -> FALSE | E97: ='アセスメント'!H98 -> FALSE | F97: =not(and(C97,D97)) -> TRUE | G97: =or(C97,D97) -> FALSE | H97: =and(G97,not(F97)) -> FALSE | I97: =and(G97,F97) -> FALSE | J97: =if(B97="アンチパターン",true,false) -> TRUE | K97: =if(E97,0.5,if(C97,1,0)) -> 0 | L97: =if(H97,"@" ,if(G97, if(J97,1-K97,K97),"-")) -> - | M97: =IFERROR(__xludf.DUMMYFUNCTION("split(A97,""-"")"),"SYSTEM") -> SYSTEM | N97: =IFERROR(__xludf.DUMMYFUNCTION("""COMPUTED_VALUE"""),4.0) -> 4 | O97: =IFERROR(__xludf.DUMMYFUNCTION("""COMPUTED_VALUE"""),8.0) -> 8
A98: ='アセスメント'!B99 -> SYSTEM-5-1 | B98: =criteria!D98 -> メトリクスの計測 | C98: ='アセスメント'!F99 -> FALSE | D98: ='アセスメント'!G99 -> FALSE | E98: ='アセスメント'!H99 -> FALSE | F98: =not(and(C98,D98)) -> TRUE | G98: =or(C98,D98) -> FALSE | H98: =and(G98,not(F98)) -> FALSE | I98: =and(G98,F98) -> FALSE | J98: =if(B98="アンチパターン",true,false) -> FALSE | K98: =if(E98,0.5,if(C98,1,0)) -> 0 | L98: =if(H98,"@" ,if(G98, if(J98,1-K98,K98),"-")) -> - | M98: =IFERROR(__xludf.DUMMYFUNCTION("split(A98,""-"")"),"SYSTEM") -> SYSTEM | N98: =IFERROR(__xludf.DUMMYFUNCTION("""COMPUTED_VALUE"""),5.0) -> 5 | O98: =IFERROR(__xludf.DUMMYFUNCTION("""COMPUTED_VALUE"""),1.0) -> 1
A99: ='アセスメント'!B100 -> SYSTEM-5-2 | B99: =criteria!D99 -> 学習と改善 | C99: ='アセスメント'!F100 -> FALSE | D99: ='アセスメント'!G100 -> FALSE | E99: ='アセスメント'!H100 -> FALSE | F99: =not(and(C99,D99)) -> TRUE | G99: =or(C99,D99) -> FALSE | H99: =and(G99,not(F99)) -> FALSE | I99: =and(G99,F99) -> FALSE | J99: =if(B99="アンチパターン",true,false) -> FALSE | K99: =if(E99,0.5,if(C99,1,0)) -> 0 | L99: =if(H99,"@" ,if(G99, if(J99,1-K99,K99),"-")) -> - | M99: =IFERROR(__xludf.DUMMYFUNCTION("split(A99,""-"")"),"SYSTEM") -> SYSTEM | N99: =IFERROR(__xludf.DUMMYFUNCTION("""COMPUTED_VALUE"""),5.0) -> 5 | O99: =IFERROR(__xludf.DUMMYFUNCTION("""COMPUTED_VALUE"""),2.0) -> 2
A100: ='アセスメント'!B101 -> SYSTEM-5-3 | B100: =criteria!D100 -> プラクティス | C100: ='アセスメント'!F101 -> FALSE | D100: ='アセスメント'!G101 -> FALSE | E100: ='アセスメント'!H101 -> FALSE | F100: =not(and(C100,D100)) -> TRUE | G100: =or(C100,D100) -> FALSE | H100: =and(G100,not(F100)) -> FALSE | I100: =and(G100,F100) -> FALSE | J100: =if(B100="アンチパターン",true,false) -> FALSE | K100: =if(E100,0.5,if(C100,1,0)) -> 0 | L100: =if(H100,"@" ,if(G100, if(J100,1-K100,K100),"-")) -> - | M100: =IFERROR(__xludf.DUMMYFUNCTION("split(A100,""-"")"),"SYSTEM") -> SYSTEM | N100: =IFERROR(__xludf.DUMMYFUNCTION("""COMPUTED_VALUE"""),5.0) -> 5 | O100: =IFERROR(__xludf.DUMMYFUNCTION("""COMPUTED_VALUE"""),3.0) -> 3
...

Sheet criteria
A1: Id | B1: Name | C1: Theme | D1: PointOfView | E1: Category | F1: Criterion
A2: 1 | B2: TEAM-1-1 | C2: チーム | D2: メトリクスの計測 | E2: チーム構成と権限委譲 | F2: システムを開発する１チームの構成人数は、3人以上10人以下か。（ピザ2枚ルール）
A3: 2 | B3: TEAM-1-2 | C3: チーム | D3: 学習と改善 | E3: チーム構成と権限委譲 | F3: ある特定の人物に属人化した仕事を洗い出し、減らしていく仕組みがチームにあるか。
A4: 3 | B4: TEAM-1-3 | C4: チーム | D4: プラクティス | E4: チーム構成と権限委譲 | F4: チームとチームメンバーの権限について、RACI図やデリゲーションポーカーなどによって、可視化され共有されているか。
A5: 4 | B5: TEAM-1-4 | C5: チーム | D5: プラクティス | E5: チーム構成と権限委譲 | F5: チームは価値提供をするのに必要な全職能のメンバーで構成されているか。(フィーチャーチーム)
A6: 5 | B6: TEAM-1-5 | C6: チーム | D6: プラクティス | E6: チーム構成と権限委譲 | F6: チームおよびチームリーダーは、チームのミッションのために必要な外部のリソースを調達するための予算や権限をもっているか。
A7: 6 | B7: TEAM-1-6 | C7: チーム | D7: アンチパターン | E7: チーム構成と権限委譲 | F7: チームという単位は存在するが、メンバーのそれぞれのやっている仕事の内容をよく知らないし、代わりにやることもできない。
A8: 7 | B8: TEAM-1-7 | C8: チーム | D8: アンチパターン | E8: チーム構成と権限委譲 | F8: チームリーダーが複数のチームやプロジェクトを兼務しており、自チームのためにすべての時間を使うことができない。
A9: 8 | B9: TEAM-1-8 | C9: チーム | D9: アンチパターン | E9: チーム構成と権限委譲 | F9: チームリーダーがメンバーに権限委譲できておらず、ボトルネックになっている。
A10: 9 | B10: TEAM-2-1 | C10: チーム | D10: メトリクスの計測 | E10: チームビルディング | F10: チームは少なくとも半年以上継続して存在しているか。
A11: 10 | B11: TEAM-2-2 | C11: チーム | D11: 学習と改善 | E11: チームビルディング | F11: チームは月に一度以上の頻度で仕事のふりかえりをおこなっており、その際にプロジェクト憲章またはインセプションデッキを見返して目的を再確認しているか。
A12: 11 | B12: TEAM-2-3 | C12: チーム | D12: プラクティス | E12: チームビルディング | F12: インセプションデッキまたはプロジェクト憲章を作成し、チームの存在理由についてチーム全員が把握しているか。
A13: 12 | B13: TEAM-2-4 | C13: チーム | D13: プラクティス | E13: チームビルディング | F13: 新しくチームに参画するメンバー用のオンボーディング・デック（チームの一員として働き始めるための、価値観・実務・スキル・相互理解のための明文化されたドキュメント集）が存在するか。
... A329: 328 | B329: CORPORATE-9-8 | C329: コーポレート | D329: アンチパターン | E329: リモートワーク | F329: オンラインのマネジメントに積極的に適応できずに、オフラインに固執するマネージャがいる。

Sheet category
B1: No | C1: =IFERROR(__xludf.DUMMYFUNCTION("unique(criteria!E:E)"),"Category") -> Category | D1: =IFERROR(__xludf.DUMMYFUNCTION("unique(criteria!C:C)"),"Theme") -> Theme
A2: 1 | B2: =mod(A2-1,8)+1 -> 1 | C2: =IFERROR(__xludf.DUMMYFUNCTION("""COMPUTED_VALUE"""),"チーム構成と権限委譲") -> チーム構成と権限委譲 | D2: =IFERROR(__xludf.DUMMYFUNCTION("""COMPUTED_VALUE"""),"チーム") -> チーム
A3: 2 | B3: =mod(A3-1,8)+1 -> 2 | C3: =IFERROR(__xludf.DUMMYFUNCTION("""COMPUTED_VALUE"""),"チームビルディング") -> チームビルディング | D3: =IFERROR(__xludf.DUMMYFUNCTION("""COMPUTED_VALUE"""),"システム") -> システム
A4: 3 | B4: =mod(A4-1,8)+1 -> 3 | C4: =IFERROR(__xludf.DUMMYFUNCTION("""COMPUTED_VALUE"""),"心理的安全性") -> 心理的安全性 | D4: =IFERROR(__xludf.DUMMYFUNCTION("""COMPUTED_VALUE"""),"データ駆動") -> データ駆動
A5: 4 | B5: =mod(A5-1,8)+1 -> 4 | C5: =IFERROR(__xludf.DUMMYFUNCTION("""COMPUTED_VALUE"""),"タスクマネジメント") -> タスクマネジメント | D5: =IFERROR(__xludf.DUMMYFUNCTION("""COMPUTED_VALUE"""),"デザイン思考") -> デザイン思考
A6: 5 | B6: =mod(A6-1,8)+1 -> 5 | C6: =IFERROR(__xludf.DUMMYFUNCTION("""COMPUTED_VALUE"""),"透明性ある目標管理") -> 透明性ある目標管理 | D6: =IFERROR(__xludf.DUMMYFUNCTION("""COMPUTED_VALUE"""),"コーポレート") -> コーポレート
A7: 6 | B7: =mod(A7-1,8)+1 -> 6 | C7: =IFERROR(__xludf.DUMMYFUNCTION("""COMPUTED_VALUE"""),"経験主義的な見積りと計画") -> 経験主義的な見積りと計画
A8: 7 | B8: =mod(A8-1,8)+1 -> 7 | C8: =IFERROR(__xludf.DUMMYFUNCTION("""COMPUTED_VALUE"""),"ふりかえり習慣") -> ふりかえり習慣
A9: 8 | B9: =mod(A9-1,8)+1 -> 8 | C9: =IFERROR(__xludf.DUMMYFUNCTION("""COMPUTED_VALUE"""),"バリューストリーム最適化") -> バリューストリーム最適化
A10: 9 | B10: =mod(A10-1,8)+1 -> 1 | C10: =IFERROR(__xludf.DUMMYFUNCTION("""COMPUTED_VALUE"""),"バージョン管理") -> バージョン管理
A11: 10 | B11: =mod(A11-1,8)+1 -> 2 | C11: =IFERROR(__xludf.DUMMYFUNCTION("""COMPUTED_VALUE"""),"ソースコードの明確さ") -> ソースコードの明確さ
A12: 11 | B12: =mod(A12-1,8)+1 -> 3 | C12: =IFERROR(__xludf.DUMMYFUNCTION("""COMPUTED_VALUE"""),"継続的インテグレーション") -> 継続的インテグレーション
A13: 12 | B13: =mod(A13-1,8)+1 -> 4 | C13: =IFERROR(__xludf.DUMMYFUNCTION("""COMPUTED_VALUE"""),"継続的デプロイ") -> 継続的デプロイ
A14: 13 | B14: =mod(A14-1,8)+1 -> 5 | C14: =IFERROR(__xludf.DUMMYFUNCTION("""COMPUTED_VALUE"""),"API駆動開発") -> API駆動開発
A15: 14 | B15: =mod(A15-1,8)+1 -> 6 | C15: =IFERROR(__xludf.DUMMYFUNCTION("""COMPUTED_VALUE"""),"疎結合アーキテクチャ") -> 疎結合アーキテクチャ
A16: 15 | B16: =mod(A16-1,8)+1 -> 7 | C16: =IFERROR(__xludf.DUMMYFUNCTION("""COMPUTED_VALUE"""),"システムモニタリング") -> システムモニタリング
A17: 16 | B17: =mod(A17-1,8)+1 -> 8 | C17: =IFERROR(__xludf.DUMMYFUNCTION("""COMPUTED_VALUE"""),"セキュリティシフトレフト") -> セキュリティシフトレフト
A18: 17 | B18: =mod(A18-1,8)+1 -> 1 | C18: =IFERROR(__xludf.DUMMYFUNCTION("""COMPUTED_VALUE"""),"顧客接点のデジタル化") -> 顧客接点のデジタル化
A19: 18 | B19: =mod(A19-1,8)+1 -> 2 | C19: =IFERROR(__xludf.DUMMYFUNCTION("""COMPUTED_VALUE"""),"事業活動データの収集") -> 事業活動データの収集
A20: 19 | B20: =mod(A20-1,8)+1 -> 3 | C20: =IFERROR(__xludf.DUMMYFUNCTION("""COMPUTED_VALUE"""),"データ蓄積・分析基盤") -> データ蓄積・分析基盤
A21: 20 | B21: =mod(A21-1,8)+1 -> 4 | C21: =IFERROR(__xludf.DUMMYFUNCTION("""COMPUTED_VALUE"""),"データ処理パイプライン") -> データ処理パイプライン
A22: 21 | B22: =mod(A22-1,8)+1 -> 5 | C22: =IFERROR(__xludf.DUMMYFUNCTION("""COMPUTED_VALUE"""),"データ可視化とリテラシー") -> データ可視化とリテラシー
A23: 22 | B23: =mod(A23-1,8)+1 -> 6 | C23: =IFERROR(__xludf.DUMMYFUNCTION("""COMPUTED_VALUE"""),"機械学習プロジェクト管理") -> 機械学習プロジェクト管理
A24: 23 | B24: =mod(A24-1,8)+1 -> 7 | C24: =IFERROR(__xludf.DUMMYFUNCTION("""COMPUTED_VALUE"""),"マーケティング自動化") -> マーケティング自動化
A25: 24 | B25: =mod(A25-1,8)+1 -> 8 | C25: =IFERROR(__xludf.DUMMYFUNCTION("""COMPUTED_VALUE"""),"自動的な意思決定") -> 自動的な意思決定
A26: 25 | B26: =mod(A26-1,8)+1 -> 1 | C26: =IFERROR(__xludf.DUMMYFUNCTION("""COMPUTED_VALUE"""),"ペルソナの設定") -> ペルソナの設定
A27: 26 | B27: =mod(A27-1,8)+1 -> 2 | C27: =IFERROR(__xludf.DUMMYFUNCTION("""COMPUTED_VALUE"""),"顧客体験") -> 顧客体験
A28: 27 | B28: =mod(A28-1,8)+1 -> 3 | C28: =IFERROR(__xludf.DUMMYFUNCTION("""COMPUTED_VALUE"""),"ユーザーインタビュー") -> ユーザーインタビュー
A29: 28 | B29: =mod(A29-1,8)+1 -> 4 | C29: =IFERROR(__xludf.DUMMYFUNCTION("""COMPUTED_VALUE"""),"デザインシステムの管理") -> デザインシステムの管理
A30: 29 | B30: =mod(A30-1,8)+1 -> 5 | C30: =IFERROR(__xludf.DUMMYFUNCTION("""COMPUTED_VALUE"""),"デザイン組織") -> デザイン組織
A31: 30 | B31: =mod(A31-1,8)+1 -> 6 | C31: =IFERROR(__xludf.DUMMYFUNCTION("""COMPUTED_VALUE"""),"プロトタイピング") -> プロトタイピング
A32: 31 | B32: =mod(A32-1,8)+1 -> 7 | C32: =IFERROR(__xludf.DUMMYFUNCTION("""COMPUTED_VALUE"""),"ユーザビリティテスト") -> ユーザビリティテスト
A33: 32 | B33: =mod(A33-1,8)+1 -> 8 | C33: =IFERROR(__xludf.DUMMYFUNCTION("""COMPUTED_VALUE"""),"プロダクトマネジメント") -> プロダクトマネジメント
A34: 33 | B34: =mod(A34-1,8)+1 -> 1 | C34: =IFERROR(__xludf.DUMMYFUNCTION("""COMPUTED_VALUE"""),"スパン・オブ・コントロール") -> スパン・オブ・コントロール
A35: 34 | B35: =mod(A35-1,8)+1 -> 2 | C35: =IFERROR(__xludf.DUMMYFUNCTION("""COMPUTED_VALUE"""),"開発者環境投資") -> 開発者環境投資
A36: 35 | B36: =mod(A36-1,8)+1 -> 3 | C36: =IFERROR(__xludf.DUMMYFUNCTION("""COMPUTED_VALUE"""),"コミュニケーションツール") -> コミュニケーションツール
A37: 36 | B37: =mod(A37-1,8)+1 -> 4 | C37: =IFERROR(__xludf.DUMMYFUNCTION("""COMPUTED_VALUE"""),"人事制度・育成戦略") -> 人事制度・育成戦略
A38: 37 | B38: =mod(A38-1,8)+1 -> 5 | C38: =IFERROR(__xludf.DUMMYFUNCTION("""COMPUTED_VALUE"""),"デジタル人材採用戦略") -> デジタル人材採用戦略
A39: 38 | B39: =mod(A39-1,8)+1 -> 6 | C39: =IFERROR(__xludf.DUMMYFUNCTION("""COMPUTED_VALUE"""),"モダンなITサービスの活用") -> モダンなITサービスの活用
A40: 39 | B40: =mod(A40-1,8)+1 -> 7 | C40: =IFERROR(__xludf.DUMMYFUNCTION("""COMPUTED_VALUE"""),"経営のデジタルファースト") -> 経営のデジタルファースト
A41: 40 | B41: =mod(A41-1,8)+1 -> 8 | C41: =IFERROR(__xludf.DUMMYFUNCTION("""COMPUTED_VALUE"""),"攻めのセキュリティ") -> 攻めのセキュリティ
A42: 41 | B42: 9 | C42: =IFERROR(__xludf.DUMMYFUNCTION("""COMPUTED_VALUE"""),"リモートワーク") -> リモートワーク

Sheet stats
B1: 平均 | C1: 偏差 | D1: スコア | G1: ポジ | H1: ネガ | I1: BUT | J1: 未記入 | K1: エラー | L1: 合計
A2: チーム | B2: 36.3 | C2: 8.54 | D2: ='可視化'!M3 -> 0 | E2: =D2/64 -> 0 | F2: 2 | G2: =countif(counting!$L2:$L65,"=1") -> 0 | H2: =countif(counting!$L2:$L65,"=0") -> 0 | I2: =countif(counting!$L2:$L65,"=0.5") -> 0 | J2: =countif(counting!$L2:$L65,"-") -> 64 | K2: =countif(counting!$L2:$L65,"@") -> 0 | L2: =sum(G2:K2) -> 64
A3: システム | B3: 33.6 | C3: 9.93 | D3: ='可視化'!M11 -> 0 | E3: =D3/64 -> 0 | F3: =F2+64 -> 66 | G3: =countif(counting!$L66:$L129,"=1") -> 0 | H3: =countif(counting!$L66:$L129,"=0") -> 0 | I3: =countif(counting!$L66:$L129,"=0.5") -> 0 | J3: =countif(counting!$L66:$L129,"-") -> 64 | K3: =countif(counting!$L66:$L129,"@") -> 0 | L3: =sum(G3:K3) -> 64
A4: データ | B4: 28 | C4: 11.14 | D4: ='可視化'!M19 -> 0 | E4: =D4/64 -> 0 | F4: =F3+64 -> 130 | G4: =countif(counting!$L130:$L193,"=1") -> 0 | H4: =countif(counting!$L130:$L193,"=0") -> 0 | I4: =countif(counting!$L130:$L193,"=0.5") -> 0 | J4: =countif(counting!$L130:$L193,"-") -> 64 | K4: =countif(counting!$L130:$L193,"@") -> 0 | L4: =sum(G4:K4) -> 64
A5: デザイン | B5: 29.7 | C5: 10.39 | D5: ='可視化'!M27 -> 0 | E5: =D5/64 -> 0 | F5: =F4+64 -> 194 | G5: =countif(counting!$L194:$L257,"=1") -> 0 | H5: =countif(counting!$L194:$L257,"=0") -> 0 | I5: =countif(counting!$L194:$L257,"=0.5") -> 0 | J5: =countif(counting!$L194:$L257,"-") -> 64 | K5: =countif(counting!$L194:$L257,"@") -> 0 | L5: =sum(G5:K5) -> 64
A6: コーポレート | B6: 38.3 | C6: 8.55 | D6: ='可視化'!M35 -> 0 | E6: =D6/64 -> 0 | F6: =F5+64 -> 258 | G6: =countif(counting!$L258:$L321,"=1") -> 0 | H6: =countif(counting!$L258:$L321,"=0") -> 0 | I6: =countif(counting!$L258:$L321,"=0.5") -> 0 | J6: =countif(counting!$L258:$L321,"-") -> 64 | K6: =countif(counting!$L258:$L321,"@") -> 0 | L6: =sum(G6:K6) -> 64
F7: =F6+64 -> 322

Sheet link
D1: https://dxcriteria.cto-a.org/
B2: CORPORATE-1-1 | C2: a4c62de10b2a4353ab9e60ba496ddf79 | D2: =$D$1&C2 -> https://dxcriteria.cto-a.org/a4c62de10b2a4353ab9e60ba496ddf79
B3: CORPORATE-1-2 | C3: 5e24dc66cdd842cebd4989b42b553211 | D3: =$D$1&C3 -> https://dxcriteria.cto-a.org/5e24dc66cdd842cebd4989b42b553211
B4: CORPORATE-1-3 | C4: 267dea516b68402980c3e137f1d08c3d | D4: =$D$1&C4 -> https://dxcriteria.cto-a.org/267dea516b68402980c3e137f1d08c3d
B5: CORPORATE-1-4 | C5: 5ecead53effa40afbc0f9c5fb59efed5 | D5: =$D$1&C5 -> https://dxcriteria.cto-a.org/5ecead53effa40afbc0f9c5fb59efed5
B6: CORPORATE-1-5 | C6: b444642b20e9497daa7ee0f9316e9e15 | D6: =$D$1&C6 -> https://dxcriteria.cto-a.org/b444642b20e9497daa7ee0f9316e9e15
B7: CORPORATE-1-6 | C7: 8b523a8cd629433885fc4a48298cfae6 | D7: =$D$1&C7 -> https://dxcriteria.cto-a.org/8b523a8cd629433885fc4a48298cfae6
B8: CORPORATE-1-7 | C8: b4ffeacbf51f4f5194bebd7de078652d | D8: =$D$1&C8 -> https://dxcriteria.cto-a.org/b4ffeacbf51f4f5194bebd7de078652d
B9: CORPORATE-1-8 | C9: a140d9ff41c044e388ed17df0f07a01f | D9: =$D$1&C9 -> https://dxcriteria.cto-a.org/a140d9ff41c044e388ed17df0f07a01f
B10: CORPORATE-2-1 | C10: efbaefc371a047b6a556eeabd32fc278 | D10: =$D$1&C10 -> https://dxcriteria.cto-a.org/efbaefc371a047b6a556eeabd32fc278
B11: CORPORATE-2-2 | C11: 670ef336155a4801a2a119f7a3aaf3a0 | D11: =$D$1&C11 -> https://dxcriteria.cto-a.org/670ef336155a4801a2a119f7a3aaf3a0
B12: CORPORATE-2-3 | C12: 37de6aa0a5f94d2b80ed64c6b81514e5 | D12: =$D$1&C12 -> https://dxcriteria.cto-a.org/37de6aa0a5f94d2b80ed64c6b81514e5
B13: CORPORATE-2-4 | C13: 4419b95a0e124b1f846e3075d47f10ad | D13: =$D$1&C13 -> https://dxcriteria.cto-a.org/4419b95a0e124b1f846e3075d47f10ad
... B329: TEAM-8-8 | C329: 0a64434beedb43e6b85ba7fb14af37ad | D329: =$D$1&C329 -> https://dxcriteria.cto-a.org/0a64434beedb43e6b85ba7fb14af37ad
